Workbook

Sheet M-INDEX
A1: 🏛 QUADRUM v1.0: Sistema Integral de Auditoría y Planificación (SIAP-ICPI) · Desarrollado bajo el Protocolo de Integridad Forense ALFARO VIRTUS · GAD Municipal Montecristi · Plan Bicentenario 2023-2027
A2: ◉ INICIO | G2: =HYPERLINK("#'M6-FEDS'!A1","M6") -> M6 | H2: =HYPERLINK("#'M7-PROSP'!A1","M7") -> M7 | I2: =HYPERLINK("#'DATA-POA'!A1","DATA-POA") -> DATA-POA | J2: =HYPERLINK("#'DATA-CNE'!A1","DATA-CNE") -> DATA-CNE | K2: =HYPERLINK("#'DATA-ORG'!A1","DATA-ORG") -> DATA-ORG | L2: =HYPERLINK("#'M-DASHBOARD'!A1","DASH") -> DASH
A3: GAD: | B3: Municipal de Montecristi | D3: PDOT: | E3: Bicentenario 2023-2027
A4: Provincia: | B4: Manabí, Ecuador | D4: Metas: | E4: 20 (muestra estratégica)
A5: Período: | B5: 2023-2027 | D5: Presupuesto: | E5: 32990353
A6: Versión: | B6: SIAP-ICPI v1.0 | D6: Hojas: | E6: 38 módulos activos | F6: 38 módulos activos
A8: # | B8: GRUPO | C8: HOJA | D8: DESCRIPCIÓN | E8: CAPA SIAP-ICPI | F8: IR
A9: 1 | B9: Ejecutiva | C9: =HYPERLINK("#'M-DASHBOARD'!A1","M-DASHBOARD") -> M-DASHBOARD | D9: Panel ejecutivo ICPI global · semáforos · KPIs · ejes PDOT | E9: ❺ SALIDA · Panel ejecutivo | F9: =HYPERLINK("#'M-DASHBOARD'!A1","Ir →") -> Ir →
A10: 2 | B10: Estratégica | C10: =HYPERLINK("#'M-TECH-GAD'!A1","M-TECH-GAD") -> M-TECH-GAD | D10: Configuración institucional GAD Montecristi | E10: ⬡ CONTROL · Configuración GAD | F10: =HYPERLINK("#'M-TECH-GAD'!A1","Ir →") -> Ir →
A11: 3 | B11: Estratégica | C11: =HYPERLINK("#'M-TECH-PARAMS'!A1","M-TECH-PARAMS") -> M-TECH-PARAMS | D11: Parámetros globales · umbrales · constantes del sistema | E11: ⬡ CONTROL · Parámetros | F11: =HYPERLINK("#'M-TECH-PARAMS'!A1","Ir →") -> Ir →
A12: 4 | B12: Auditoría | C12: =HYPERLINK("#'M1-ITME'!A1","M1-ITME") -> M1-ITME | D12: Catálogo documental PDOT · universo n=35 · muestra n=20 | E12: ❶ BASE PDOT · Catálogo | F12: =HYPERLINK("#'M1-ITME'!A1","Ir →") -> Ir →
A13: 5 | B13: Estratégica | C13: =HYPERLINK("#'M2-PDOT'!A1","M2-PDOT") -> M2-PDOT | D13: Base primaria operativa · 20 metas · Pi · Ri · Vi · Ti · Ci · Marco legal COOTAD | E13: ❶ BASE PDOT · Operativa | F13: =HYPERLINK("#'M2-PDOT'!A1","Ir →") -> Ir →
A14: 6 | B14: Estratégica | C14: =HYPERLINK("#'M2-PLAN-Pi'!A1","M2-PLAN-Pi") -> M2-PLAN-Pi | D14: Ponderación Pi · presupuesto PDOT 2023-2027 · ΣPi=1.000 | E14: ❶ BASE PDOT · Ponderación Pi | F14: =HYPERLINK("#'M2-PLAN-Pi'!A1","Ir →") -> Ir →
A15: 7 | B15: Auditoría | C15: =HYPERLINK("#'DATA-TFR'!A1","DATA-TFR") -> DATA-TFR | D15: Tabla de Factores de Relevancia · Ri por competencia COOTAD | E15: ❶ BASE PDOT · Relevancia Ri | F15: =HYPERLINK("#'DATA-TFR'!A1","Ir →") -> Ir →
A16: 8 | B16: Auditoría | C16: =HYPERLINK("#'M3-MAO'!A1","M3-MAO") -> M3-MAO | D16: Matriz de Atribución Orgánica · factor Ci por Dirección GAD | E16: ❶ BASE PDOT · Atribución Ci | F16: =HYPERLINK("#'M3-MAO'!A1","Ir →") -> Ir →
A17: 9 | B17: Cálculo | C17: =HYPERLINK("#'DATA-SSC'!A1","DATA-SSC") -> DATA-SSC | D17: Subíndice Social Complementario · escalabilidad institucional | E17: ❶ BASE PDOT · Escalabilidad | F17: =HYPERLINK("#'DATA-SSC'!A1","Ir →") -> Ir →
A18: 10 | B18: Auditoría | C18: =HYPERLINK("#'M4-AUDIT'!A1","M4-AUDIT") -> M4-AUDIT | D18: Matriz Auditoría Documental · Vi · Ei · Ti · n=20 metas PDOT | E18: ❷ AUDITORÍA · MAD | F18: =HYPERLINK("#'M4-AUDIT'!A1","Ir →") -> Ir →
A19: 11 | B19: Auditoría | C19: =HYPERLINK("#'DATA-MEC'!A1","DATA-MEC") -> DATA-MEC | D19: Matriz de Evidencia y Cadena de Custodia (§3.4.3 SIAP-ICPI) | E19: ❷ AUDITORÍA · Cadena custodia | F19: =HYPERLINK("#'DATA-MEC'!A1","Ir →") -> Ir →
A20: 12 | B20: Ingesta | C20: =HYPERLINK("#'DATA-CED'!A1","DATA-CED") -> DATA-CED | D20: Cédulas Presupuestarias eSIGEF · Ti = Devengado ÷ Codificado | E20: ❖ INGESTA · Ejecución Ti | F20: =HYPERLINK("#'DATA-CED'!A1","Ir →") -> Ir →
A21: 13 | B21: Ingesta | C21: =HYPERLINK("#'DATA-POA'!A1","DATA-POA") -> DATA-POA | D21: Alineación PAC/POA 2023-2025 · brechas de activación por meta | E21: ❖ INGESTA · POA | F21: =HYPERLINK("#'DATA-POA'!A1","Ir →") -> Ir →
A22: 14 | B22: Ingesta | C22: =HYPERLINK("#'DATA-PAC'!A1","DATA-PAC") -> DATA-PAC | D22: Plan Anual de Contratación · fuente SERCOP · por meta PDOT | E22: ❖ INGESTA · PAC SERCOP | F22: =HYPERLINK("#'DATA-PAC'!A1","Ir →") -> Ir →
A23: 15 | B23: Cálculo | C23: =HYPERLINK("#'M5-ICPI'!A1","M5-ICPI") -> M5-ICPI | D23: Motor Central ICPI = Σ(Pi×Ri×Vi×Ei×Ti×Ci) ÷ Σ(Pi×Ri) | E23: ❸ CÁLCULO · Motor ICPI | F23: =HYPERLINK("#'M5-ICPI'!A1","Ir →") -> Ir →
A24: 16 | B24: Cálculo | C24: =HYPERLINK("#'DATA-RESULTADOS'!A1","DATA-RESULTADOS") -> DATA-RESULTADOS | D24: Resultados consolidados ICPI · semáforo AVEP · brecha vs 2027 · Dashboard resumen PDOT | E24: ❸ CÁLCULO · Resultado ICPI + Dashboard | F24: =HYPERLINK("#'DATA-RESULTADOS'!A1","Ir →") -> Ir →
A25: 17 | B25: Cálculo | C25: =HYPERLINK("#'SUPPORT-INTERP'!A1","SUPPORT-INTERP") -> SUPPORT-INTERP | D25: Interpretación cualitativa · escala AVEP 5 niveles | E25: ❸ CÁLCULO · Interpretación AVEP | F25: =HYPERLINK("#'SUPPORT-INTERP'!A1","Ir →") -> Ir →
A26: 18 | B26: Cálculo | C26: =HYPERLINK("#'VALID-CST'!A1","VALID-CST") -> VALID-CST | D26: Validación de consistencia melógica y flujos de datos | E26: ❹ VALIDACIÓN · Consistencia | F26: =HYPERLINK("#'VALID-CST'!A1","Ir →") -> Ir →
A27: 19 | B27: Cálculo | C27: =HYPERLINK("#'M7-PROSP'!A1","M7-PROSP") -> M7-PROSP | D27: Análisis analítico cruzado de variables SIAP-ICPI | E27: ❹ VALIDACIÓN · Análisis cruzado | F27: =HYPERLINK("#'M7-PROSP'!A1","Ir →") -> Ir →
A28: 20 | B28: Cálculo | C28: =HYPERLINK("#'VALID-MVCI'!A1","VALID-MVCI") -> VALID-MVCI | D28: Matriz de Verificación de Coherencia Interna · 20/20 | E28: ❹ VALIDACIÓN · Coherencia interna | F28: =HYPERLINK("#'VALID-MVCI'!A1","Ir →") -> Ir →
A29: 21 | B29: Cálculo | C29: =HYPERLINK("#'DATA-EJES'!A1","DATA-EJES") -> DATA-EJES | D29: ICPI desagregado por eje estratégico PDOT · 5 ejes | E29: ❹ VALIDACIÓN · ICPI por eje | F29: =HYPERLINK("#'DATA-EJES'!A1","Ir →") -> Ir →
A30: 22 | B30: Cálculo | C30: =HYPERLINK("#'VALID-SENS'!A1","VALID-SENS") -> VALID-SENS | D30: Análisis de sensibilidad · Vi=0→Vi=1 · Δ máx. +20.6pp | E30: ❹ VALIDACIÓN · Sensibilidad | F30: =HYPERLINK("#'VALID-SENS'!A1","Ir →") -> Ir →
A31: 23 | B31: Ejecutiva | C31: =HYPERLINK("#'DATA-BRECHA'!A1","DATA-BRECHA") -> DATA-BRECHA | D31: Análisis de Brecha Programática · ICPI vs Meta PDOT 2027 | E31: ❖ EJECUTIVA · Brecha ICPI | F31: =HYPERLINK("#'DATA-BRECHA'!A1","Ir →") -> Ir →
A32: 24 | B32: Ejecutiva | C32: =HYPERLINK("#'DATA-ORG'!A1","DATA-ORG") -> DATA-ORG | D32: Estructura Orgánica GAD · auditoría Ci vs Estatuto Orgánico | E32: ❖ EJECUTIVA · Estructura orgánica | F32: =HYPERLINK("#'DATA-ORG'!A1","Ir →") -> Ir →
A33: 25 | B33: Cálculo | C33: =HYPERLINK("#'M6-FEDS'!A1","M6-FEDS") -> M6-FEDS | D33: Estrategia Desarrollo Sostenible · IED servidores públicos | E33: ❖ CÁLCULO · IED desarrollo | F33: =HYPERLINK("#'M6-FEDS'!A1","Ir →") -> Ir →
A34: 26 | B34: Ejecutiva | C34: =HYPERLINK("#'SUPPORT-EVALDIR'!A1","SUPPORT-EVALDIR") -> SUPPORT-EVALDIR | D34: Evaluación semestral directivos LOSEP · escala 5 niveles | E34: ❻ EVALUACIÓN · Directivos | F34: =HYPERLINK("#'SUPPORT-EVALDIR'!A1","Ir →") -> Ir →
A35: 27 | B35: Ejecutiva | C35: =HYPERLINK("#'SUPPORT-SEM'!A1","SUPPORT-SEM") -> SUPPORT-SEM | D35: Cortes semestrales S1/S2 · SIITH-MDT · 12 directivos GAD | E35: ❻ EVALUACIÓN · Cortes SIITH | F35: =HYPERLINK("#'SUPPORT-SEM'!A1","Ir →") -> Ir →
A36: 28 | B36: Cálculo | C36: =HYPERLINK("#'DATA-ITAM'!A1","DATA-ITAM") -> DATA-ITAM | D36: Índice Transparencia Activa Municipal · LOTAIP Art.7 · 84% | E36: ⬡ TRANSVERSAL · ITAM | F36: =HYPERLINK("#'DATA-ITAM'!A1","Ir →") -> Ir →
A37: 29 | B37: Ejecutiva | C37: =HYPERLINK("#'SUPPORT-SIL'!A1","SUPPORT-SIL") -> SUPPORT-SIL | D37: Exportación SIL SIGAD · portal Planifica Ecuador · mensual día 5 | E37: ❼ SALIDA/SIL · Exportación | F37: =HYPERLINK("#'SUPPORT-SIL'!A1","Ir →") -> Ir →
A38: 30 | B38: Ejecutiva | C38: =HYPERLINK("#'SUPPORT-ALERT'!A1","SUPPORT-ALERT") -> SUPPORT-ALERT | D38: Alertas automáticas · 14 alertas · 4 niveles COOTAD + LOSEP | E38: ❼ SALIDA/SIL · Alertas | F38: =HYPERLINK("#'SUPPORT-ALERT'!A1","Ir →") -> Ir →
A39: 31 | B39: Auditoría | C39: =HYPERLINK("#'VALID-VER'!A1","VALID-VER") -> VALID-VER | D39: Matriz de Control Documental · 8 fuentes verificadas por meta | E39: ❷ AUDITORÍA · Control documental | F39: =HYPERLINK("#'VALID-VER'!A1","Ir →") -> Ir →
A40: 32 | B40: Ingesta | C40: =HYPERLINK("#'DATA-CPCCS'!A1","DATA-CPCCS") -> DATA-CPCCS | D40: Anexo CPCCS · participación ciudadana por meta PDOT | E40: ⬡ TRANSVERSAL · CPCCS | F40: =HYPERLINK("#'DATA-CPCCS'!A1","Ir →") -> Ir →
A41: 33 | B41: Ingesta | C41: =HYPERLINK("#'DATA-CNE'!A1","DATA-CNE") -> DATA-CNE | D41: Anexo CNE · evidencias procesos electorales por meta PDOT | E41: ⬡ TRANSVERSAL · CNE | F41: =HYPERLINK("#'DATA-CNE'!A1","Ir →") -> Ir →
A42: 34 | B42: Ingesta | C42: =HYPERLINK("#'DATA-SIGAD'!A1","DATA-SIGAD") -> DATA-SIGAD | D42: Exportación y validación SIGAD nacional por meta PDOT | E42: ⬡ TRANSVERSAL · SIGAD | F42: =HYPERLINK("#'DATA-SIGAD'!A1","Ir →") -> Ir →
A43: 35 | B43: Estratégica | C43: =HYPERLINK("#'M-TECH-VARS'!A1","M-TECH-VARS") -> M-TECH-VARS | D43: Variables del modelo Pi·Ri·Vi·Ei·Ti·Ci · definición · rango · §3.5 | E43: ⬡ CONTROL · Variables modelo | F43: =HYPERLINK("#'M-TECH-VARS'!A1","Ir →") -> Ir →
A44: 36 | B44: Ingesta | C44: =HYPERLINK("#'DATA-MONIT'!A1","DATA-MONIT") -> DATA-MONIT | D44: Monitoreo PDOT · seguimiento por meta · evolución 2023-2027 | E44: ❖ INGESTA · Monitoreo PDOT | F44: =HYPERLINK("#'DATA-MONIT'!A1","Ir →") -> Ir →
A45: 37 | B45: Documentación | C45: =HYPERLINK("#'M-DOCS'!A1","M-DOCS") -> M-DOCS | D45: Marco Metodológico fusionado: Manual · Glosario · Limitaciones · Metadatos · Trazabilidad | E45: ⬡ DOCUMENTACIÓN · Marco consolidado | F45: =HYPERLINK("#'M-DOCS'!A1","Ir →") -> Ir →
A46: 38 | B46: Estratégica | C46: =HYPERLINK("#'M-INDEX'!A1","M-INDEX") -> M-INDEX | D46: Índice maestro de navegación · 38 módulos activos · acceso rápido | E46: ⬡ CONTROL · Índice navegación | F46: =HYPERLINK("#'M-INDEX'!A1","Ir →") -> Ir →

Sheet M-DASHBOARD
A1: QUADRUM v1.0: Sistema Integral de Auditoría y Planificación (SIAP-ICPI) · Desarrollado bajo el Protocolo de Integridad Forense ALFARO VIRTUS · GAD Municipal Montecristi
A2: =HYPERLINK("#'M-INDEX'!A1","⌂ INDICE") -> ⌂ INDICE | F2: =HYPERLINK("#'M5-ICPI'!A1","M5") -> M5 | G2: =HYPERLINK("#'M6-FEDS'!A1","M6") -> M6 | H2: =HYPERLINK("#'M7-PROSP'!A1","M7") -> M7 | I2: =HYPERLINK("#'DATA-POA'!A1","DATA-POA") -> DATA-POA | J2: =HYPERLINK("#'DATA-CNE'!A1","DATA-CNE") -> DATA-CNE | K2: =HYPERLINK("#'DATA-ORG'!A1","DATA-ORG") -> DATA-ORG | L2: =HYPERLINK("#'M-DASHBOARD'!A1","DASH") -> DASH
A3: ="Capa: Documentación > Panel Ejecutivo ICPI · ICPI Global = "&TEXT('M5-ICPI'!G29,"0,00")&"% · "&'DATA-RESULTADOS'!B8&" · Actualización: mensual" -> Capa: Documentación > Panel Ejecutivo ICPI · ICPI Global = 38,28% · Transición Crítica 🟡 · Actualización: mensual | F3: ICM Oficial SIGAD (%) | G3: 92.25 | H3: 100
A4: ◉ ICPI GLOBAL — Principio de Invariabilidad Algorítmica | C4: =TEXT('M5-ICPI'!G29,"0,00")&" %" -> 38,28 % | D4: =IF('M5-ICPI'!G29>=85,"🔵 EXCELENCIA",IF('M5-ICPI'!G29>=70,"🟢 GESTIÓN POR MANDATO",IF('M5-ICPI'!G29>=40,"🟠 TRANSICIÓN CRÍTICA",IF('M5-ICPI'!G29>=20,"🔴 GESTIÓN POR OCURRENCIA","⬛ RUPTURA TOTAL")))) -> 🔴 GESTIÓN POR OCURRENCIA | E4: ="Brecha vs ICM: "&TEXT('M5-ICPI'!G29-92.25,"0,00")&" pp · Meta 2027: 92,5%" -> Brecha vs ICM: -53,97 pp · Meta 2027: 92,5% | F4: Ejecución completa Vi=1,Ti=1 (n) | G4: =COUNTIFS('M5-ICPI'!E5:E24,1,'M5-ICPI'!F5:F24,">="&0.8) -> 5 | H4: 20
A5: ◉ INDICADORES CLAVE · KPIs del Sistema SIAP-ICPI · Base: PDOT Plan Bicentenario 2023-2027 | F5: Metas con Evidencia Vi=1 (%) | G5: =COUNTIF('M5-ICPI'!E5:E24,1)/20*100 -> 75 | H5: 100
A6: KPI | B6: VALOR ACTUAL | C6: BARRA DE AVANCE | E6: CONTEXTO / FUENTE | F6: 🌐 ITAM Global — Transp. (%) | G6: ='DATA-ITAM'!B6*100 -> 78 | H6: 100
A7: ICPI GLOBAL (%) | B7: =TEXT('M5-ICPI'!G29,"0,00")&" %" -> 38,28 % | C7: =REPT("█",ROUND('M5-ICPI'!G29/5,0))&REPT("░",20-ROUND('M5-ICPI'!G29/5,0))&" "&TEXT('M5-ICPI'!G29,"0,00")&" %" -> ████████░░░░░░░░░░░░ 38,28 % | E7: ="Meta: 92,5 % · "&IF('M5-ICPI'!G29>=85,"🔵 EXCELENCIA",IF('M5-ICPI'!G29>=70,"🟢 GESTIÓN POR MANDATO",IF('M5-ICPI'!G29>=40,"🟠 TRANSICIÓN CRÍTICA",IF('M5-ICPI'!G29>=20,"🔴 GESTIÓN POR OCURRENCIA","⬛ RUPTURA TOTAL"))))&" · Motor ICPI" -> Meta: 92,5 % · 🔴 GESTIÓN POR OCURRENCIA · Motor ICPI | F7: Brecha de Integridad ICPI vs ICM (pp) | G7: =ABS('M5-ICPI'!G29-92.25) -> 53.966986 | H7: 100
A8: Semáforo ICPI | B8: =IF('M5-ICPI'!G29>=85,"🔵 EXCELENCIA",IF('M5-ICPI'!G29>=70,"🟢 GESTIÓN POR MANDATO",IF('M5-ICPI'!G29>=40,"🟠 TRANSICIÓN CRÍTICA",IF('M5-ICPI'!G29>=20,"🔴 GESTIÓN POR OCURRENCIA","⬛ RUPTURA TOTAL")))) -> 🔴 GESTIÓN POR OCURRENCIA | C8: ="Nivel "&IF('M5-ICPI'!G29>=85,"1",IF('M5-ICPI'!G29>=70,"2",IF('M5-ICPI'!G29>=40,"3",IF('M5-ICPI'!G29>=20,"4","5"))))&" de 5 — §3.7 SIAP-ICPI" -> Nivel 4 de 5 — §3.7 SIAP-ICPI | E8: Ver INTERP para tabla de rangos
A9: ICM Oficial SIGAD (%) | B9: =TEXT(92.25,"0,00")&" %" -> 92,25 % | C9: =REPT("█",ROUND(92.25/5,0))&REPT("░",20-ROUND(92.25/5,0))&" "&TEXT(92.25,"0,00")&" %" -> ██████████████████░░ 92,25 % | E9: ="Mandato OK · SIGAD · Brecha integridad: "&TEXT('M5-ICPI'!G29-92.25,"0,00")&" pp" -> Mandato OK · SIGAD · Brecha integridad: -53,97 pp
A10: Brecha de Integridad (pp) | B10: =TEXT('M5-ICPI'!G29-92.25,"0,00")&" pp" -> -53,97 pp | C10: =REPT("█",ROUND(ABS('M5-ICPI'!G29-92.25)/5,0))&REPT("░",20-ROUND(ABS('M5-ICPI'!G29-92.25)/5,0))&" "&TEXT('M5-ICPI'!G29-92.25,"0,00")&" pp" -> ███████████░░░░░░░░░ -53,97 pp | E10: Brecha ICPI vs ICM · Ver BI · Prioridad máxima | F10: Eje | G10: ICPI (%)
A11: Metas con Evidencia (Vi=1) | B11: =COUNTIF('M5-ICPI'!E5:E24,1)&" / 20 ("&TEXT(COUNTIF('M5-ICPI'!E5:E24,1)/20,"0%")&")" -> 15 / 20 (75%) | C11: =REPT("█",ROUND(COUNTIF('M5-ICPI'!E5:E24,1),0))&REPT("░",20-ROUND(COUNTIF('M5-ICPI'!E5:E24,1),0))&" "&COUNTIF('M5-ICPI'!E5:E24,1)&" / 20" -> ███████████████░░░░░ 15 / 20 | E11: Vi=1 verificadas documentalmente · Ver MAD | F11: TERRITORIAL | G11: ='DATA-EJES'!D4 -> 25.761436
A12: Ejecución Completa (Vi=1,Ti=1) | B12: =COUNTIFS('M5-ICPI'!E5:E24,1,'M5-ICPI'!F5:F24,">="&0.8)&" / 20 ("&TEXT(COUNTIFS('M5-ICPI'!E5:E24,1,'M5-ICPI'!F5:F24,">="&0.8)/20,"0%")&")" -> 5 / 20 (25%) | C12: =REPT("█",COUNTIFS('M5-ICPI'!E5:E24,1,'M5-ICPI'!F5:F24,">="&0.8))&REPT("░",20-COUNTIFS('M5-ICPI'!E5:E24,1,'M5-ICPI'!F5:F24,">="&0.8))&" "&COUNTIFS('M5-ICPI'!E5:E24,1,'M5-ICPI'!F5:F24,">="&0.8)&" / 20" -> █████░░░░░░░░░░░░░░░ 5 / 20 | E12: Vi=1 y Ti≥80% · Ver MAD · Prioridad POA 2025 | F12: SOCIAL | G12: ='DATA-EJES'!D5 -> 51.686758
A13: 🌐 ITAM — Transparencia Activa | B13: =TEXT('DATA-ITAM'!B6*100,"0,0")&" %" -> 78,0 % | C13: =REPT("█",ROUND('DATA-ITAM'!B6*20,0))&REPT("░",20-ROUND('DATA-ITAM'!B6*20,0))&" "&TEXT('DATA-ITAM'!B6*100,"0,0")&" %" -> ████████████████░░░░ 78,0 % | E13: LOTAIP Art.7 · Ver ITAM · Meta: 100% | F13: AMBIENTAL | G13: ='DATA-EJES'!D6 -> 44.931664
A14: ⊕ ICPI POR EJE ESTRATÉGICO · Distribución del desempeño por sistema PDOT · 5 ejes Plan Bicentenario 2023-2027 | F14: ECONÓMICO | G14: ='DATA-EJES'!D7 -> 70
A15: EJE ESTRATÉGICO | B15: ICPI (%) | C15: BARRA DE AVANCE | D15: PESO EN MUESTRA | E15: ESTADO | F15: INSTITUCIONAL | G15: ='DATA-EJES'!D8 -> 60.15129
A16: TERRITORIAL | B16: =TEXT('DATA-EJES'!D4,"0,0")&" %" -> 25,8 % | C16: =REPT("█",ROUND('DATA-EJES'!D4/5,0))&REPT("░",20-ROUND('DATA-EJES'!D4/5,0))&" "&TEXT('DATA-EJES'!D4,"0,0")&" %" -> █████░░░░░░░░░░░░░░░ 25,8 % | D16: =TEXT(SUMIF('M5-ICPI'!B5:B24,"TERRITORIAL",'M5-ICPI'!H5:H24)/SUMIF('M5-ICPI'!H5:H24,">0",'M5-ICPI'!H5:H24),"0,0%") -> 0,0% | E16: =IF('DATA-EJES'!D4>=85,"🔵 EXCELENCIA",IF('DATA-EJES'!D4>=70,"🟢 GESTIÓN POR MANDATO",IF('DATA-EJES'!D4>=40,"🟠 TRANSICIÓN CRÍTICA",IF('DATA-EJES'!D4>=20,"🔴 GESTIÓN POR OCURRENCIA","⬛ RUPTURA TOTAL")))) -> 🔴 GESTIÓN POR OCURRENCIA
A17: SOCIAL | B17: =TEXT('DATA-EJES'!D5,"0,0")&" %" -> 51,7 % | C17: =REPT("█",ROUND('DATA-EJES'!D5/5,0))&REPT("░",20-ROUND('DATA-EJES'!D5/5,0))&" "&TEXT('DATA-EJES'!D5,"0,0")&" %" -> ██████████░░░░░░░░░░ 51,7 % | D17: =TEXT(SUMIF('M5-ICPI'!B5:B24,"SOCIAL",'M5-ICPI'!H5:H24)/SUMIF('M5-ICPI'!H5:H24,">0",'M5-ICPI'!H5:H24),"0,0%") -> 0,0% | E17: =IF('DATA-EJES'!D5>=85,"🔵 EXCELENCIA",IF('DATA-EJES'!D5>=70,"🟢 GESTIÓN POR MANDATO",IF('DATA-EJES'!D5>=40,"🟠 TRANSICIÓN CRÍTICA",IF('DATA-EJES'!D5>=20,"🔴 GESTIÓN POR OCURRENCIA","⬛ RUPTURA TOTAL")))) -> 🟠 TRANSICIÓN CRÍTICA | F17: Estado | G17: n
A18: AMBIENTAL | B18: =TEXT('DATA-EJES'!D6,"0,0")&" %" -> 44,9 % | C18: =REPT("█",ROUND('DATA-EJES'!D6/5,0))&REPT("░",20-ROUND('DATA-EJES'!D6/5,0))&" "&TEXT('DATA-EJES'!D6,"0,0")&" %" -> █████████░░░░░░░░░░░ 44,9 % | D18: =TEXT(SUMIF('M5-ICPI'!B5:B24,"AMBIENTAL",'M5-ICPI'!H5:H24)/SUMIF('M5-ICPI'!H5:H24,">0",'M5-ICPI'!H5:H24),"0,0%") -> 17,8% | E18: =IF('DATA-EJES'!D6>=85,"🔵 EXCELENCIA",IF('DATA-EJES'!D6>=70,"🟢 GESTIÓN POR MANDATO",IF('DATA-EJES'!D6>=40,"🟠 TRANSICIÓN CRÍTICA",IF('DATA-EJES'!D6>=20,"🔴 GESTIÓN POR OCURRENCIA","⬛ RUPTURA TOTAL")))) -> 🟠 TRANSICIÓN CRÍTICA | F18: ✅ Evidencia completa | G18: =COUNTIFS('M4-AUDIT'!X5:X24,1,'M4-AUDIT'!Y5:Y24,">="&0.8) -> 1 | H18: =COUNTIFS('M4-AUDIT'!X5:X24,1,'M4-AUDIT'!Y5:Y24,">="&0.99) -> 0
A19: ECONÓMICO | B19: =TEXT('DATA-EJES'!D7,"0,0")&" %" -> 70,0 % | C19: =REPT("█",ROUND('DATA-EJES'!D7/5,0))&REPT("░",20-ROUND('DATA-EJES'!D7/5,0))&" "&TEXT('DATA-EJES'!D7,"0,0")&" %" -> ██████████████░░░░░░ 70,0 % | D19: =TEXT(SUMIF('M5-ICPI'!B5:B24,"ECONÓMICO",'M5-ICPI'!H5:H24)/SUMIF('M5-ICPI'!H5:H24,">0",'M5-ICPI'!H5:H24),"0,0%") -> 0,0% | E19: =IF('DATA-EJES'!D7>=85,"🔵 EXCELENCIA",IF('DATA-EJES'!D7>=70,"🟢 GESTIÓN POR MANDATO",IF('DATA-EJES'!D7>=40,"🟠 TRANSICIÓN CRÍTICA",IF('DATA-EJES'!D7>=20,"🔴 GESTIÓN POR OCURRENCIA","⬛ RUPTURA TOTAL")))) -> 🟢 GESTIÓN POR MANDATO | F19: ⚠️ Evidencia parcial | G19: =COUNTIF('M4-AUDIT'!X5:X24,1)-COUNTIFS('M4-AUDIT'!X5:X24,1,'M4-AUDIT'!Y5:Y24,">="&0.8) -> 7 | H19: =COUNTIF('M4-AUDIT'!X5:X24,1)-COUNTIFS('M4-AUDIT'!X5:X24,1,'M4-AUDIT'!Y5:Y24,">="&0.99) -> 8
A20: INSTITUCIONAL | B20: =TEXT('DATA-EJES'!D8,"0,0")&" %" -> 60,2 % | C20: =REPT("█",ROUND('DATA-EJES'!D8/5,0))&REPT("░",20-ROUND('DATA-EJES'!D8/5,0))&" "&TEXT('DATA-EJES'!D8,"0,0")&" %" -> ████████████░░░░░░░░ 60,2 % | D20: =TEXT(SUMIF('M5-ICPI'!B5:B24,"INSTITUCIONAL",'M5-ICPI'!H5:H24)/SUMIF('M5-ICPI'!H5:H24,">0",'M5-ICPI'!H5:H24),"0,0%") -> 0,0% | E20: =IF('DATA-EJES'!D8>=85,"🔵 EXCELENCIA",IF('DATA-EJES'!D8>=70,"🟢 GESTIÓN POR MANDATO",IF('DATA-EJES'!D8>=40,"🟠 TRANSICIÓN CRÍTICA",IF('DATA-EJES'!D8>=20,"🔴 GESTIÓN POR OCURRENCIA","⬛ RUPTURA TOTAL")))) -> 🟠 TRANSICIÓN CRÍTICA | F20: ❌ Sin evidencia | G20: =20-COUNTIF('M4-AUDIT'!X5:X24,1) -> 12 | H20: =20-COUNTIF('M4-AUDIT'!X5:X24,1) -> 12
A21: △ TOP 5 METAS CRÍTICAS · Mayores brechas de integridad ICPI · Vi=0 o Ti<50% · Prioridad de acción inmediata POA 2025
A23: Nº | B23: COD-META PDOT | C23: BRECHA (pp) | D23: DESCRIPCIÓN / ÁREA CRÍTICA | E23: ACCIÓN REQUERIDA
A24: 1 | B24: PDOT.SC.OE2.M1.01 | C24: −100 pp | D24: Centro de Salud Tipo C · Ri=1.5 · Vi=0 | E24: Convenio MSP urgente · SERCOP · POA 2025
A25: 2 | B25: PDOT.SC.OE2.M3.01 | C25: −100 pp | D25: Unidad Médica Móvil · Ri=1.5 · Vi=0 | E25: Registro vehicular SERCOP · Contrato formal
A26: 3 | B26: PDOT.SC.PI.M5.01 | C26: −100 pp | D26: Central Monitoreo/Cámaras · Ri=1.0 · Vi=0 | E26: Proceso contratación · Especificaciones técnicas
A27: 4 | B27: PDOT.SC.OE2.M4.01 | C27: −90 pp | D27: Guarderías Nocturnas · Ri=1.0 · Ti=0 | E27: Convenio MIES · CIBV · Reformular POA
A28: 5 | B28: PDOT.AS.OE1.M2.02 | C28: −75 pp | D28: Nuevo Camal Municipal · Ri=1.0 · Ti=0,25 | E28: Activar proceso SERCOP · Asignación presupuesto
A30: ≡ ESTADO DOCUMENTAL · Distribución de evidencia forense · n=20 metas PDOT · Ver MAD · MEC · MUAF
A31: ESTADO DOCUMENTAL | B31: n ACTUAL | C31: n META | D31: COBERTURA
A32: ✅ Evidencia completa (Vi=1 · Ti≥80%) | B32: =COUNTIFS('M5-ICPI'!E5:E24,1,'M5-ICPI'!F5:F24,">="&0.8) -> 5 | C32: 20 | D32: ="Ejección plena · "&TEXT(COUNTIFS('M4-AUDIT'!X5:X24,1,'M4-AUDIT'!Y5:Y24,">="&0.8)/20,"0,0%")&" de la muestra · Ver MAD" -> Ejección plena · 5,0% de la muestra · Ver MAD
A33: ⚠️ Evidencia parcial (Vi=1 · Ti<80%) | B33: =COUNTIF('M5-ICPI'!E5:E24,1)-COUNTIFS('M5-ICPI'!E5:E24,1,'M5-ICPI'!F5:F24,">="&0.8) -> 10 | C33: 0 | D33: ="Avance parcial · "&TEXT((COUNTIF('M4-AUDIT'!X5:X24,1)-COUNTIFS('M4-AUDIT'!X5:X24,1,'M4-AUDIT'!Y5:Y24,">="&0.8))/20,"0,0%")&" · Ti pendiente · Ver CEDULAS" -> Avance parcial · 35,0% · Ti pendiente · Ver CEDULAS
A34: ❌ Sin evidencia (Vi=0) | B34: =20-COUNTIF('M5-ICPI'!E5:E24,1) -> 5 | C34: 0 | D34: ="Sin trazabilidad · "&TEXT((20-COUNTIF('M4-AUDIT'!X5:X24,1))/20,"0,0%")&" · Riesgo ICPI · Ver VERIF" -> Sin trazabilidad · 60,0% · Riesgo ICPI · Ver VERIF
A36: ="◈ SIAP-ICPI · GAD Municipal Montecristi · ICPI = "&TEXT('M5-ICPI'!G29,"0,00")&" % · "&IF('M5-ICPI'!G29>=85,"🔵 EXCELENCIA",IF('M5-ICPI'!G29>=70,"🟢 GESTIÓN POR MANDATO",IF('M5-ICPI'!G29>=40,"🟠 TRANSICIÓN CRÍTICA",IF('M5-ICPI'!G29>=20,"🔴 GESTIÓN POR OCURRENCIA","⬛ RUPTURA TOTAL"))))&" · Meta 2027: 100 % · Brecha: "&TEXT('M5-ICPI'!G29-100,"0,00")&" pp" -> ◈ SIAP-ICPI · GAD Municipal Montecristi · ICPI = 38,28 % · 🔴 GESTIÓN POR OCURRENCIA · Meta 2027: 100 % · Brecha: -61,72 pp
A39: 📊 PANEL 5 — CUMPLIMIENTO METAS PDOT POR AÑO · Evolución 2023-2027 · Fuente: Q-SIL + F-EDS + L-PDOT
A40: AÑO | B40: METAS PROGRAMADAS | C40: METAS EJECUTADAS (Ti≥80%) | D40: % CUMPLIMIENTO | E40: ESTADO
A41: 2023 | B41: 12 | C41: 6 | D41: =IF(B41=0,0,C41/B41) -> 0.5 | E41: =IF(C41=0,"Sin ejecución — "&B41&" metas programadas",IF(D41>=1,"✅ Completado — "&C41&"/"&B41&" metas al 100%",IF(D41>=0.8,"🟢 En buen ritmo — "&C41&"/"&B41&" (±80%)",IF(D41>=0.5,"En curso — "&TEXT(D41,"0%")&" metas completadas","🔴 Rezago — "&TEXT(D41,"0%")&" · Requiere acción")))) -> En curso — 50% metas completadas
A42: 2024 | B42: 16 | C42: 8 | D42: =IF(B42=0,0,C42/B42) -> 0.5 | E42: =IF(C42=0,"Sin ejecución — "&B42&" metas programadas",IF(D42>=1,"✅ Completado — "&C42&"/"&B42&" metas al 100%",IF(D42>=0.8,"🟢 En buen ritmo — "&C42&"/"&B42&" (±80%)",IF(D42>=0.5,"En curso — "&TEXT(D42,"0%")&" metas completadas","🔴 Rezago — "&TEXT(D42,"0%")&" · Requiere acción")))) -> En curso — 50% metas completadas
A43: 2025 | B43: 18 | C43: 0 | D43: =IF(B43=0,0,C43/B43) -> 0 | E43: =IF(C43=0,"Por iniciar — "&B43&" metas planificadas",IF(D43>=1,"✅ Completado — "&C43&"/"&B43&" metas al 100%",IF(D43>=0.5,"En curso — "&TEXT(D43,"0%")&" metas completadas","🔴 Rezago — Requiere acción urgente"))) -> Por iniciar — 18 metas planificadas
A44: 2026 | B44: 10 | C44: 0 | D44: =IF(B44=0,0,C44/B44) -> 0 | E44: =IF(C44=0,"Por iniciar — "&B44&" metas planificadas","En curso — "&C44&"/"&B44&" completadas") -> Por iniciar — 10 metas planificadas
A45: 2027 | B45: 8 | C45: 0 | D45: =IF(B45=0,0,C45/B45) -> 0 | E45: =IF(C45=0,"Cierre PDOT Plan Bicentenario — "&B45&" metas","Ejecutado — "&C45&"/"&B45&" completadas") -> Cierre PDOT Plan Bicentenario — 8 metas
A47: 📊 PANEL 6 — ESTADO EXPORTACIÓN SIL · Sincronización COOTAD Art.598 · Compatible SIGAD / Planifica Ecuador
A48: ÚLTIMA SINCRONIZACIÓN SIL | B48: ="Últ. actualiz.: "&'SUPPORT-SIL'!L6 -> Últ. actualiz.: Fri Feb 27 2026
A49: METAS SINCRONIZADAS | B49: =COUNTIF('SUPPORT-SIL'!K6:K25,"✅ Completado")&" / "&COUNTA('SUPPORT-SIL'!A6:A25) -> 6 / 20
A50: METAS LISTAS PARA EXPORTAR | B50: =COUNTA('SUPPORT-SIL'!A6:A25) -> 20
A51: METAS CON VI=1 (Verificables) | B51: =COUNTIF('SUPPORT-SIL'!J6:J25,1) -> 15
A52: AVANCE PROMEDIO GLOBAL (Ti̅) | B52: =TEXT(AVERAGE('SUPPORT-SIL'!I6:I25),"0,0%") -> 53,0%
A54: ▶ INSTRUCCIÓN EXPORTACIÓN: Ir a hoja Q-SIL → Verificar Sección B → Archivo → Guardar copia → CSV UTF-8 → Subir a planificaecuador.gob.ec → Módulo SIL
A57: 📊 PANEL 3 — TOP 3 DIRECCIONES ALTO DESEMPEÑO (IED ≥70%) · Fuente: F-EDS Sección B
A58: RANKING | B58: DIRECCIÓN | C58: IED | D58: NIVEL
A59: 🥇 1° | B59: =INDEX('SUPPORT-EVALDIR'!B28:B39,MATCH(LARGE('SUPPORT-EVALDIR'!H28:H39,1),'SUPPORT-EVALDIR'!H28:H39,0)) -> Dir. Desarrollo Social y Cultural | C59: =LARGE('SUPPORT-EVALDIR'!H28:H39,1) -> 150 | D59: =IF(LARGE('SUPPORT-EVALDIR'!H28:H39,1)>=96,"⭐ EXCELENCIA",IF(LARGE('SUPPORT-EVALDIR'!H28:H39,1)>=85,"✅ MUY BUENO",IF(LARGE('SUPPORT-EVALDIR'!H28:H39,1)>=70,"🟢 GESTIÓN POR MANDATO",IF(LARGE('SUPPORT-EVALDIR'!H28:H39,1)>=60,"🟡 REGULAR","🔴 INACEPTABLE")))) -> ⭐ EXCELENCIA
A60: 🥈 2° | B60: =INDEX('SUPPORT-EVALDIR'!B28:B39,MATCH(LARGE('SUPPORT-EVALDIR'!H28:H39,2),'SUPPORT-EVALDIR'!H28:H39,0)) -> Dir. Agua Potable y Saneamiento | C60: =LARGE('SUPPORT-EVALDIR'!H28:H39,2) -> 82.5 | D60: =IF(LARGE('SUPPORT-EVALDIR'!H28:H39,2)>=96,"⭐ EXCELENCIA",IF(LARGE('SUPPORT-EVALDIR'!H28:H39,2)>=85,"✅ MUY BUENO",IF(LARGE('SUPPORT-EVALDIR'!H28:H39,2)>=70,"🟢 GESTIÓN POR MANDATO",IF(LARGE('SUPPORT-EVALDIR'!H28:H39,2)>=60,"🟡 REGULAR","🔴 INACEPTABLE")))) -> 🟢 GESTIÓN POR MANDATO
A61: 🥉 3° | B61: =INDEX('SUPPORT-EVALDIR'!B28:B39,MATCH(LARGE('SUPPORT-EVALDIR'!H28:H39,3),'SUPPORT-EVALDIR'!H28:H39,0)) -> Dir. Obras Publicas | C61: =LARGE('SUPPORT-EVALDIR'!H28:H39,3) -> 80.5 | D61: =IF(LARGE('SUPPORT-EVALDIR'!H28:H39,3)>=96,"⭐ EXCELENCIA",IF(LARGE('SUPPORT-EVALDIR'!H28:H39,3)>=85,"✅ MUY BUENO",IF(LARGE('SUPPORT-EVALDIR'!H28:H39,3)>=70,"🟢 GESTIÓN POR MANDATO",IF(LARGE('SUPPORT-EVALDIR'!H28:H39,3)>=60,"🟡 REGULAR","🔴 INACEPTABLE")))) -> 🟢 GESTIÓN POR MANDATO
A63: 📊 PANEL 4 — DIRECCIONES REQUIEREN ATENCIÓN URGENTE (IED <50%) · Fuente: F-EDS + R-ALERTAS
A64: ALERTA | B64: DIRECCIÓN | C64: IED | D64: ACCIÓN REQUERIDA
A65: =IF(SMALL('SUPPORT-EVALDIR'!H28:H39,1)=0,"⬛ CRÍTICA",IF(SMALL('SUPPORT-EVALDIR'!H28:H39,1)<30,"🔴 CRÍTICA",IF(SMALL('SUPPORT-EVALDIR'!H28:H39,1)<50,"🟠 ALTA","🟡 MEDIA"))) -> ⬛ CRÍTICA | B65: =INDEX('SUPPORT-EVALDIR'!B28:B39,MATCH(SMALL('SUPPORT-EVALDIR'!H28:H39,1),'SUPPORT-EVALDIR'!H28:H39,0)) -> Dir. Servicios Publicos y Gestion | C65: =SMALL('SUPPORT-EVALDIR'!H28:H39,1) -> 0 | D65: =IF(SMALL('SUPPORT-EVALDIR'!H28:H39,1)=0,"SUMARIO — LOSEP Art.80 (IED=0)",IF(SMALL('SUPPORT-EVALDIR'!H28:H39,1)<30,"SUMARIO — LOSEP Art.80",IF(SMALL('SUPPORT-EVALDIR'!H28:H39,1)<50,"MEMORANDO FORMAL — Plan 30 días","SEGUIMIENTO — Plan de mejora"))) -> SUMARIO — LOSEP Art.80 (IED=0)
A66: =IF(SMALL('SUPPORT-EVALDIR'!H28:H39,2)=0,"⬛ CRÍTICA",IF(SMALL('SUPPORT-EVALDIR'!H28:H39,2)<30,"🔴 CRÍTICA",IF(SMALL('SUPPORT-EVALDIR'!H28:H39,2)<50,"🟠 ALTA","🟡 MEDIA"))) -> 🔴 CRÍTICA | B66: =INDEX('SUPPORT-EVALDIR'!B28:B39,MATCH(SMALL('SUPPORT-EVALDIR'!H28:H39,2),'SUPPORT-EVALDIR'!H28:H39,0)) -> Unidad de Turismo | C66: =SMALL('SUPPORT-EVALDIR'!H28:H39,2) -> 13.5 | D66: =IF(SMALL('SUPPORT-EVALDIR'!H28:H39,2)=0,"SUMARIO — LOSEP Art.80 (IED=0)",IF(SMALL('SUPPORT-EVALDIR'!H28:H39,2)<30,"SUMARIO — LOSEP Art.80",IF(SMALL('SUPPORT-EVALDIR'!H28:H39,2)<50,"MEMORANDO FORMAL — Plan 30 días","SEGUIMIENTO — Plan de mejora"))) -> SUMARIO — LOSEP Art.80
A67: =IF(SMALL('SUPPORT-EVALDIR'!H28:H39,3)=0,"⬛ CRÍTICA",IF(SMALL('SUPPORT-EVALDIR'!H28:H39,3)<30,"🔴 CRÍTICA",IF(SMALL('SUPPORT-EVALDIR'!H28:H39,3)<50,"🟠 ALTA","🟡 MEDIA"))) -> 🔴 CRÍTICA | B67: =INDEX('SUPPORT-EVALDIR'!B28:B39,MATCH(SMALL('SUPPORT-EVALDIR'!H28:H39,3),'SUPPORT-EVALDIR'!H28:H39,0)) -> Unidad Gestion Sanitaria/MSP | C67: =SMALL('SUPPORT-EVALDIR'!H28:H39,3) -> 15.8 | D67: =IF(SMALL('SUPPORT-EVALDIR'!H28:H39,3)=0,"SUMARIO — LOSEP Art.80 (IED=0)",IF(SMALL('SUPPORT-EVALDIR'!H28:H39,3)<30,"SUMARIO — LOSEP Art.80",IF(SMALL('SUPPORT-EVALDIR'!H28:H39,3)<50,"MEMORANDO FORMAL — Plan 30 días","SEGUIMIENTO — Plan de mejora"))) -> SUMARIO — LOSEP Art.80
A68: =IF(SMALL('SUPPORT-EVALDIR'!H28:H39,4)=0,"⬛ CRÍTICA",IF(SMALL('SUPPORT-EVALDIR'!H28:H39,4)<30,"🔴 CRÍTICA",IF(SMALL('SUPPORT-EVALDIR'!H28:H39,4)<50,"🟠 ALTA","🟡 MEDIA"))) -> 🔴 CRÍTICA | B68: =INDEX('SUPPORT-EVALDIR'!B28:B39,MATCH(SMALL('SUPPORT-EVALDIR'!H28:H39,4),'SUPPORT-EVALDIR'!H28:H39,0)) -> Patronato Municipal de Amparo Social | C68: =SMALL('SUPPORT-EVALDIR'!H28:H39,4) -> 18 | D68: =IF(SMALL('SUPPORT-EVALDIR'!H28:H39,4)=0,"SUMARIO — LOSEP Art.80 (IED=0)",IF(SMALL('SUPPORT-EVALDIR'!H28:H39,4)<30,"SUMARIO — LOSEP Art.80",IF(SMALL('SUPPORT-EVALDIR'!H28:H39,4)<50,"MEMORANDO FORMAL — Plan 30 días","SEGUIMIENTO — Plan de mejora"))) -> SUMARIO — LOSEP Art.80
A69: =IF(SMALL('SUPPORT-EVALDIR'!H28:H39,5)=0,"⬛ CRÍTICA",IF(SMALL('SUPPORT-EVALDIR'!H28:H39,5)<30,"🔴 CRÍTICA",IF(SMALL('SUPPORT-EVALDIR'!H28:H39,5)<50,"🟠 ALTA","🟡 MEDIA"))) -> 🔴 CRÍTICA | B69: =INDEX('SUPPORT-EVALDIR'!B28:B39,MATCH(SMALL('SUPPORT-EVALDIR'!H28:H39,5),'SUPPORT-EVALDIR'!H28:H39,0)) -> Dir. Planificacion y Desarrollo | C69: =SMALL('SUPPORT-EVALDIR'!H28:H39,5) -> 20 | D69: =IF(SMALL('SUPPORT-EVALDIR'!H28:H39,5)=0,"SUMARIO — LOSEP Art.80 (IED=0)",IF(SMALL('SUPPORT-EVALDIR'!H28:H39,5)<30,"SUMARIO — LOSEP Art.80",IF(SMALL('SUPPORT-EVALDIR'!H28:H39,5)<50,"MEMORANDO FORMAL — Plan 30 días","SEGUIMIENTO — Plan de mejora"))) -> SUMARIO — LOSEP Art.80

Sheet M-TECH-GAD
A1: QUADRUM v1.0 · M-TECH-GAD · Configuración Institucional · GAD Municipal Montecristi · Protocolo ALFARO VIRTUS
A2: =HYPERLINK("#'M-INDEX'!A1","⌂ INDICE") -> ⌂ INDICE | B2: =HYPERLINK("#'M1-ITME'!A1","M1") -> M1 | C2: =HYPERLINK("#'M2-PDOT'!A1","M2") -> M2 | D2: =HYPERLINK("#'M3-MAO'!A1","M3") -> M3 | E2: =HYPERLINK("#'M4-AUDIT'!A1","M4") -> M4 | F2: =HYPERLINK("#'M5-ICPI'!A1","M5") -> M5 | G2: =HYPERLINK("#'M6-FEDS'!A1","M6") -> M6 | H2: =HYPERLINK("#'M7-PROSP'!A1","M7") -> M7 | I2: =HYPERLINK("#'DATA-POA'!A1","DATA-POA") -> DATA-POA | J2: =HYPERLINK("#'DATA-CNE'!A1","DATA-CNE") -> DATA-CNE | K2: =HYPERLINK("#'DATA-ORG'!A1","DATA-ORG") -> DATA-ORG | L2: =HYPERLINK("#'M-DASHBOARD'!A1","DASH") -> DASH
A3: Capa: Control > Configuración Institucional · Solo Administrador · SIAP-ICPI §1.1
A4: 🔷 CONFIGURACIÓN INSTITUCIONAL · Solo Administrador · Parámetros base del instrumento
A5: PARÁMETRO | B5: 🟢 VALOR ACTIVO (Montecristi) | C5: EDITABLE (⚫ Sí / ⚫ No) | D5: DESCRIPCIÓN | E5: BASE LEGAL | F5: IMPACTO EN MODELO | G5: FECHA ULT.ACTUALIZ. | H5: RESPONSABLE ACTUALIZ.
A6: NOMBRE_GAD | B6: Gobierno Autónomo Descentralizado Municipal de Montecristi | C6: ⚫ Sí | D6: Nombre oficial completo del GAD Municipal | E6: CRE Art.264 + COOTAD Art.53 | F6: Todos los títulos, headers y exports del modelo | G6: 28/02/2026 | H6: Dir. Planificación
A7: CANTON | B7: Montecristi | C7: ⚫ Sí | D7: Nombre del cantón | E7: COOTAD Art.53 | F7: Dashboard y reportes | G7: 28/02/2026 | H7: Dir. Planificación
A8: PROVINCIA | B8: Manabí | C8: ⚫ Sí | D8: Provincia del cantón | E8: División político-administrativa | F8: Metadata y exports | G8: 28/02/2026 | H8: Dir. Planificación
A9: PAIS | B9: Ecuador | C9: ⚫ No | D9: País (fijo para este modelo) | E9: — | F9: Metadata | G9: 28/02/2026 | H9: —
A10: CLASE_GAD | B10: Municipal / Cantonal | C10: ⚫ No | D10: Clase según COOTAD — este modelo es para GADs Municipales | E10: COOTAD Art.53 | F10: Determina competencias y presupuesto tipo | G10: 28/02/2026 | H10: —
A11: CODIGO_INEC | B11: 130101 | C11: ⚫ Sí | D11: Código INEC del cantón (6 dígitos) | E11: Clasificación territorial INEC | F11: SIGAD, SIGPIP, eSIGEF | G11: 28/02/2026 | H11: Dir. Planificación
A12: ALCALDE | B12: Por confirmar — GAD Montecristi | C12: ⚫ Sí | D12: Nombre del Alcalde/Alcaldesa vigente | E12: COOTAD Art.60 | F12: Firmas y actos administrativos | G12: 28/02/2026 | H12: Secretaría Alcaldía
A14: 🔶 SECCIÓN B — PARÁMETROS PDOT Y EVALUACIÓN · Ajustar al período PDOT y muestra del GAD destino
A15: PERIODO_PDOT | B15: 2023-2027 | C15: ⚫ Sí | D15: Período del PDOT vigente — determina horizonte de evaluación | E15: COOTAD Art.295 | F15: A-PDOT, M-POA, todas las metas | G15: 28/02/2026 | H15: Dir. Planificación
A16: N_METAS | B16: 20 | C16: ⚫ Sí | D16: Número de metas en la muestra estratégica. Cambiar si el GAD tiene más o menos metas auditables. | E16: SIAP-ICPI §3.2 | F16: E1-ICPI (rango fórmulas), B-PONDER (ΣPi=1) | G16: 28/02/2026 | H16: Dir. Planificación
A17: N_EJES | B17: 5 | C17: ⚫ Sí | D17: Número de ejes estratégicos del PDOT | E17: COOTAD Art.295 | F17: H2-EJES, B-PONDER | G17: 28/02/2026 | H17: Dir. Planificación
A18: META_PDOT_2027 | B18: 1 | C18: Benchmark primario del modelo. Ti=1.0 = meta PDOT cumplida al 100% al cierre 2027
A19: ICM_SIGAD_REF | B19: 0.9225 | C19: ICM SIGAD 2023 — solo comparativo §4.2. Benchmark del modelo es Meta PDOT 2027 = 100% | D19: ICM oficial SIGAD más reciente. Actualizar con ICM 2024 cuando esté disponible. | E19: SIGAD-SNP | F19: PARAMS B6, brecha ICPI vs ICM, F-BI | G19: 28/02/2026 | H19: Dir. Planificación
A20: AÑO_ICM_REF | B20: 2023 | C20: 🔵 Sí | D20: Año del índice SIGAD comparativo §4.2. Actualizar junto con ICM_BASE si cambia. | E20: SIGAD-SNP | F20: PARAMS, Dashboard | G20: 28/02/2026 | H20: Dir. Planificación
A21: N_DIRECCIONES | B21: 13 | C21: 🔵 Sí | D21: Número de direcciones en el orgánico. Actualizar con Estatuto Orgánico real. | E21: Estatuto Orgánico GAD | F21: X-ORGANICO, Y-EVAL-DIR, Ci | G21: 28/02/2026 | H21: Dir. Planificación
A22: N_SERVIDORES | B22: ~120 (aprox) | C22: 🔵 Sí | D22: Total servidores públicos en nómina. Base para Z-EVAL-SP completo. | E22: LOSEP + RRHH GAD | F22: Z-EVAL-SP (escalabilidad QUADRUM) | G22: 28/02/2026 | H22: Dir. RRHH
A23: PRESUP_PDOT_USD | B23: 122857648 | C23: 🔵 Sí | D23: Presupuesto total PDOT n=20 metas en USD. Actualizar con cédulas eSIGEF. | E23: PDOT Plan Bicentenario + eSIGEF | F23: L-CEDULAS, B-PONDER, Pi | G23: 28/02/2026 | H23: Dir. Financiera
A25: 🔶 SECCIÓN C — ESCALA LOSEP OFICIAL · Norma Técnica MDT · NO modificar sin cambio normativo
A26: UMBRAL_EXCELENTE | B26: 0.96 | C26: ⚫ No | D26: IED ≥ 96% → Felicitación pública + registro SIITH | E26: LOSEP Art.78 + NT MDT | F26: Y-EVAL-DIR col I, Z-EVAL-SP col N, F-EDS | G26: 28/02/2026 | H26: —
A27: UMBRAL_MUY_BUENO | B27: 0.85 | C27: ⚫ No | D27: IED 85-95.99% → Reconocimiento + SIITH | E27: LOSEP Art.77 + NT MDT | F27: Ídem | G27: 28/02/2026 | H27: —
A28: UMBRAL_SATISFACTORIO | B28: 0.7 | C28: ⚫ No | D28: IED 70-84.99% → Sin acción (aprobado) | E28: LOSEP Art.76 + NT MDT | F28: Ídem | G28: 28/02/2026 | H28: —
A29: UMBRAL_REGULAR | B29: 0.6 | C29: ⚫ No | D29: IED 60-69.99% → Plan mejora 90 días | E29: LOSEP Art.77 + NT MDT | F29: Ídem | G29: 28/02/2026 | H29: —
A30: UMBRAL_INACEPTABLE | B30: 0 | C30: ⚫ No | D30: IED <60% → Sumario administrativo LOSEP Art.80 | E30: LOSEP Art.80 + COA Art.196 | F30: Ídem | G30: 28/02/2026 | H30: —
A32: 🔶 SECCIÓN D — PARÁMETROS CININ Y EVALUACIÓN PRESUPUESTARIA · Ajustar si el GAD tiene menos silos activos (ej: GAD rural sin SIGAD completo)
A33: CININ_SILOS | B33: 6 | C33: ⚫ No | D33: 🟢 Número de silos CININ activos. 6 = modelo completo. Ver TRAZABILIDAD. | E33: SIAP-ICPI §3.4 | F33: D-MAD cols Q:V, Vi_CADENA | G33: 28/02/2026 | H33: SIAP-ICPI
A34: MODO_CININ | B34: COMPLETO | C34: 🔵 Sí | D34: COMPLETO = 6 silos. LITE = 3 silos (GADs rurales sin SIGAD/CPCCS). MÍNIMO = S1+S4 (solo PDOT+cédula). | E34: SIAP-ICPI §3.4 | F34: D-MAD lógica Vi_CADENA | G34: 28/02/2026 | H34: Dir. Planificación
A35: Ti_BASE | B35: Devengado/Codif | C35: ⚫ No | D35: Ti = Devengado / Codificado vigente (no inicial PDOT). Ver L-CEDULAS. | E35: COPFP Art.111+118 | F35: L-CEDULAS col K, D-MAD col T | G35: 28/02/2026 | H35: Dir. Financiera
A36: CORTE_SEMESTRAL | B36: Junio | C36: 🔵 Sí | D36: Mes del corte semestral de evaluación LOSEP Art.77 | E36: LOSEP Art.77 | F36: Y-EVAL-DIR, Z-EVAL-SP | G36: 28/02/2026 | H36: Dir. RRHH
A37: CORTE_ANUAL | B37: Diciembre | C37: ⚫ No | D37: Mes del corte anual obligatorio LOSEP | E37: LOSEP Art.77 | F37: Y-EVAL-DIR, Z-EVAL-SP | G37: 28/02/2026 | H37: —
A39: 🔶 SECCIÓN E — ESTADO DE IMPLEMENTACIÓN Y S · Hoja de ruta para el modelo al 10/10
A40: ESTATUTO_ORGANICO | C40: 🔵 Actualizar | D40: Actualizar con Estatuto Orgánico vigente GAD Montecristi → Hoja ORGANICO refleja estructura administrativa oficial según normativa vigente | E40: X-ORGANICO | F40: 🟠 Alta | G40: Dir. Planificación + Alcaldía
A41: SIITH_INTEGRACION | C41: 🔵 Implementar | D41: Protocolo exportación Z-EVAL-SP → sistema SIITH MDT para validez jurídica evaluación LOSEP | E41: Z-EVAL-SP | F41: 🟠 Alta | G41: Dir. RRHH + Dir. TI
A42: ICM_2024 | C42: 🔵 Actualizar | D42: Actualizar ICM_BASE con valor oficial SIGAD 2024 cuando esté disponible (Q1 2025) | E42: PARAMS B6 | F42: 🟠 Alta | G42: Dir. Planificación
A43: CEDULAS_REALES | C43: 🔵 Actualizar | D43: Ingresar CUPs reales y codificado vigente real de eSIGEF en L-CEDULAS (actualmente aproximado) | E43: L-CEDULAS | F43: 🟠 Alta | G43: Dir. Financiera
A44: EVAL_SEMESTRAL | C44: 🔵 Implementar | D44: Módulo corte junio: copia Y-EVAL-DIR + Z-EVAL-SP a hojas Y-EVAL-DIR-S1 y Z-EVAL-SP-S1 | E44: Y/Z-EVAL | F44: 🟡 Media | G44: Dir. RRHH
A45: AUTOEVALUACION | C45: 🔵 Implementar | D45: 🟡 Formulario autoevaluación servidor (60%) + jefe inmediato (40%) — LOSEP NT MDT | E45: Z-EVAL-SP | F45: 🟡 Media | G45: Dir. RRHH
A46: CONFIG_ESCALADO | B46: ✅ LISTO | C46: — | D46: CONFIG-GAD implementado. Para nuevo GAD: cambiar NOMBRE_GAD, CANTON, N_METAS, ICM_BASE. | E46: CONFIG-GAD | F46: — | G46: —
A47: NOMENCLATURA | B47: ✅ LISTO | C47: — | D47: COD-META PDOT actualizado. 155 celdas actualizadas. [v1.0 · Nomenclatura PDOT unificada] | E47: Todo el modelo | F47: — | G47: —
A48: CININ_6_SILOS | B48: ✅ LISTO | C48: — | D48: Cadena CININ PDOT→POA→PAC→CED→SIGAD→CPCCS implementada en D-MAD | E48: D-MAD | F48: — | G48: —
A49: L_CEDULAS | B49: ✅ LISTO | C49: — | D49: Control presupuestario codificado/devengado/pagado con CUP — puente Ti formal | E49: L-CEDULAS | F49: — | G49: —
A50: ESCALA_LOSEP | B50: ✅ LISTO | C50: — | D50: Escala IED unificada con LOSEP 5 niveles. F-EDS, Y-EVAL-DIR, Z-EVAL-SP alineados. | E50: Todo el modelo | F50: — | G50: —

Sheet M-TECH-PARAMS
A1: QUADRUM v1.0 · M-TECH-PARAMS · Parámetros Globales · Umbrales · Constantes del Sistema · Protocolo de Integridad Forense ALFARO VIRTUS
A2: =HYPERLINK("#'M-INDEX'!A1","⌂ INDICE") -> ⌂ INDICE | B2: =HYPERLINK("#'M1-ITME'!A1","M1") -> M1 | C2: =HYPERLINK("#'M2-PDOT'!A1","M2") -> M2 | D2: =HYPERLINK("#'M3-MAO'!A1","M3") -> M3 | E2: =HYPERLINK("#'M4-AUDIT'!A1","M4") -> M4 | F2: =HYPERLINK("#'M5-ICPI'!A1","M5") -> M5 | G2: =HYPERLINK("#'M6-FEDS'!A1","M6") -> M6 | H2: =HYPERLINK("#'M7-PROSP'!A1","M7") -> M7 | I2: =HYPERLINK("#'DATA-POA'!A1","DATA-POA") -> DATA-POA | J2: =HYPERLINK("#'DATA-CNE'!A1","DATA-CNE") -> DATA-CNE | K2: =HYPERLINK("#'DATA-ORG'!A1","DATA-ORG") -> DATA-ORG | L2: =HYPERLINK("#'M-DASHBOARD'!A1","DASH") -> DASH
A3: Capa: Control > Parámetros Globales del Sistema · SIAP-ICPI §1.2
A4: 🔷 PARÁMETROS TÉCNICOS · Rangos de Integridad Programática · Categorías ICPI · Factores globales del modelo
A5: ━━ SECCIÓN ❶ BENCHMARK PDOT 2027 — Meta de cumplimiento y comparativo ICM-SIGAD
A6: Meta PDOT 2027 (benchmark primario) | B6: 1 | C6: Cada meta debe alcanzar Ti=1.0 al cierre del Plan Bicentenario 2027 — fuente PDOT §4 | D6: Valor oficial ICM 2023 del SIGAD — fuente: Informe rendicion de cuentas RDC 2023 + SIGAD-SNP linea Montecristi | E6: 23/02/2025
A7: ICM SIGAD 2023 (comparativo — auto-reporte) | B7: =92.25&" %" -> 92,25 % | C7: Auto-reporte SIGAD. NO es el benchmark. Útil para cuantificar diferencial forense §4.2 | D7: : SIGAD libera dato oficial ICM 2024 primer trimestre 2025 — actualizar con valor oficial
A8: Brecha PDOT (ICPI − Meta 2027) pp | B8: =TEXT(('M5-ICPI'!G26-1)*100,"0,00")&" pp" -> -100,00 pp | C8: Brecha primaria del modelo. Meta=100% PDOT 2027. Negativa = incumplimiento §3.6 | D8: ICPI − ICM en puntos porcentuales. Fuente: E2-RESUL (motor ICPI) vs. ICM SIGAD 2023 (celda B6 PARAMS) | E8: 23/02/2025
A9: ICPI Calculado (%) | B9: ='M5-ICPI'!G29 -> 38.283014 | C9: E2-RESUL!B6 * 100 | D9: SIAP-ICPI · 36 hojas · CININ 6 silos · Ti corregido (S4=eSIGEF autoridad) · Cadena PDOT→POA→PAC→Cédula→SIGAD→CPCCS · ORGANICO+EVAL-DIR+EVAL-SP · CONFIG-GAD · CEDULAS · SEMESTRAL · ITME inventario técnico | E9: 23/02/2025
A10: ━━ SECCIÓN ➊ ICPI — Motor Algorítmico Central
A11: ICPI Final (decimal) | B11: ='DATA-RESULTADOS'!C6 -> 0.40003606 | C11: E2-RESUL!B6 | D11: Motor E1-ICPI: Σ(Pi×Ri×Vi×Ei×Ti×Ci) ÷ Σ(Pi×Ri) · Ci incorporado §3.7.1 | E11: 23/02/2025
A12: ICPI Final (%) | B12: ='DATA-RESULTADOS'!C6*100 -> 40.003606 | C12: E2-RESUL!B6 * 100 | D12: ICPI expresado en % para comparación con ICM y Rangos de Integridad Programática (AVEP) | E12: 23/02/2025
A13: Rango de Integridad (AVEP) | B13: 🟡 TRANSICIÓN CRÍTICA | C13: E2-RESUL!B8 | D13: ⭐ Rangos de Integridad (AVEP): Ruptura | Ocurrencia | Transición Crítica | Mandato | Excelencia | E13: 23/02/2025
A14: Σ Numerador Σ(Pi×Ri×Vi×Ei×Ti) | B14: ='M5-ICPI'!G25 -> 0.40896482 | C14: E2-RESUL!B4 | D14: Numerador de la fórmula multifactorial ICPI · Incluye Ci por meta (C-MAO → D-MAD col P → E1-ICPI col I) · Ci incorporado §3.7.1 | E14: 23/02/2025
A15: Σ Denominador Σ(Pi×Ri) | B15: =SUM('M5-ICPI'!H5:H24) -> 1.0682671 | C15: E2-RESUL!B5 | D15: Denominador de la fórmula multifactorial ICPI | E15: 23/02/2025
A16: Interpretación cualitativa | B16: ='DATA-RESULTADOS'!B8 -> Transición Crítica 🟡 | C16: E2-RESUL!B9 | D16: Texto narrativo del Rango de Integridad activo (AVEP) | E16: 23/02/2025
A18: ━━ SECCIÓN ➋ MUESTRA — Universo y Representatividad
A19: N — Universo PDOT (metas estrategicas Plan Bicentenario) | B19: 20 | C19: A-PDOT (n=20 metas seleccionadas por mayor impacto presupuestario y competencia GAD) | D19: Total metas PDOT en muestra estrategica SIAP-ICPI. Fuente: A-PDOT Plan Bicentenario 2023-2027 | E19: 22/02/2025
A20: n — Muestra estrategica PDOT activa | B20: =COUNTA('M4-AUDIT'!A5:A24) -> 20 | C20: A-PDOT (conteo metas activas con evidencia auditada) | D20: Muestra SEPP: n=20 de N=67 por mayor impacto presupuestario | E20: 22/02/2025
A21: Representatividad financiera (%) | B21: =IFERROR(B23/B22, 0) -> 0 | C21: B3-VALREP | D21: La muestra n=20 representa el 87.2% del presupuesto total ($13.875M / $15.91M) | E21: 22/02/2025
A22: Presupuesto muestra n=20 ($) | B22: {=IFERROR(SUMPRODUCT(('M2-PLAN-Pi'!E13:E32>0)*'M2-PLAN-Pi'!E13:E32),0)} -> 0 | C22: A-PDOT col M (Presupuesto PDOT por meta) — suma metas n=20 | D22: Suma de presupuestos de las 20 metas muestra (USD) | E22: 46075
A23: Presupuesto con trazabilidad ($) | B23: {=IFERROR(SUMPRODUCT(('M4-AUDIT'!F5:F24=1)*('M2-PLAN-Pi'!E13:E32>0)*'M2-PLAN-Pi'!E13:E32),0)} -> 0 | C23: D-MAD (Vi=1) | D23: Inversión trazada documentalmente (metas Vi=1) | E23: 23/02/2025
A25: ━━ SECCIÓN ➉ VARIABLES Vi / Ei / Ti / Ci — Estado Documental y Atribución Orgánica
A26: Metas con Vi=1 (soporte documental) | B26: =COUNTIF('M4-AUDIT'!F5:F24,1) -> 15 | C26: D-MAD (conteo Vi=1) | D26: Metas con respaldo forense verificado en sistemas oficiales | E26: 23/02/2025
A27: Metas con Vi=0 (sin soporte) | B27: =COUNTIF('M4-AUDIT'!F5:F24,0) -> 5 | C27: D-MAD (conteo Vi=0) | D27: Metas sin respaldo — Vi=0 anula completamente la contribución al ICPI | E27: 23/02/2025
A28: Metas con ejecución completa (Vi=1 y Ti=1) | B28: {=SUMPRODUCT(('M4-AUDIT'!F5:F24=1)*('M4-AUDIT'!H5:H24>=1))} -> 4 | C28: D-MAD | D28: TER-01 (Maquinaria), TER-18 (Señalética), SOC-03 (Geriátrico), INS-05 (Catastro) | E28: 23/02/2025
A29: Metas con evidencia parcial (Vi=1 y Ti<1) | B29: {=SUMPRODUCT(('M4-AUDIT'!F5:F24=1)*('M4-AUDIT'!H5:H24<1))} -> 11 | C29: D-MAD | D29: Con respaldo pero ejecución incompleta — Ti entre 0.25 y 0.90 | E29: 23/02/2025
A30: Metas con Ci<1.0 (control parcial) | B30: =COUNTIF('M4-AUDIT'!P5:P24,"<1") -> 3 | C30: C-MAO / D-MAD col P | D30: Ci∈{1.0;0.9;0.75;0.5} según dueño del proceso (Estatuto Orgánico + COOTAD §3.7.1). 13 GAD directo Ci=1.0 | 7 adscritos Ci=0.9. Fuente: C-MAO → D-MAD col P (VLOOKUP) → E1-ICPI col I. D-MAD: col C=Silo Oficial §3.4 | col D=Área Temática. | E30: 27/02/2026
A31: IED Promedio (F-EDS) — Score desempeño | B31: =IFERROR(AVERAGE('M6-FEDS'!J7:J26),"-") -> 30.4625 | C31: F-EDS!J7:J26 | D31: IED promedio de las 20 metas (0-100) · F-EDS triangula Estatuto Orgánico→POA→PAC→Cédula · OUTPUT §3.7.1 | E31: 27/02/2026
A32: ❌ Direcciones con IED INACEPTABLE (0-19) | B32: =COUNTIF('M6-FEDS'!F30:F41,"RUPTURA TOTAL") -> 0 | C32: F-EDS!F30:F41 | D32: Direcciones con RUPTURA TOTAL (IED=0) · Sumario administrativo LOSEP Art.80 + COOTAD Art.339 | E32: 27/02/2026
A33: ━━ SECCIÓN ➍ ICPI POR EJE ESTRATÉGICO
A34: ICPI Eje TERRITORIAL (%) | B34: ='DATA-EJES'!D4 -> 25.761436 | C34: H2-EJES!D4 | D34: 9 metas territoriales | Mayor eje por peso presupuestario (61.0%) | E34: 23/02/2025
A35: ICPI Eje SOCIAL (%) | B35: ='DATA-EJES'!D5 -> 51.686758 | C35: H2-EJES!D5 | D35: 6 metas sociales | Eje con mayor cantidad de Vi=0 (4 sin soporte) | E35: 23/02/2025
A36: ICPI Eje AMBIENTAL (%) | B36: ='DATA-EJES'!D6 -> 44.931664 | C36: H2-EJES!D6 | D36: 2 metas ambientales | Vi=1 en ambas pero Ti bajo (0.27-0.36) | E36: 23/02/2025
A37: ICPI Eje ECONÓMICO (%) | B37: ='DATA-EJES'!D7 -> 70 | C37: H2-EJES!D7 | D37: 1 meta económica | ECO-12 con Vi=1 Ti=0.30 — Playa San José | E37: 23/02/2025
A38: ICPI Eje INSTITUCIONAL (%) | B38: ='DATA-EJES'!D8 -> 60.15129 | C38: H2-EJES!D8 | D38: 2 metas institucionales | Eje mejor documentado (85.8% ICPI) | E38: 23/02/2025
A40: ━━ SECCIÓN ➎ BRECHA DE INTEGRIDAD — ICPI vs Meta PDOT 2027 (primaria) + Diferencial SIGAD (comparativo)
A41: Brecha PDOT (ICPI vs Meta 2027) pp | B41: =TEXT(('M5-ICPI'!G26-1)*100,"0,00")&" pp" -> -100,00 pp | C41: E2-RESUL!B6*100 - A-PDOT!AA5 | D41: ICPI auditado (41,53%) vs ICM oficial SIGAD (92,25%) → Diferencial de Integridad SIGAD §4.2 · Ci incorporado | E41: 23/02/2025
A42: Brecha promedio por meta (pp) | B42: =TEXT(('M5-ICPI'!G26-1)*100/20,"0,00")&" pp" -> -5,00 pp | C42: Déficit promedio de cada meta respecto a Ti=1.0 — señal de dispersión §3.6 | D42: Brecha promedio simple por meta (F-BI fila PROMEDIO) | E42: 23/02/2025
A43: Diferencial forense SIGAD − ICPI (§4.2 comparativo) | B43: =TEXT((0.9225-'M5-ICPI'!G26)*100,"0,00")&" pp" -> 92,25 pp | C43: ICM SIGAD auto-reportado (92,25%) supera ICPI auditado (41,53%) en +50,72 pp → Erosión del Compromiso §4.2 | D43: Metas donde ICPI auditado < ICM SIGAD reportado | E43: 23/02/2025
A44: Metas PDOT con Ti = 1,0 (cumplidas al 100%) | B44: =COUNTIF('M4-AUDIT'!I5:I24,1)&" / 20" -> 4 / 20 | C44: Metas con ejecución completa Ti=1.0 y Vi=1 — fuente D-MAD col I | D44: TER-03, SOC-03, TER-01, INS-05 — ICPI auditado ≥ ICM SIGAD reportado | E44: 23/02/2025
A45: ━━ SECCIÓN ➏ SENSIBILIDAD — Potencial de mejora del ICPI
A46: ΔICPI máximo (si SOC-02 Vi→1, Ti→1) | B46: ='VALID-SENS'!F7 -> 5.18 | C46: H3-SENSI B6 (escenario 1) | D46: SOC-02 es la meta con mayor impacto potencial (Pi=0.20, Ri=1.5) | E46: 23/02/2025
A47: ICPI potencial (si SOC-02 se activa) | B47: ='VALID-SENS'!E7 -> 52.2 | C47: H3-SENSI!E6 | D47: Escenario 1 H3-SENSI: ICPI sube a ~67.6% → entra en Gestión por Mandato | E47: 23/02/2025
A48: ΔICPI total acumulado potencial (s Vi=0→1) | B48: ='VALID-SENS'!C18 -> +52,98 pp | C48: H3-SENSI!B18 | D48: Escenario acumulativo: todas las metas Vi=0 se corrigen (H3-SENSI) | E48: 23/02/2025
A49: Presupuesto sin trazabilidad ($) | B49: ='VALID-SENS'!C19 -> +9,1 pp | C49: H3-SENSI!B19 | D49: Monto total de inversión sin trazabilidad documental en la muestra | E49: 23/02/2025
A50: ━━ SECCIÓN ➑ DOCUMENTACIÓN — P-VERIFICACION
A51: Documentos recibidos | B51: =COUNTA('VALID-VER'!B6:B15) -> 10 | C51: P-VERIFICACION | D51: RDC 2023 (N°17649, 10/05/2024) y RDC 2024 (N°22844, 11/07/2025) | E51: 22/02/2025
A52: Documentos s | B52: =10-B51 -> 0 | C52: P-VERIFICACION | D52: Cédulas presup. GAD + Patronato (2023-2024) y POA GAD + Patronato (2023-2024)
A53: ΔICPI potencial con documentos s | B53: ±8 pp | C53: P-VERIFICACION (estimado) | D53: Impacto estimado si cédulas GAD/Patronato confirman Vi=1 en metas críticas
A54: ━━ SECCIÓN ➒ CRITERIOS DE EVALUACIÓN PROGRAMÁTICA · Umbrales de alerta SIAP-ICPI ━━
A55: UAP — Umbral de Alerta Programática: Brecha PDOT ≥ 30 pp | B55: 🔴 ⚠️ DÉFICIT CONFIRMADO | C55: SIAP-ICPI §3.6 — Si ICPI está ≥30 pp bajo la Meta PDOT 2027, se activa protocolo de intervención
A56: UCM — Umbral de Congruencia Mínima: Brecha PDOT ≤ 10 pp | B56: =IF(ABS(('M5-ICPI'!G26-1)*100)<=10,"✅ CONGRUENTE","❌ FUERA DEL RANGO UCM") -> ❌ FUERA DEL RANGO UCM | C56: SIAP-ICPI §3.6 — Brecha ≤10 pp indica congruencia entre ejecución y compromiso PDOT
A57: Diagnóstico Programático | B57: 🔴 ⚠️ DÉFICIT PROGRAMÁTICO — activar Plan de Mejora POA
A58: ━━ SECCIÓN ➓ ESCALA LOSEP OFICIAL — IED · Norma Técnica MDT Evaluación Servidores Públicos · LOSEP Art.76-80 · Fuente única de verdad para Y-EVAL-DIR, Z-EVAL-SP, F-EDS, R-ALERTAS
A59: PARÁMETRO ESCALA | B59: VALOR UMBRAL | C59: NIVEL LOSEP | D59: ACCIÓN ADMINISTRATIVA OBLIGATORIA | E59: BASE LEGAL | F59: APLICACIÓN EN MODELO
A60: ⭐ UMBRAL_EXCELENTE | B60: 0.96 | C60: ⭐ EXCELENTE | D60: Felicitación pública + acción de personal + registro SIITH + informe MDT | E60: LOSEP Art.78 + NT MDT Eval. | F60: Y-EVAL-DIR, Z-EVAL-SP, F-EDS col F
A61: ✅ UMBRAL_MUY_BUENO | B61: 0.85 | C61: ✅ MUY BUENO | D61: Reconocimiento escrito + registro SIITH + incremento remunerativo si procede | E61: LOSEP Art.77 + NT MDT Eval. | F61: Y-EVAL-DIR, Z-EVAL-SP, F-EDS col F
A62: 🟢 UMBRAL_SATISFACTORIO | B62: 0.7 | C62: 🟢 SATISFACTORIO | D62: Sin acción correctiva — Evaluación aprobada — Continúa en funciones | E62: LOSEP Art.76 + NT MDT Eval. | F62: Y-EVAL-DIR, Z-EVAL-SP, F-EDS col F
A63: 🟡 UMBRAL_REGULAR | B63: 0.6 | C63: 🟡 REGULAR | D63: Plan mejora 90 días obligatorio + seguimiento mensual Dir. RRHH + SIITH | E63: LOSEP Art.77 + NT MDT Eval. | F63: Y-EVAL-DIR, Z-EVAL-SP, F-EDS col F
A64: ❌ UMBRAL_INACEPTABLE | B64: 0 | C64: ❌ 🔴 INACEPTABLE | D64: Sumario administrativo LOSEP Art.80 + Notificación Alcaldía 48h + SIITH | E64: LOSEP Art.80 + COA Art.196 | F64: Y-EVAL-DIR, Z-EVAL-SP, F-EDS col F
A65: Criterio de Usabilidad de Auditoría — IED>100%: Cuando Ti>1.0 (ejecución supera meta PDOT), IED puede exceder 100%. Caso: DSC=150% → clasifica como EXCELENTE. El valor real IED se preserva; solo el nivel LOSEP se evalúa contra umbrales de 0-100%.

Sheet M1-ITME
A1: QUADRUM v1.0 · M1-ITME · Inventario Técnico de Metas Estratégicas · GAD Municipal Montecristi | Z1: ⌂ ÍNDICE
A2: =HYPERLINK("#'M-INDEX'!A1","⌂ INDICE") -> ⌂ INDICE | B2: =HYPERLINK("#'M1-ITME'!A1","◉ M1") -> ◉ M1 | C2: =HYPERLINK("#'M2-PDOT'!A1","M2") -> M2 | D2: =HYPERLINK("#'M3-MAO'!A1","M3") -> M3 | E2: =HYPERLINK("#'M4-AUDIT'!A1","M4") -> M4 | F2: =HYPERLINK("#'M5-ICPI'!A1","M5") -> M5 | G2: =HYPERLINK("#'M6-FEDS'!A1","M6") -> M6 | H2: =HYPERLINK("#'M7-PROSP'!A1","M7") -> M7 | I2: =HYPERLINK("#'DATA-POA'!A1","DATA-POA") -> DATA-POA | J2: =HYPERLINK("#'DATA-CNE'!A1","DATA-CNE") -> DATA-CNE | K2: =HYPERLINK("#'DATA-ORG'!A1","DATA-ORG") -> DATA-ORG | L2: =HYPERLINK("#'DATA-RESULTADOS'!A1","RESULT") -> RESULT | M2: =HYPERLINK("#'M-DASHBOARD'!A1","DASH") -> DASH
A3: #
A4: N° | B4: COD-PDOT (Inventario) | C4: SISTEMA PDOT | D4: EJE ESTRATÉGICO | E4: PROGRAMA PDOT | F4: SUBPROGRAMA | G4: PROYECTO / DESCRIPCIÓN SINTÉTICA | H4: PROYECTO ESTRATÉGICO PDOT | I4: OBJETIVO DE GESTIÓN | J4: PRESUP. PDOT ($) | K4: EN MUESTRA SIAP-ICPI | L4: COD-META MUESTRA | M4: ALINEACIÓN PDOT | N4: OBSERVACIÓN / CANDIDATOS PARA MUESTRA FUTURA
A5: 1 | B5: PDOT.FA.OE1.PV.01 | C5: Físico Ambiental | D5: AMBIENTAL | E5: Áreas verdes y zonas de Protección | F5: Nuevos parques y zonas de protección | G5: Red Verde urbana: Parque Las Pampas + Parque Cárcel Simón Bolívar + Parque Estancia Las Palmas | H5: Parques Inter barriales / Parque Las Pampas / Parque Cárcel Simón Bolívar | I5: Incrementar áreas de protección e índice verde urbano | J5: 709999.54 | K5: No | L5: — | M5: ⚠️ PARCIAL | N5: Candidato próxima muestra — parques urbanos IE PDOT
A6: 2 | B6: PDOT.FA.OE1.PV.02 | C6: Físico Ambiental | D6: AMBIENTAL | E6: Áreas verdes y zonas de Protección | F6: Mantenimiento de áreas verdes | G6: Mantenimiento arbolado urbano y Rehabilitación Parque Colorado | H6: Rehabilitación Parque Colorado | I6: Incrementar áreas de protección e índice verde urbano | J6: 25000 | K6: No | L6: — | M6: ✅ ALINEADA | N6: Operación recurrente — presupuesto bajo
A7: 3 | B7: PDOT.FA.OE1.MA.01 | C7: Físico Ambiental | D7: AMBIENTAL | E7: Áreas verdes / Recuperación ambiental | F7: Recuperación y preservación ambiental | G7: Proyecto Ecoturístico Manglar Vivo Playa San José (Muestra M18) | H7: Recuperación y manejo sustentable Playa San José / Repotenciación manglar costero | I7: Incrementar áreas de protección e índice verde urbano | J7: 75000 | K7: ✅ Sí | L7: PDOT.EP.OE5.M1.01 | M7: ✅ ALINEADA | N7: M18 en muestra — Vi=1 Ti=0.30 — BDE Premio Verde
A8: 4 | B8: PDOT.FA.OE2.MA.01 | C8: Físico Ambiental | D8: AMBIENTAL | E8: Ambiente | F8: Mitigación Ambiental | G8: Albergue/Centro recuperación fauna urbana — componente manglar y biodiversidad | H8: Estudio diseño Centro de Recuperación de paso de Fauna | I8: Cumplir el desarrollo de la planificación ambiental | J8: 137136.64 | K8: ✅ Sí | L8: PDOT.AM.SC.M3.01 | M8: ⚠️ PARCIAL | N8: M17 en muestra — Vi=1 Ti=0.35 — vincular Manglar Vivo
A9: 5 | B9: PDOT.FA.OE3.GR.01 | C9: Físico Ambiental | D9: AMBIENTAL | E9: Gestión del Riesgo | F9: Infraestructura de mitigación + Zonas evacuación | G9: Gestión del riesgo: reforestación quebradas + señalética + sistema alerta temprana | H9: Reforestación zonas susceptibles amenazas / Sistema integrado alerta temprana | I9: Reducir el riesgo fortaleciendo la infraestructura y mejorando la resiliencia | J9: 950000 | K9: No | L9: — | M9: ⚠️ PARCIAL | N9: Candidato próxima muestra — Ri=1.5 resiliencia climática
A10: 6 | B10: PDOT.FA.OE4.AH.01 | C10: Físico Ambiental | D10: AMBIENTAL | E10: Aseo e Higiene | F10: Recolección de desechos sólidos | G10: Gestión integral desechos sólidos: recolección y transporte | H10: Repotenciación y adquisición de recolectores de basura | I10: Promover prácticas sostenibles de manejo de desechos | J10: 5001962.8 | K10: No | L10: — | M10: ✅ ALINEADA | N10: EP Aseo gestiona — candidato muestra futura
A11: 7 | B11: PDOT.FA.OE4.AH.02 | C11: Físico Ambiental | D11: AMBIENTAL | E11: Aseo e Higiene | F11: Tratamiento de desechos — Relleno Sanitario | G11: Nuevo relleno sanitario cantonal — construcción y operación EP Aseo | H11: Construcción nuevo relleno sanitario cantón Montecristi | I11: Promover prácticas sostenibles de manejo de desechos | J11: 748782.57 | K11: ✅ Sí | L11: PDOT.AM.OE3.M2.01 | M11: ⚠️ PARCIAL | N11: M12 en muestra — Vi=1 Ti=0.30 — regularización MAATE
A12: 8 | B12: PDOT.AS.OE1.AP.01 | C12: Asentamientos Humanos | D12: TERRITORIAL | E12: Agua y saneamiento | F12: Agua Potable — Redes + Acueducto CAF | G12: Cobertura agua potable: ampliación redes + Acueducto CAF 30.000m³/día — mayor ítem PDOT | H12: Gestión Construcción Acueducto CAF $45.6M — 30.000m³/día | I12: Ampliar y mejorar la cobertura de equipamientos, áreas verdes y servicios básicos | J12: 46904874 | K12: ✅ Sí | L12: PDOT.AS.OE1.M1.01 | M12: ✅ ALINEADA | N12: M1 en muestra — Pi=0.112 — Vi=1 Ti=0.85 — CAF contraparte
A13: 9 | B13: PDOT.AS.OE1.AP.02 | C13: Asentamientos Humanos | D13: TERRITORIAL | E13: Agua y saneamiento | F13: Agua Potable — Reservorios y Captación Rural | G13: Reservorios y captación agua rural: tanques reserva comunas + continuidad servicio | H13: Nueva infraestructura captación y tratamiento agua — reservorios rurales | I13: Ampliar y mejorar la cobertura de servicios básicos | J13: 0 | K13: ✅ Sí | L13: PDOT.AS.OE1.M1.03 | M13: 🔴 BAJA | N13: M20 en muestra — Ti=0.25 — BDE reservorios rurales
A14: 10 | B14: PDOT.AS.OE1.SN.01 | C14: Asentamientos Humanos | D14: TERRITORIAL | E14: Agua y saneamiento | F14: Saneamiento — Alcantarillado + PTAR | G14: Alcantarillado sanitario: Fase I PROGAPSA + Colector Principal + PTAR | H14: Fase I Alcantarillado BEI-PROGAPSA + PTAR Montecristi | I14: Ampliar y mejorar la cobertura de servicios básicos | J14: 1269859.5 | K14: ✅ Sí | L14: PDOT.AS.OE1.M1.02 | M14: ✅ ALINEADA | N14: M2 en muestra — Pi=0.231 — mayor Pi — BDE-PROGAPSA
A15: 11 | B15: PDOT.FA.OE4.PT.01 | C15: F. Ambiental / As. Humanos | D15: AMBIENTAL | E15: Agua y saneamiento / Ambiente | F15: PTAR — Planta de Tratamiento de Aguas Residuales | G15: PTAR: Planta Tratamiento Aguas Residuales Montecristi + Aníbal San Andrés | H15: Construcción Colector Principal y PTAR Montecristi + Aníbal San Andrés (CELEC/BDE) | I15: Gestión integral de aguas residuales — componente ambiental crítico | J15: 0 | K15: ✅ Sí | L15: PDOT.AM.OE3.M1.01 | M15: ⚠️ PARCIAL | N15: M9 en muestra — Pi=0.045 — Ti=0.40 — CELEC/BDE PTAR
A16: 12 | B16: PDOT.AS.OE1.PL.01 | C16: Asentamientos Humanos | D16: TERRITORIAL | E16: Agua y saneamiento | F16: Pluvial — Redes de drenaje urbano | G16: Redes pluviales: estudios técnicos para ampliación de cobertura | H16: Estudios técnicos proyección nuevas redes pluviales urbanas | I16: Ampliar y mejorar la cobertura de servicios básicos | J16: 10000 | K16: No | L16: — | M16: ⚠️ PARCIAL | N16: Presupuesto mínimo — solo estudios — complementa M1+M2
... A39: 35 | B39: PDOT.PI.OE6.PC.01 | C39: Político Institucional | D39: INSTITUCIONAL | E39: Participación y cogestión ciudadana | F39: Construcción participativa ciudadana | G39: Participación ciudadana: asambleas + cabildo + rendición cuentas + cogestión | H39: Sistema construcción participativa planificación + Rendición Cuentas CPCCS | I39: Fomentar la participación ciudadana y la construcción colaborativa | J39: 137900 | K39: No | L39: — | M39: ✅ ALINEADA | N39: Vinculado LOTAIP Art.7 lit.m y CPCCS — rendición cuentas
A40: Σ | B40: TOTALES UNIVERSO · 35 programas/proyectos en 5 sistemas
A41: 🔷 SECCIÓN B — MUESTRA SIAP-ICPI · n=20 Metas Estratégicas · Datos oficiales PDOT Plan Bicentenario 2023-2027 · Fuente: Plan Plurianual Inversiones + PAC 2023-2024 · Pi = Presup_i / ΣPresup (fuente maestra: PDOT!L4:L23)
A42: Nº | B42: CÓD. PDOT (Oficial) | C42: SISTEMA PDOT | D42: META ESTRATÉGICA PDOT (descripción oficial) | E42: Pi (peso pres.) | F42: Ri (relevancia) | G42: Vi (evidencia) | H42: Ti (ejecución) | I42: PROYECTO ESTRATÉGICO PDOT (descripción sintética) | J42: PRESUP. PDOT ($) (fuente: PDOT!L) | K42: INDICADOR META 2027 (oficial PDOT) | L42: RESPONSABLE INSTITUCIONAL | M42: ALINEACIÓN PDOT | N42: ESTADO POA 2025 / RECOMENDACIÓN
A43: 1 | B43: ='M2-PDOT'!B4 -> PDOT.AS.VL.M1.01 | C43: ='M2-PDOT'!C4 -> Asentamientos Humanos | D43: ='M2-PDOT'!D4 -> Mantenimiento de vías urbanas para el acceso de los barrios del cantón | E43: ='M2-PDOT'!E4 -> 0.33155843 | F43: ='M2-PDOT'!F4 -> 1 | G43: ='M2-PDOT'!G4 -> 1 | H43: ='M2-PDOT'!H4 -> 0.25 | I43: Integración ejes viales estratégicos — bacheo, pavimentación y mantenimiento vías urbanas y rurales | J43: ='M2-PDOT'!L4 -> 10892761 | K43: Kilómetros de vías intervenidas / mantenidas por año | L43: ='M2-PDOT'!K4 -> Dir. Obras Públicas | M43: ='M2-PDOT'!N4 -> ✅ ALINEADA | N43: Vi=1 Ti=0.90 ✅ — PAC $3.1M ejecutado — Pi=0.330 mayor muestra
A44: 2 | B44: ='M2-PDOT'!B5 -> PDOT.SC.OE2.M1.01 | C44: ='M2-PDOT'!C5 -> Socio Cultural | D44: ='M2-PDOT'!D5 -> Desarrollo del Bienestar Integral para Montecristi | E44: ='M2-PDOT'!E5 -> 0.17737919 | F44: ='M2-PDOT'!F5 -> 1 | G44: ='M2-PDOT'!G5 -> 1 | H44: ='M2-PDOT'!H5 -> 0.65 | I44: Centro de Salud Tipo C «Nacer Aquí» + Repotenciación Clínica de Diálisis — gestión convenio MSP-ULEAM | J44: ='M2-PDOT'!L5 -> 5827477 | K44: % avance físico construcción / convenio MSP suscrito | L44: ='M2-PDOT'!K5 -> Patronato Municipal | M44: ='M2-PDOT'!N5 -> ✅ ALINEADA | N44: Vi=0 CRÍTICO — convenio MSP pendiente — Δ ICPI +9.1pp si Vi→1
A45: 3 | B45: ='M2-PDOT'!B6 -> PDOT.AM.OE3.M2.01 | C45: ='M2-PDOT'!C6 -> Ambiental | D45: ='M2-PDOT'!D6 -> Gestión Integral de Desechos Sólidos | E45: ='M2-PDOT'!E6 -> 0.15225184 | F45: ='M2-PDOT'!F6 -> 1 | G45: ='M2-PDOT'!G6 -> 1 | H45: ='M2-PDOT'!H6 -> 0.75 | I45: Gestión integral desechos sólidos: recolección, transporte y relleno sanitario — Empresa de Aseo Municipal EP | J45: ='M2-PDOT'!L6 -> 5001962.8 | K45: Toneladas procesadas por año / cobertura recolección cantonal | L45: ='M2-PDOT'!K6 -> Dir. Gestión Ambiental | M45: ='M2-PDOT'!N6 -> ✅ ALINEADA | N45: Vi=1 Ti=0.30 — Ordenanza Aseo sancionada — iniciar MAATE
A46: 4 | B46: ='M2-PDOT'!B7 -> PDOT.AS.OE1.M2.01 | C46: ='M2-PDOT'!C7 -> Asentamientos Humanos | D46: ='M2-PDOT'!D7 -> Fortalecimiento estratégico de equipamiento público comercial y administrativo | E46: ='M2-PDOT'!E7 -> 0.051556596 | F46: ='M2-PDOT'!F7 -> 1 | G46: ='M2-PDOT'!G7 -> 0 | H46: ='M2-PDOT'!H7 -> 0.1 | I46: Terminal Terrestre Ciudad Bicentenario + Estación Bomberil Chirijos + Infocentros | J46: ='M2-PDOT'!L7 -> 1693800 | K46: % avance físico construcción / índice equipamiento urbano CUP | L46: ='M2-PDOT'!K7 -> Dir. Planificación | M46: ='M2-PDOT'!N7 -> ⚠️ PARCIAL | N46: Vi=1 Ti=0.45 — estudios diseño POA 2025 — RDC 2023
A47: 5 | B47: ='M2-PDOT'!B8 -> PDOT.SC.OE2.M4.01 | C47: ='M2-PDOT'!C8 -> Socio Cultural | D47: ='M2-PDOT'!D8 -> Proyecto Integral de Desarrollo y Apoyo Comunitario | E47: ='M2-PDOT'!E8 -> 0.049038304 | F47: ='M2-PDOT'!F8 -> 1 | G47: ='M2-PDOT'!G8 -> 1 | H47: ='M2-PDOT'!H8 -> 0.2 | I47: CDI + Guarderías Nocturnas + Montecristi Solidario — Protección derechos grupos vulnerables | J47: ='M2-PDOT'!L8 -> 1611066 | K47: % avance físico / Nº beneficiarios grupos vulnerables atendidos | L47: ='M2-PDOT'!K8 -> Dir. Planificación | M47: ='M2-PDOT'!N8 -> ⚠️ PARCIAL | N47: Vi=0 Ti=0 CRÍTICO — convenio MIES CIBV nocturno pendiente
A48: 6 | B48: ='M2-PDOT'!B9 -> PDOT.AS.OE1.M1.02 | C48: ='M2-PDOT'!C9 -> Asentamientos Humanos | D48: ='M2-PDOT'!D9 -> Gestión para la construcción de nueva infraestructura de tratamiento de aguas residuales | E48: ='M2-PDOT'!E9 -> 0.038652516 | F48: ='M2-PDOT'!F9 -> 1.5 | G48: ='M2-PDOT'!G9 -> 0 | H48: ='M2-PDOT'!H9 -> 0 | I48: Fase I Alcantarillado BDE-PROGAPSA + Colector Principal + PTAR Montecristi | J48: ='M2-PDOT'!L9 -> 1269859.5 | K48: Metros lineales de red construida / % cobertura alcantarillado cantonal | L48: ='M2-PDOT'!K9 -> Dir. Agua Potable y Alcantarillado | M48: ='M2-PDOT'!N9 -> 🔴 BAJA | N48: Vi=1 Ti=0.75 — BDE-PROGAPSA activar Fase I
A49: 7 | B49: ='M2-PDOT'!B10 -> PDOT.PI.OE4.M1.01 | C49: ='M2-PDOT'!C10 -> Político Institucional | D49: ='M2-PDOT'!D10 -> Implementación de la Transformación digital de los procedimientos institucionales | E49: ='M2-PDOT'!E10 -> 0.037123042 | F49: ='M2-PDOT'!F10 -> 1 | G49: ='M2-PDOT'!G10 -> 1 | H49: ='M2-PDOT'!H10 -> 1 | I49: Transformación digital trámites + Catastro Integrado alfanumérico-gráfico + WiFi público + ERP municipal | J49: ='M2-PDOT'!L10 -> 1219611.3 | K49: % digitalización trámites / nivel conocimiento gestión municipal al 55% | L49: ='M2-PDOT'!K10 -> Dir. TICs | M49: ='M2-PDOT'!N10 -> ✅ ALINEADA | N49: Vi=1 Ti=0.70 ✅ — ERP $636K ejecutado — plataforma ciudadana pendiente
A50: 8 | B50: ='M2-PDOT'!B11 -> PDOT.AV.OE1.M1.01 | C50: ='M2-PDOT'!C11 -> Asentamientos Humanos | D50: ='M2-PDOT'!D11 -> Recuperación integral de los espacios públicos | E50: ='M2-PDOT'!E11 -> 0.027234953 | F50: ='M2-PDOT'!F11 -> 1 | G50: ='M2-PDOT'!G11 -> 1 | H50: ='M2-PDOT'!H11 -> 0.9 | I50: Parque Las Pampas Fase I + Red Verde + canchas recreativas — Recuperación espacios públicos | J50: ='M2-PDOT'!L11 -> 894755.8 | K50: Índice verde urbano / Nº parques nuevos construidos | L50: ='M2-PDOT'!K11 -> Dir. Planificación | M50: ='M2-PDOT'!N11 -> ✅ ALINEADA | N50: Vi=1 Ti=0.50 — Parque Las Pampas Fase I en POA 2025
A51: 9 | B51: ='M2-PDOT'!B12 -> PDOT.AM.OE3.M1.01 | C51: ='M2-PDOT'!C12 -> Ambiental | D51: ='M2-PDOT'!D12 -> Implementación de Infraestructura civil para la mitigación y reducción de impactos ante la susceptib | E51: ='M2-PDOT'!E12 -> 0.025568273 | F51: ='M2-PDOT'!F12 -> 1.5 | G51: ='M2-PDOT'!G12 -> 0 | H51: ='M2-PDOT'!H12 -> 0.3 | I51: Construcción Colector Principal y PTAR Montecristi + Aníbal San Andrés — financiamiento CELEC/BDE | J51: ='M2-PDOT'!L12 -> 840000 | K51: Nº plantas y estaciones de bombeo operativas / % avance PTAR | L51: ='M2-PDOT'!K12 -> Dir. Planificación | M51: ='M2-PDOT'!N12 -> 🔴 BAJA | N51: Vi=1 Ti=0.40 — CELEC/BDE gestionar — estudios PTAR POA 2025
A52: 10 | B52: ='M2-PDOT'!B13 -> PDOT.FA.OE4.AH.02 | C52: ='M2-PDOT'!C13 -> Físico Ambiental | D52: ='M2-PDOT'!D13 -> Mejorando la capacidad de disposición final de desechos sólidos | E52: ='M2-PDOT'!E13 -> 0.022791758 | F52: ='M2-PDOT'!F13 -> 1 | G52: ='M2-PDOT'!G13 -> 1 | H52: ='M2-PDOT'!H13 -> 0.4 | I52: Nuevo relleno sanitario cantonal — construcción y operación EP Aseo — regularización MAATE | J52: ='M2-PDOT'!L13 -> 748782.57 | K52: Capacidad disposición final (toneladas/año) / proceso MAATE iniciado | L52: ='M2-PDOT'!K13 -> Dir. Gestión Ambiental | M52: ='M2-PDOT'!N13 -> ⚠️ PARCIAL | N52: Vi=1 Ti=0.30 — proceso MAATE pendiente — EIA en POA 2025
A53: 11 | B53: ='M2-PDOT'!B14 -> PDOT.FA.OE1.PV.01 | C53: ='M2-PDOT'!C14 -> Físico Ambiental | D53: ='M2-PDOT'!D14 -> Desarrollo de la red Verde y recuperación del espacio público | E53: ='M2-PDOT'!E14 -> 0.018567422 | F53: ='M2-PDOT'!F14 -> 1 | G53: ='M2-PDOT'!G14 -> 1 | H53: ='M2-PDOT'!H14 -> 0.5 | I53: Red Verde urbana: Parque Las Pampas + Parque Cárcel Simón Bolívar + Parque Estancia Las Palmas | J53: ='M2-PDOT'!L14 -> 609999.54 | K53: Índice verde urbano consolidado / Hectáreas nuevas áreas protegidas | L53: ='M2-PDOT'!K14 -> Dir. Gestión Ambiental | M53: ='M2-PDOT'!N14 -> ⚠️ PARCIAL | N53: Vi=1 Ti=0.50 — incluir POA 2025 como IE PDOT — complementa M8
A54: 12 | B54: ='M2-PDOT'!B15 -> PDOT.PI.OE4.M2.01 | C54: ='M2-PDOT'!C15 -> Político Institucional | D54: ='M2-PDOT'!D15 -> Fortalecimiento del Sistema de Información Territorial Municipal | E54: ='M2-PDOT'!E15 -> 0.018292146 | F54: ='M2-PDOT'!F15 -> 1 | G54: ='M2-PDOT'!G15 -> 0 | H54: ='M2-PDOT'!H15 -> 0 | I54: SIT Municipal + LIDAR + geomática institucional — Catastro Integrado alfanumérico-gráfico | J54: ='M2-PDOT'!L15 -> 600955.83 | K54: % actualización catastral / cobertura SIG cantonal | L54: ='M2-PDOT'!K15 -> Dir. TICs | M54: ='M2-PDOT'!N15 -> 🔴 BAJA | N54: Vi=1 Ti=1.0 ✅ CUMPLIDA — LIDAR $250K — integrar en SIG
... A62: 20 | B62: ='M2-PDOT'!B23 -> PDOT.FA.OE2.MA.01 | C62: ='M2-PDOT'!C23 -> 0 | D62: ='M2-PDOT'!D23 -> 0 | E62: ='M2-PDOT'!E23 -> 0 | F62: ='M2-PDOT'!F23 -> 0 | G62: ='M2-PDOT'!G23 -> 0 | H62: ='M2-PDOT'!H23 -> 0 | I62: Albergue/Centro recuperación fauna urbana + Ordenanza Nº017-2024 — componente manglar y biodiversidad | J62: ='M2-PDOT'!L23 -> 0 | K62: Nº animales atendidos / castraciones realizadas / ordenanza vigente | L62: ='M2-PDOT'!K23 -> 0 | M62: ='M2-PDOT'!N23 -> 0 | N62: Vi=1 Ti=0.35 — 172 castraciones + Ordenanza 017-2024 — vincular Manglar
A63: Σ | B63: TOTALES MUESTRA · n=20 metas · ΣPi = 1.000 ✅ · Fuente maestra: PDOT hoja
A64: 📋 | B64: CRITERIO DE EXCLUSIÓN (COOTAD Art. 234 · COPYFP Art. 292)

Sheet M2-PDOT
A1: QUADRUM v1.0 · M2-PDOT · Base Legal Operativa de Metas PDOT 2023-2027 · GAD Municipal Montecristi
A2: =HYPERLINK("#'M-INDEX'!A1","⌂ INDICE") -> ⌂ INDICE | B2: =HYPERLINK("#'M1-ITME'!A1","M1") -> M1 | C2: =HYPERLINK("#'M2-PDOT'!A1","◉ M2-PDOT") -> ◉ M2-PDOT | D2: =HYPERLINK("#'M3-MAO'!A1","M3") -> M3 | E2: =HYPERLINK("#'M4-AUDIT'!A1","M4") -> M4 | F2: =HYPERLINK("#'M5-ICPI'!A1","M5") -> M5 | G2: =HYPERLINK("#'M6-FEDS'!A1","M6") -> M6 | H2: =HYPERLINK("#'M7-PROSP'!A1","M7") -> M7 | I2: =HYPERLINK("#'DATA-POA'!A1","DATA-POA") -> DATA-POA | J2: =HYPERLINK("#'DATA-CNE'!A1","DATA-CNE") -> DATA-CNE | K2: =HYPERLINK("#'DATA-ORG'!A1","DATA-ORG") -> DATA-ORG | L2: =HYPERLINK("#'M-DASHBOARD'!A1","DASH") -> DASH
A3: Capa: Base/Plan > Metas Estratégicas PDOT Plan Bicentenario 2023-2027 · Base: COOTAD Art.295 | B3: CÓD. PDOT / ID_META | C3: SISTEMA | D3: META ESTRATÉGICA | E3: Pi | F3: Ri | G3: Vi | H3: Ti | I3: Ci | J3: Ei | K3: RESPONSABLE | L3: PRESUPUESTO | M3: INDICADOR | N3: ALINEACIÓN PDOT
A4: 1 | B4: PDOT.AS.VL.M1.01 | C4: Asentamientos Humanos | D4: Mantenimiento de vías urbanas para el acceso de los barrios del cantón | E4: =L4/L$24 -> 0.33155843 | F4: 1 | G4: =IFERROR(VLOOKUP(B4,'M4-AUDIT'!$A$5:$H$24,MATCH("Vi",'M4-AUDIT'!$A$4:$H$4,0),0),0) -> 1 | H4: =IFERROR(VLOOKUP(B4,'M4-AUDIT'!$A$5:$H$24,MATCH("Ti (H)",'M4-AUDIT'!$A$4:$H$4,0),0),0) -> 0.25 | I4: 1 | J4: 1 | K4: Dir. Obras Públicas | L4: 10892761 | M4: Kilómetros de vías intervenidas | N4: ✅ ALINEADA
A5: 2 | B5: PDOT.SC.OE2.M1.01 | C5: Socio Cultural | D5: Desarrollo del Bienestar Integral para Montecristi | E5: =L5/L$24 -> 0.17737919 | F5: 1 | G5: =IFERROR(VLOOKUP(B5,'M4-AUDIT'!$A$5:$H$24,MATCH("Vi",'M4-AUDIT'!$A$4:$H$4,0),0),0) -> 1 | H5: =IFERROR(VLOOKUP(B5,'M4-AUDIT'!$A$5:$H$24,MATCH("Ti (H)",'M4-AUDIT'!$A$4:$H$4,0),0),0) -> 0.65 | I5: 0.9 | J5: 1 | K5: Patronato Municipal | L5: 5827477 | M5: Porcentaje de avance físico | N5: ✅ ALINEADA
A6: 3 | B6: PDOT.AM.OE3.M2.01 | C6: Ambiental | D6: Gestión Integral de Desechos Sólidos | E6: =L6/L$24 -> 0.15225184 | F6: 1 | G6: =IFERROR(VLOOKUP(B6,'M4-AUDIT'!$A$5:$H$24,MATCH("Vi",'M4-AUDIT'!$A$4:$H$4,0),0),0) -> 1 | H6: =IFERROR(VLOOKUP(B6,'M4-AUDIT'!$A$5:$H$24,MATCH("Ti (H)",'M4-AUDIT'!$A$4:$H$4,0),0),0) -> 0.75 | I6: 1 | J6: 1 | K6: Dir. Gestión Ambiental | L6: 5001962.8 | M6: Toneladas procesadas/año | N6: ✅ ALINEADA
A7: 4 | B7: PDOT.AS.OE1.M2.01 | C7: Asentamientos Humanos | D7: Fortalecimiento estratégico de equipamiento público comercial y administrativo | E7: =L7/L$24 -> 0.051556596 | F7: 1 | G7: =IFERROR(VLOOKUP(B7,'M4-AUDIT'!$A$5:$H$24,MATCH("Vi",'M4-AUDIT'!$A$4:$H$4,0),0),0) -> 0 | H7: =IFERROR(VLOOKUP(B7,'M4-AUDIT'!$A$5:$H$24,MATCH("Ti (H)",'M4-AUDIT'!$A$4:$H$4,0),0),0) -> 0.1 | I7: 1 | J7: 1 | K7: Dir. Planificación | L7: 1693800 | M7: Porcentaje de avance físico | N7: ⚠️ PARCIAL
A8: 5 | B8: PDOT.SC.OE2.M4.01 | C8: Socio Cultural | D8: Proyecto Integral de Desarrollo y Apoyo Comunitario | E8: =L8/L$24 -> 0.049038304 | F8: 1 | G8: =IFERROR(VLOOKUP(B8,'M4-AUDIT'!$A$5:$H$24,MATCH("Vi",'M4-AUDIT'!$A$4:$H$4,0),0),0) -> 1 | H8: =IFERROR(VLOOKUP(B8,'M4-AUDIT'!$A$5:$H$24,MATCH("Ti (H)",'M4-AUDIT'!$A$4:$H$4,0),0),0) -> 0.2 | I8: 1 | J8: 1 | K8: Dir. Planificación | L8: 1611066 | M8: Porcentaje de avance físico | N8: ⚠️ PARCIAL
A9: 6 | B9: PDOT.AS.OE1.M1.02 | C9: Asentamientos Humanos | D9: Gestión para la construcción de nueva infraestructura de tratamiento de aguas residuales | E9: =L9/L$24 -> 0.038652516 | F9: 1.5 | G9: =IFERROR(VLOOKUP(B9,'M4-AUDIT'!$A$5:$H$24,MATCH("Vi",'M4-AUDIT'!$A$4:$H$4,0),0),0) -> 0 | H9: =IFERROR(VLOOKUP(B9,'M4-AUDIT'!$A$5:$H$24,MATCH("Ti (H)",'M4-AUDIT'!$A$4:$H$4,0),0),0) -> 0 | I9: 1 | J9: 1 | K9: Dir. Agua Potable y Alcantarillado | L9: 1269859.5 | M9: Metros lineales de red construida | N9: 🔴 BAJA
A10: 7 | B10: PDOT.PI.OE4.M1.01 | C10: Político Institucional | D10: Implementación de la Transformación digital de los procedimientos institucionales | E10: =L10/L$24 -> 0.037123042 | F10: 1 | G10: =IFERROR(VLOOKUP(B10,'M4-AUDIT'!$A$5:$H$24,MATCH("Vi",'M4-AUDIT'!$A$4:$H$4,0),0),0) -> 1 | H10: =IFERROR(VLOOKUP(B10,'M4-AUDIT'!$A$5:$H$24,MATCH("Ti (H)",'M4-AUDIT'!$A$4:$H$4,0),0),0) -> 1 | I10: 1 | J10: 1 | K10: Dir. TICs | L10: 1219611.3 | M10: Porcentaje de avance físico | N10: ✅ ALINEADA
A11: 8 | B11: PDOT.AV.OE1.M1.01 | C11: Asentamientos Humanos | D11: Recuperación integral de los espacios públicos | E11: =L11/L$24 -> 0.027234953 | F11: 1 | G11: =IFERROR(VLOOKUP(B11,'M4-AUDIT'!$A$5:$H$24,MATCH("Vi",'M4-AUDIT'!$A$4:$H$4,0),0),0) -> 1 | H11: =IFERROR(VLOOKUP(B11,'M4-AUDIT'!$A$5:$H$24,MATCH("Ti (H)",'M4-AUDIT'!$A$4:$H$4,0),0),0) -> 0.9 | I11: 1 | J11: 1 | K11: Dir. Planificación | L11: 894755.8 | M11: Porcentaje de avance físico | N11: ✅ ALINEADA
A12: 9 | B12: PDOT.AM.OE3.M1.01 | C12: Ambiental | D12: Implementación de Infraestructura civil para la mitigación y reducción de impactos ante la susceptib | E12: =L12/L$24 -> 0.025568273 | F12: 1.5 | G12: =IFERROR(VLOOKUP(B12,'M4-AUDIT'!$A$5:$H$24,MATCH("Vi",'M4-AUDIT'!$A$4:$H$4,0),0),0) -> 0 | H12: =IFERROR(VLOOKUP(B12,'M4-AUDIT'!$A$5:$H$24,MATCH("Ti (H)",'M4-AUDIT'!$A$4:$H$4,0),0),0) -> 0.3 | I12: 1 | J12: 1 | K12: Dir. Planificación | L12: 840000 | M12: Porcentaje de avance físico | N12: 🔴 BAJA
A13: 10 | B13: PDOT.FA.OE4.AH.02 | C13: Físico Ambiental | D13: Mejorando la capacidad de disposición final de desechos sólidos | E13: =L13/L$24 -> 0.022791758 | F13: 1 | G13: =IFERROR(VLOOKUP(B13,'M4-AUDIT'!$A$5:$H$24,MATCH("Vi",'M4-AUDIT'!$A$4:$H$4,0),0),0) -> 1 | H13: =IFERROR(VLOOKUP(B13,'M4-AUDIT'!$A$5:$H$24,MATCH("Ti (H)",'M4-AUDIT'!$A$4:$H$4,0),0),0) -> 0.4 | I13: 1 | J13: 1 | K13: Dir. Gestión Ambiental | L13: 748782.57 | M13: Toneladas procesadas/año | N13: ⚠️ PARCIAL
A14: 11 | B14: PDOT.FA.OE1.PV.01 | C14: Físico Ambiental | D14: Desarrollo de la red Verde y recuperación del espacio público | E14: =L14/L$24 -> 0.018567422 | F14: 1 | G14: =IFERROR(VLOOKUP(B14,'M4-AUDIT'!$A$5:$H$24,MATCH("Vi",'M4-AUDIT'!$A$4:$H$4,0),0),0) -> 1 | H14: =IFERROR(VLOOKUP(B14,'M4-AUDIT'!$A$5:$H$24,MATCH("Ti (H)",'M4-AUDIT'!$A$4:$H$4,0),0),0) -> 0.5 | I14: 1 | J14: 1 | K14: Dir. Gestión Ambiental | L14: 609999.54 | M14: Porcentaje de avance físico | N14: ⚠️ PARCIAL
A15: 12 | B15: PDOT.PI.OE4.M2.01 | C15: Político Institucional | D15: Fortalecimiento del Sistema de Información Territorial Municipal | E15: =L15/L$24 -> 0.018292146 | F15: 1 | G15: =IFERROR(VLOOKUP(B15,'M4-AUDIT'!$A$5:$H$24,MATCH("Vi",'M4-AUDIT'!$A$4:$H$4,0),0),0) -> 0 | H15: =IFERROR(VLOOKUP(B15,'M4-AUDIT'!$A$5:$H$24,MATCH("Ti (H)",'M4-AUDIT'!$A$4:$H$4,0),0),0) -> 0 | I15: 1 | J15: 1 | K15: Dir. TICs | L15: 600955.83 | M15: Porcentaje de avance físico | N15: 🔴 BAJA
... A22: 19 | B22: PDOT.SC.OE2.M2.01 | C22: Socio Cultural | D22: Fortalecimiento para la reducción de indicadores territoriales del cantón Montecristi relacionados a | E22: =L22/L$24 -> 0.0043831325 | F22: 1 | G22: =IFERROR(VLOOKUP(B22,'M4-AUDIT'!$A$5:$H$24,MATCH("Vi",'M4-AUDIT'!$A$4:$H$4,0),0),0) -> 1 | H22: =IFERROR(VLOOKUP(B22,'M4-AUDIT'!$A$5:$H$24,MATCH("Ti (H)",'M4-AUDIT'!$A$4:$H$4,0),0),0) -> 0.3 | I22: 1 | J22: 1 | K22: Dir. Planificación | L22: 144000 | M22: Porcentaje de avance físico | N22: ⚠️ PARCIAL
A23: 20 | B23: PDOT.FA.OE2.MA.01
A24: Σ | B24: TOTAL MUESTRA · n=20 | L24: =SUM(L4:L23) -> 32853216
A25: Σ | B25: TOTALES · n=20 · Muestra Estratégica SIAP-ICPI | C25: ΣPi Validación: | D25: =IF(ABS(E24-1)<0.0001,"✅ ΣPi=1.000","❌ ERROR") -> ❌ ERROR | E25: ΣPi = 1.000 | F25: — | G25: ="Vi=1: "&COUNTIF(G4:G23,1)&" · Vi=0: "&COUNTIF(G4:G23,0) -> Vi=1: 14 · Vi=0: 5 | H25: ="Tī = "&ROUND(AVERAGE(H4:H23),3) -> Tī = 0,468 | I25: — | J25: — | K25: — | L25: — | M25: $107.9M+ PDOT | N25: ✅×10 / ⚠️×6 / 🔴×4

Sheet M2-PLAN-Pi
A1: QUADRUM v1.0 · M2-PLAN-Pi · Ponderación Pi · Presupuesto PDOT 2023-2027 · ΣPi=1.000
A2: =HYPERLINK("#'M-INDEX'!A1","⌂ INDICE") -> ⌂ INDICE | B2: =HYPERLINK("#'M1-ITME'!A1","M1") -> M1 | C2: =HYPERLINK("#'M2-PDOT'!A1","M2") -> M2 | D2: =HYPERLINK("#'M3-MAO'!A1","M3") -> M3 | E2: =HYPERLINK("#'M4-AUDIT'!A1","M4") -> M4 | F2: =HYPERLINK("#'M5-ICPI'!A1","M5") -> M5 | G2: =HYPERLINK("#'M6-FEDS'!A1","M6") -> M6 | H2: =HYPERLINK("#'M7-PROSP'!A1","M7") -> M7 | I2: =HYPERLINK("#'DATA-POA'!A1","DATA-POA") -> DATA-POA | J2: =HYPERLINK("#'DATA-CNE'!A1","DATA-CNE") -> DATA-CNE | K2: =HYPERLINK("#'DATA-ORG'!A1","DATA-ORG") -> DATA-ORG | L2: =HYPERLINK("#'M-DASHBOARD'!A1","DASH") -> DASH
A3: Capa: Motor ICPI > Ponderación de Variables · Factores Pi por Meta Estratégica
A4: EJE ESTRATÉGICO PDOT | B4: N° METAS (n=20) | C4: PRESUPUESTO PDOT TOTAL ($) | D4: PI AGREGADO POR EJE | E4: SISTEMA PDOT | F4: PROGRAMAS PRINCIPALES | G4: FUENTE PRESUPUESTO | H4: ESTADO
A5: TERRITORIAL | B5: 9 | C5: 116297389 | D5: 0.8935 | E5: Asentamientos Humanos + Vialidad | F5: Agua Potable · Alcantarillado · Vialidad · Equipamientos | G5: PDOT pág. 370-440 · PAC 2023-2024 | H5: ✅ Base PDOT
A6: SOCIAL | B6: 6 | C6: 1811700 | D6: 0.0139 | E6: Socio Cultural | F6: Derechos en Acción · Montecristi Solidario | G6: PDOT pág. 380-395 · POA 2023-2025 | H6: ✅ Base PDOT
A7: AMBIENTAL | B7: 2 | C7: 748783 | D7: 0.0058 | E7: Factor Ambiental | F7: Aseo e Higiene · Tratamiento desechos | G7: PDOT pág. 400-415 · PAC EP Aseo 2023 | H7: ✅ Base PDOT
A8: ECONÓMICO | B8: 1 | C8: 0 | D8: 0 | E8: Económico Productivo | F8: Turismo · Desarrollo recursos | G8: PDOT pág. 385-400 · Convenio MINTUR | H8: ⚠️ Sin presup. PDOT asignado
A9: INSTITUCIONAL | B9: 2 | C9: 0 | D9: 0 | E9: Político Institucional | F9: Fortalecimiento Inst. · TIC | G9: PDOT pág. 385-392 · POA 2023 | H9: ⚠️ Sin presup. PDOT asignado
A10: Σ TOTAL · n=20 METAS
A11: 🔷 SECCIÓN B — PONDERACIÓN Pi INDIVIDUAL POR META PDOT · Pi = Presup_i ÷ Σ(Presup_n=20) · ΣPi=1.000 ✅ · Usado directamente en E1-ICPI
A12: Nº | B12: CÓDIGO PDOT | C12: DESCRIPCIÓN SINTÉTICA | D12: EJE | E12: PRESUP. PDOT ($) | F12: Pi ACTUAL | G12: ORIGEN Pi | H12: NOTA
A13: Nº | B13: CÓDIGO PDOT | C13: DESCRIPCIÓN SINTÉTICA | D13: SISTEMA | E13: PRESUP. PDOT ($) | F13: Pi (= Presup / Σ) | G13: ORIGEN Pi | H13: NOTA
A14: 1 | B14: ='M2-PDOT'!B4 -> PDOT.AS.VL.M1.01 | C14: ='M2-PDOT'!D4 -> Mantenimiento de vías urbanas para el acceso de los barrios del cantón | D14: ='M2-PDOT'!C4 -> Asentamientos Humanos | E14: ='M2-PDOT'!L4 -> 10892761 | F14: ='M2-PDOT'!E4 -> 0.33155843 | G14: Pi = PDOT!L4 / PDOT!L24 | H14: Fuente maestra: PDOT hoja · ratio presupuestario
A15: 2 | B15: ='M2-PDOT'!B5 -> PDOT.SC.OE2.M1.01 | C15: ='M2-PDOT'!D5 -> Desarrollo del Bienestar Integral para Montecristi | D15: ='M2-PDOT'!C5 -> Socio Cultural | E15: ='M2-PDOT'!L5 -> 5827477 | F15: ='M2-PDOT'!E5 -> 0.17737919 | G15: Pi = PDOT!L5 / PDOT!L24 | H15: Fuente maestra: PDOT hoja
A16: 3 | B16: ='M2-PDOT'!B6 -> PDOT.AM.OE3.M2.01 | C16: ='M2-PDOT'!D6 -> Gestión Integral de Desechos Sólidos | D16: ='M2-PDOT'!C6 -> Ambiental | E16: ='M2-PDOT'!L6 -> 5001962.8 | F16: ='M2-PDOT'!E6 -> 0.15225184 | G16: Pi = PDOT!L6 / PDOT!L24 | H16: Fuente maestra: PDOT hoja
A17: 4 | B17: ='M2-PDOT'!B7 -> PDOT.AS.OE1.M2.01 | C17: ='M2-PDOT'!D7 -> Fortalecimiento estratégico de equipamiento público comercial y administrativo | D17: ='M2-PDOT'!C7 -> Asentamientos Humanos | E17: ='M2-PDOT'!L7 -> 1693800 | F17: ='M2-PDOT'!E7 -> 0.051556596 | G17: Pi = PDOT!L7 / PDOT!L24 | H17: Fuente maestra: PDOT hoja
A18: 5 | B18: ='M2-PDOT'!B8 -> PDOT.SC.OE2.M4.01 | C18: ='M2-PDOT'!D8 -> Proyecto Integral de Desarrollo y Apoyo Comunitario | D18: ='M2-PDOT'!C8 -> Socio Cultural | E18: ='M2-PDOT'!L8 -> 1611066 | F18: ='M2-PDOT'!E8 -> 0.049038304 | G18: Pi = PDOT!L8 / PDOT!L24 | H18: Fuente maestra: PDOT hoja
A19: 6 | B19: ='M2-PDOT'!B9 -> PDOT.AS.OE1.M1.02 | C19: ='M2-PDOT'!D9 -> Gestión para la construcción de nueva infraestructura de tratamiento de aguas residuales | D19: ='M2-PDOT'!C9 -> Asentamientos Humanos | E19: ='M2-PDOT'!L9 -> 1269859.5 | F19: ='M2-PDOT'!E9 -> 0.038652516 | G19: Pi = PDOT!L9 / PDOT!L24 | H19: Fuente maestra: PDOT hoja
A20: 7 | B20: ='M2-PDOT'!B10 -> PDOT.PI.OE4.M1.01 | C20: ='M2-PDOT'!D10 -> Implementación de la Transformación digital de los procedimientos institucionales | D20: ='M2-PDOT'!C10 -> Político Institucional | E20: ='M2-PDOT'!L10 -> 1219611.3 | F20: ='M2-PDOT'!E10 -> 0.037123042 | G20: Pi = PDOT!L10 / PDOT!L24 | H20: Fuente maestra: PDOT hoja
A21: 8 | B21: ='M2-PDOT'!B11 -> PDOT.AV.OE1.M1.01 | C21: ='M2-PDOT'!D11 -> Recuperación integral de los espacios públicos | D21: ='M2-PDOT'!C11 -> Asentamientos Humanos | E21: ='M2-PDOT'!L11 -> 894755.8 | F21: ='M2-PDOT'!E11 -> 0.027234953 | G21: Pi = PDOT!L11 / PDOT!L24 | H21: Fuente maestra: PDOT hoja
A22: 9 | B22: ='M2-PDOT'!B12 -> PDOT.AM.OE3.M1.01 | C22: ='M2-PDOT'!D12 -> Implementación de Infraestructura civil para la mitigación y reducción de impactos ante la susceptib | D22: ='M2-PDOT'!C12 -> Ambiental | E22: ='M2-PDOT'!L12 -> 840000 | F22: ='M2-PDOT'!E12 -> 0.025568273 | G22: Pi = PDOT!L12 / PDOT!L24 | H22: Fuente maestra: PDOT hoja
A23: 10 | B23: ='M2-PDOT'!B13 -> PDOT.FA.OE4.AH.02 | C23: ='M2-PDOT'!D13 -> Mejorando la capacidad de disposición final de desechos sólidos | D23: ='M2-PDOT'!C13 -> Físico Ambiental | E23: ='M2-PDOT'!L13 -> 748782.57 | F23: ='M2-PDOT'!E13 -> 0.022791758 | G23: Pi = PDOT!L13 / PDOT!L24 | H23: Fuente maestra: PDOT hoja
A24: 11 | B24: ='M2-PDOT'!B14 -> PDOT.FA.OE1.PV.01 | C24: ='M2-PDOT'!D14 -> Desarrollo de la red Verde y recuperación del espacio público | D24: ='M2-PDOT'!C14 -> Físico Ambiental | E24: ='M2-PDOT'!L14 -> 609999.54 | F24: ='M2-PDOT'!E14 -> 0.018567422 | G24: Pi = PDOT!L14 / PDOT!L24 | H24: Fuente maestra: PDOT hoja
A25: 12 | B25: ='M2-PDOT'!B15 -> PDOT.PI.OE4.M2.01 | C25: ='M2-PDOT'!D15 -> Fortalecimiento del Sistema de Información Territorial Municipal | D25: ='M2-PDOT'!C15 -> Político Institucional | E25: ='M2-PDOT'!L15 -> 600955.83 | F25: ='M2-PDOT'!E15 -> 0.018292146 | G25: Pi = PDOT!L15 / PDOT!L24 | H25: Fuente maestra: PDOT hoja
... A33: 20 | B33: ='M2-PDOT'!B23 -> PDOT.FA.OE2.MA.01 | C33: ='M2-PDOT'!D23 -> 0 | D33: ='M2-PDOT'!C23 -> 0 | E33: ='M2-PDOT'!L23 -> 0 | F33: ='M2-PDOT'!E23 -> 0 | G33: Pi = PDOT!L23 / PDOT!L24 | H33: Fuente maestra: PDOT hoja
A34: Σ | B34: TOTAL n=20 | C34: ΣPi = 1.000 ✅ | E34: =SUM(E14:E33) -> 32853216 | F34: =SUM(F14:F33) -> 1

Sheet DATA-TFR
A1: QUADRUM v1.0 · DATA-TFR · Tabla de Factores de Relevancia · Ri por Competencia COOTAD
A2: =HYPERLINK("#'M-INDEX'!A1","⌂ INDICE") -> ⌂ INDICE | B2: =HYPERLINK("#'M1-ITME'!A1","M1") -> M1 | C2: =HYPERLINK("#'M2-PDOT'!A1","M2") -> M2 | D2: =HYPERLINK("#'M3-MAO'!A1","M3") -> M3 | E2: =HYPERLINK("#'M4-AUDIT'!A1","M4") -> M4 | F2: =HYPERLINK("#'M5-ICPI'!A1","M5") -> M5 | G2: =HYPERLINK("#'M6-FEDS'!A1","M6") -> M6 | H2: =HYPERLINK("#'M7-PROSP'!A1","M7") -> M7 | I2: =HYPERLINK("#'DATA-POA'!A1","DATA-POA") -> DATA-POA | J2: =HYPERLINK("#'DATA-CNE'!A1","DATA-CNE") -> DATA-CNE | K2: =HYPERLINK("#'DATA-ORG'!A1","DATA-ORG") -> DATA-ORG | L2: =HYPERLINK("#'M-DASHBOARD'!A1","DASH") -> DASH
A3: Capa: Base/Plan > Tabla de Factores de Riesgo · Parámetros Ri por Meta
A4: # | B4: CÓD. PDOT | C4: EJE | D4: META ESTRATÉGICA | E4: NIVEL RIESGO | F4: Ri (FACTOR) | G4: PRESUP. PDOT ($) | H4: Pi (PESO)
A5: 1 | B5: ='M2-PDOT'!B4 -> PDOT.AS.VL.M1.01 | C5: ='M2-PDOT'!C4 -> Asentamientos Humanos | D5: ='M2-PDOT'!D4 -> Mantenimiento de vías urbanas para el acceso de los barrios del cantón | E5: ALTO | F5: 1 | G5: ='M2-PDOT'!L4 -> 10892761 | H5: ='M2-PLAN-Pi'!F14 -> 0.33155843
A6: 2 | B6: ='M2-PDOT'!B5 -> PDOT.SC.OE2.M1.01 | C6: ='M2-PDOT'!C5 -> Socio Cultural | D6: ='M2-PDOT'!D5 -> Desarrollo del Bienestar Integral para Montecristi | E6: CRÍTICO | F6: 1.5 | G6: ='M2-PDOT'!L5 -> 5827477 | H6: ='M2-PLAN-Pi'!F15 -> 0.17737919
A7: 3 | B7: ='M2-PDOT'!B6 -> PDOT.AM.OE3.M2.01 | C7: ='M2-PDOT'!C6 -> Ambiental | D7: ='M2-PDOT'!D6 -> Gestión Integral de Desechos Sólidos | E7: ALTO | F7: 1 | G7: ='M2-PDOT'!L6 -> 5001962.8 | H7: ='M2-PLAN-Pi'!F16 -> 0.15225184
A8: 4 | B8: ='M2-PDOT'!B7 -> PDOT.AS.OE1.M2.01 | C8: ='M2-PDOT'!C7 -> Asentamientos Humanos | D8: ='M2-PDOT'!D7 -> Fortalecimiento estratégico de equipamiento público comercial y administrativo | E8: ALTO | F8: 1 | G8: ='M2-PDOT'!L7 -> 1693800 | H8: ='M2-PLAN-Pi'!F17 -> 0.051556596
A9: 5 | B9: ='M2-PDOT'!B8 -> PDOT.SC.OE2.M4.01 | C9: ='M2-PDOT'!C8 -> Socio Cultural | D9: ='M2-PDOT'!D8 -> Proyecto Integral de Desarrollo y Apoyo Comunitario | E9: ALTO | F9: 1 | G9: ='M2-PDOT'!L8 -> 1611066 | H9: ='M2-PLAN-Pi'!F18 -> 0.049038304
A10: 6 | B10: ='M2-PDOT'!B9 -> PDOT.AS.OE1.M1.02 | C10: ='M2-PDOT'!C9 -> Asentamientos Humanos | D10: ='M2-PDOT'!D9 -> Gestión para la construcción de nueva infraestructura de tratamiento de aguas residuales | E10: CRÍTICO | F10: 1.5 | G10: ='M2-PDOT'!L9 -> 1269859.5 | H10: ='M2-PLAN-Pi'!F19 -> 0.038652516
A11: 7 | B11: ='M2-PDOT'!B10 -> PDOT.PI.OE4.M1.01 | C11: ='M2-PDOT'!C10 -> Político Institucional | D11: ='M2-PDOT'!D10 -> Implementación de la Transformación digital de los procedimientos institucionales | E11: MEDIO | F11: 0.5 | G11: ='M2-PDOT'!L10 -> 1219611.3 | H11: ='M2-PLAN-Pi'!F20 -> 0.037123042
A12: 8 | B12: ='M2-PDOT'!B11 -> PDOT.AV.OE1.M1.01 | C12: ='M2-PDOT'!C11 -> Asentamientos Humanos | D12: ='M2-PDOT'!D11 -> Recuperación integral de los espacios públicos | E12: ALTO | F12: 1 | G12: ='M2-PDOT'!L11 -> 894755.8 | H12: ='M2-PLAN-Pi'!F21 -> 0.027234953
A13: 9 | B13: ='M2-PDOT'!B12 -> PDOT.AM.OE3.M1.01 | C13: ='M2-PDOT'!C12 -> Ambiental | D13: ='M2-PDOT'!D12 -> Implementación de Infraestructura civil para la mitigación y reducción de impactos ante la susceptib | E13: CRÍTICO | F13: 1.5 | G13: ='M2-PDOT'!L12 -> 840000 | H13: ='M2-PLAN-Pi'!F22 -> 0.025568273
A14: 10 | B14: ='M2-PDOT'!B13 -> PDOT.FA.OE4.AH.02 | C14: ='M2-PDOT'!C13 -> Físico Ambiental | D14: ='M2-PDOT'!D13 -> Mejorando la capacidad de disposición final de desechos sólidos | E14: ALTO | F14: 1 | G14: ='M2-PDOT'!L13 -> 748782.57 | H14: ='M2-PLAN-Pi'!F23 -> 0.022791758
A15: 11 | B15: ='M2-PDOT'!B14 -> PDOT.FA.OE1.PV.01 | C15: ='M2-PDOT'!C14 -> Físico Ambiental | D15: ='M2-PDOT'!D14 -> Desarrollo de la red Verde y recuperación del espacio público | E15: MEDIO | F15: 0.5 | G15: ='M2-PDOT'!L14 -> 609999.54 | H15: ='M2-PLAN-Pi'!F24 -> 0.018567422
A16: 12 | B16: ='M2-PDOT'!B15 -> PDOT.PI.OE4.M2.01 | C16: ='M2-PDOT'!C15 -> Político Institucional | D16: ='M2-PDOT'!D15 -> Fortalecimiento del Sistema de Información Territorial Municipal | E16: MEDIO | F16: 0.5 | G16: ='M2-PDOT'!L15 -> 600955.83 | H16: ='M2-PLAN-Pi'!F25 -> 0.018292146
... A24: 20 | B24: ='M2-PDOT'!B23 -> PDOT.FA.OE2.MA.01 | C24: ='M2-PDOT'!C23 -> 0 | D24: ='M2-PDOT'!D23 -> 0 | E24: MEDIO | F24: 0.5 | G24: ='M2-PDOT'!L23 -> 0 | H24: ='M2-PLAN-Pi'!F33 -> 0
A25: Σ | B25: MUESTRA AUDITADA (n=20) | C25: — | D25: Trazabilidad impoluta: B→PDOT!B · C→PDOT!C · D→PDOT!D · F→PDOT!Ri · G→PDOT!L · H→PONDER!F | E25: — | F25: — | G25: ='M2-PDOT'!L24 -> 32853216 | H25: =SUM(H5:H24) -> 1
A26: Σ | B26: TOTAL | C26: - | D26: MUESTRA AUDITADA (n=20) | E26: - | F26: - | G26: =SUM(G6:G25) -> 54813672 | H26: =SUM(H6:H25) -> 1.6684416

Sheet M3-MAO
A1: QUADRUM v1.0 · M3-MAO · Matriz de Atribución Orgánica · Factor Ci · GAD Municipal Montecristi
A2: =HYPERLINK("#'M-INDEX'!A1","⌂ INDICE") -> ⌂ INDICE | B2: =HYPERLINK("#'M1-ITME'!A1","M1") -> M1 | C2: =HYPERLINK("#'M2-PDOT'!A1","M2") -> M2 | D2: =HYPERLINK("#'M3-MAO'!A1","◉ M3-MAO") -> ◉ M3-MAO | E2: =HYPERLINK("#'M4-AUDIT'!A1","M4") -> M4 | F2: =HYPERLINK("#'M5-ICPI'!A1","M5") -> M5 | G2: =HYPERLINK("#'M6-FEDS'!A1","M6") -> M6 | H2: =HYPERLINK("#'M7-PROSP'!A1","M7") -> M7 | I2: =HYPERLINK("#'DATA-POA'!A1","DATA-POA") -> DATA-POA | J2: =HYPERLINK("#'DATA-CNE'!A1","DATA-CNE") -> DATA-CNE | K2: =HYPERLINK("#'M-DASHBOARD'!A1","DASH") -> DASH
A3: #
A4: CÓD. PDOT | B4: EJE | C4: UNIDAD RESPONSABLE | D4: BASE LEGAL | E4: COMPETENCIA | F4: MODALIDAD EJECUCIÓN | G4: Ci | H4: NIVEL JERÁRQUICO | I4: CORREO | J4: EXT. | K4: CÓD. INT.
A5: PDOT.AS.OE1.M1.02 | B5: TERRITORIAL | C5: Dirección de Obras Públicas | D5: Art. 39 EO 2021 — Dir. Obras Públicas | E5: COOTAD Art. 55(d) | F5: Dirección GAD (control directo) | G5: 1 | H5: Director | I5: dop@montecristi.gob.ec | J5: Ext. 210 | K5: 45068
A6: PDOT.SC.OE2.M1.01 | B6: SOCIAL | C6: Patronato Municipal de Amparo Social | D6: Ordenanza de Creación Patronato Municipal (Entidad Adscrita) | E6: COOTAD Art. 388 | F6: Patronato / Ente adscrito (Ordenanza) | G6: 0.9 | H6: Director Ejecutivo | I6: patronato@montecristi.gob.ec | J6: Ext. 310 | K6: ⚠️ Entidad adscrita COOTAD Art.306 · Ci=0.9 · SSC (Subíndice Social Complementario) — no integra ICPI central
A7: PDOT.AS.OE1.M2.01 | B7: TERRITORIAL | C7: Dirección de Planificación y Desarrollo | D7: Art. 24/45 EO 2021 — Dir. Planificación y OT | E7: COOTAD Art. 55(d) | F7: Dirección GAD (control directo) | G7: 1 | H7: Director | I7: dplan@montecristi.gob.ec | J7: Ext. 201 | K7: 45068
A8: PDOT.AS.OE1.M2.02 | B8: TERRITORIAL | C8: Dirección de Servicios Públicos y Gestión | D8: Art. 51 EO 2021 — Dir. Espacios Públicos y Servicios | E8: COOTAD Art. 55(d) | F8: Dirección GAD (control directo) | G8: 1 | H8: Director | I8: dsp@montecristi.gob.ec | J8: Ext. 215 | K8: 45068
A9: PDOT.SC.OE2.M2.01 | B9: SOCIAL | C9: Dirección de Desarrollo Social y Cultural | D9: Art. 69 EO 2021 — Dir. Acción e Inclusión Social | E9: COOTAD Art. 55(d) | F9: Dirección GAD (control directo) | G9: 1 | H9: Director | I9: ddsc@montecristi.gob.ec | J9: Ext. 220 | K9: 45068
A10: PDOT.AS.VL.M1.01 | B10: TERRITORIAL | C10: Dirección de Obras Públicas | D10: Art. 39 EO 2021 — Dir. Obras Públicas | E10: COOTAD Art. 55(d) | F10: Dirección GAD (control directo) | G10: 1 | H10: Director | I10: dop@montecristi.gob.ec | J10: Ext. 210 | K10: 45068
A11: PDOT.SC.OE2.M3.01 | B11: SOCIAL | C11: Patronato Municipal de Amparo Social | D11: Ordenanza de Creación Patronato Municipal (Entidad Adscrita) | E11: COOTAD Art. 388 | F11: Patronato / Ente adscrito (Ordenanza) | G11: 0.9 | H11: Director Ejecutivo | I11: patronato@montecristi.gob.ec | J11: Ext. 310 | K11: 45078
A12: PDOT.AM.OE3.M1.01 | B12: AMBIENTAL | C12: Unidad de Gestión Ambiental GAD | D12: Art. 54 EO 2021 — Dir. Gestión Ambiental (GAD directo) | E12: COOTAD Art. 54(k) | F12: Dirección GAD (control directo) | G12: 1 | H12: Jefe Departamento | I12: uga@montecristi.gob.ec | J12: Ext. 301 | K12: 45092
A13: PDOT.AV.OE1.M1.01 | B13: TERRITORIAL | C13: Dirección de Obras Públicas | D13: Art. 39 EO 2021 — Dir. Obras Públicas | E13: COOTAD Art. 55(d) | F13: Dirección GAD (control directo) | G13: 1 | H13: Director | I13: dop@montecristi.gob.ec | J13: Ext. 210 | K13: 45068
A14: PDOT.SC.OE2.M4.01 | B14: SOCIAL | C14: Patronato Municipal de Amparo Social | D14: Ordenanza de Creación Patronato Municipal (Entidad Adscrita) | E14: COOTAD Art. 388 | F14: Patronato / Ente adscrito (Ordenanza) | G14: 0.9 | H14: Director Ejecutivo | I14: patronato@montecristi.gob.ec | J14: Ext. 310 | K14: 45078
A15: PDOT.AM.OE3.M2.01 | B15: AMBIENTAL | C15: EP Aseo Integral Montecristi | D15: Estatuto EP Aseo Integral (Res. Adm. propia) — Ci=0.75 | E15: COOTAD Art. 280 | F15: Patronato / Ente adscrito (Ordenanza) | G15: 0.75 | H15: Director Ejecutivo EP | I15: epaseo@montecristi.gob.ec | J15: Ext. 401 | K15: 45108
A16: PDOT.AS.VL.M1.02 | B16: TERRITORIAL | C16: Dirección de Obras Públicas | D16: Art. 39 EO 2021 — Dir. Obras Públicas | E16: COOTAD Art. 55(d) | F16: Dirección GAD (control directo) | G16: 1 | H16: Director | I16: dop@montecristi.gob.ec | J16: Ext. 210 | K16: 45068
A17: PDOT.SC.PI.M5.01 | B17: SOCIAL | C17: Dirección de Tecnología e Información | D17: Art. 94 EO 2021 — TICs (subproceso Dir. Administrativa) | E17: COOTAD Art. 55(d) | F17: Dirección GAD (control directo) | G17: 1 | H17: Director | I17: tics@montecristi.gob.ec | J17: Ext. 230 | K17: 45068
A18: PDOT.PI.OE4.M1.01 | B18: INSTITUCIONAL | C18: Dirección de Tecnología e Información | D18: Art. 94 EO 2021 — TICs (subproceso Dir. Administrativa) | E18: COOTAD Art. 55(d) | F18: Dirección GAD (control directo) | G18: 1 | H18: Director | I18: tics@montecristi.gob.ec | J18: Ext. 230 | K18: 45068
... A23: PDOT.AS.OE1.M1.03 | B23: TERRITORIAL | C23: Dirección de Agua Potable y Saneamiento | D23: Art. 42 EO 2021 — Dir. Agua Potable y Alcantarillado | E23: COOTAD Art. 55(d) | F23: Dirección GAD (control directo) | G23: 1 | H23: Director | I23: dag@montecristi.gob.ec | J23: Ext. 205 | K23: 45068

Sheet DATA-SSC
A1: QUADRUM v1.0 · DATA-SSC · Subíndice Social Complementario · Escalabilidad Institucional
A2: =HYPERLINK("#'M-INDEX'!A1","⌂ INDICE") -> ⌂ INDICE | B2: =HYPERLINK("#'M1-ITME'!A1","M1") -> M1 | C2: =HYPERLINK("#'M2-PDOT'!A1","M2") -> M2 | D2: =HYPERLINK("#'M3-MAO'!A1","M3") -> M3 | E2: =HYPERLINK("#'M4-AUDIT'!A1","M4") -> M4 | F2: =HYPERLINK("#'M5-ICPI'!A1","M5") -> M5 | G2: =HYPERLINK("#'M6-FEDS'!A1","M6") -> M6 | H2: =HYPERLINK("#'M7-PROSP'!A1","M7") -> M7 | I2: =HYPERLINK("#'DATA-POA'!A1","DATA-POA") -> DATA-POA | J2: =HYPERLINK("#'DATA-CNE'!A1","DATA-CNE") -> DATA-CNE | K2: =HYPERLINK("#'DATA-ORG'!A1","DATA-ORG") -> DATA-ORG | L2: =HYPERLINK("#'M-DASHBOARD'!A1","DASH") -> DASH
A3: Capa: Verificación > Sistema de Supervisión y Control · Red de Verificación Interinstitucional
A4: ⬡ TABLA Ci — Escala de Imputabilidad Institucional · COOTAD Arts.54,280,306 · SIAP-ICPI §3.7.1 · Replicable en s los GADs del Ecuador
A5: CAPA | B5: TIPO DE ENTIDAD | C5: Ci | D5: ⌂ ÍNDICE | E5: HOJA / MÓDULO | F5: BASE LEGAL | G5: INTEGRA ICPI | H5: Criterio de Usabilidad de Auditoría
A6: ❶ | B6: Direcciones Municipales GAD | C6: 1 | D6: — (ICPI central) | E6: MAO · MAD · ICPI | F6: COOTAD Art.54 | G6: ✅ SÍ | H6: 13 direcciones GAD — control pleno — ICPI
A7: ❷ | B7: Entidades Adscritas (Patronato) | C7: 0.9 | D7: ISSC — Social Complementario | E7: SSC Sección A | F7: COOTAD Art.306 | G7: 🔶 NO — SSC | H7: Autonomía parcial — análisis descriptivo — ACTIVO
A8: ❸ | B8: Empresas Públicas Municipales | C8: 0.75 | D8: ISPE — Servicios Públicos EP | E8: SSC Sección B | F8: COOTAD Art.280 | G8: 🔶 NO — ISPE | H8: EP Aseo · EP Agua — módulo futuro
A9: ❹ | B9: Convenios Interinstitucionales | C9: 0.5 | D9: ISCI — Cogestión Interinst. | E9: SSC Sección C | F9: COOTAD Art.126 | G9: 🔶 NO — ISCI | H9: MSP·MIDUVI·MINTUR·MIES — módulo futuro
A10: ❺ | B10: Concesiones / Delegación Privada | C10: 0.25 | D10: — (fuera de alcance) | E10: — | F10: COOTAD Art.281 | G10: ❌ EXCLUIDO | H10: No imputable al GAD — fuera del instrumento SIAP
A11: 🔷 SECCIÓN A — ISSC · Subíndice Social Complementario · Patronato Municipal de Amparo Social · n=4 metas sociales · Ci=0.9 · ✅ PILOTO ACTIVO
A12: N° | B12: COD-META (PDOT) | C12: EJE PDOT | D12: DESCRIPCIÓN SINTÉTICA META | E12: Pi | F12: Ri | G12: Vi (Evidencia 0/1) | H12: Ti (Ejecución) | I12: Ci (Control) | J12: Pi×Ri×Vi×Ti×Ci (Contrib.) | K12: ISSC_i (% contrib.) | L12: ESTADO / ACCIÓN RECOMENDADA
A13: 1 | B13: ='M2-PDOT'!B3 -> CÓD. PDOT / ID_META | C13: ='M2-PDOT'!C3 -> SISTEMA | D13: Centro de Salud Tipo C «Nacer Aquí» | E13: ='M2-PDOT'!E3 -> Pi | F13: ='M2-PDOT'!F3 -> Ri | G13: 0 | H13: 0.15 | I13: 0.9 | J13: =E13*F13*G13*H13*I13 -> #VALUE! | K13: =IF(SUM(J13:J16)>0,J13/SUM($J$13:$J$16),0) -> #VALUE! | L13: 🔴 URGENTE — Firmar convenio MSP + cronograma SERCOP. Elevar Vi=1 como prioridad máxima GAD.
A14: 2 | B14: ='M2-PDOT'!B10 -> PDOT.PI.OE4.M1.01 | C14: ='M2-PDOT'!C10 -> Político Institucional | D14: Equipamiento Geriátrico · Montecristi Solidario | E14: ='M2-PDOT'!E10 -> 0.037123042 | F14: ='M2-PDOT'!F10 -> 1 | G14: 1 | H14: 1 | I14: 0.9 | J14: =E14*F14*G14*H14*I14 -> 0.033410738 | K14: =IF(SUM(J13:J16)>0,J14/SUM($J$13:$J$16),0) -> #VALUE! | L14: ✅ CUMPLIDA — Incluir partida operación recurrente POA 2025. Vincular indicador PDOT.
A15: 3 | B15: ='M2-PDOT'!B12 -> PDOT.AM.OE3.M1.01 | C15: ='M2-PDOT'!C12 -> Ambiental | D15: Unidad Médica Móvil — Salud Preventiva | E15: ='M2-PDOT'!E12 -> 0.025568273 | F15: ='M2-PDOT'!F12 -> 1.5 | G15: 0 | H15: 0.5 | I15: 0.9 | J15: =E15*F15*G15*H15*I15 -> 0 | K15: =IF(SUM(J13:J16)>0,J15/SUM($J$13:$J$16),0) -> #VALUE! | L15: ⚠️ URGENTE — Registrar vehículo SERCOP. Generar contrato formal → elevar Vi=1.
A16: 4 | B16: ='M2-PDOT'!B15 -> PDOT.PI.OE4.M2.01 | C16: ='M2-PDOT'!C15 -> Político Institucional | D16: Guarderías Nocturnas / CIBV Clubes Niños | E16: ='M2-PDOT'!E15 -> 0.018292146 | F16: ='M2-PDOT'!F15 -> 1 | G16: 0 | H16: 0 | I16: 0.9 | J16: =E16*F16*G16*H16*I16 -> 0 | K16: =IF(SUM(J13:J16)>0,J16/SUM($J$13:$J$16),0) -> #VALUE! | L16: 🔴 URGENTE — Convenio MIES para CIBV. Reformular como programa protección infantil POA 2025.
A17: Σ | B17: ISSC TOTAL · Subíndice Social Complementario Patronato Municipal | E17: =SUM(E13:E16) -> 0.080983461 | J17: =SUM(J13:J16) -> #VALUE! | K17: =SUM(K13:K16) -> #VALUE!
A18: INTERPRETACIÓN ISSC · El ISSC mide cuánto aporta el Patronato si tuviera control pleno (Ci=1.0 hipotético). El valor Ci=0.9 ya reduce su contribución en el ICPI central. ISSC sirve como indicador de coherencia social: cuánto de la dimensión asistencial del mandato PDOT se ejecuta vía Patronato. Si ISSC es alto pero ICPI_social es bajo → el GAD delega política social sin ejecutar directamente → señal de alerta §3.4-SSC. Vi=0 en metas prioritarias = riesgo de incumplimiento PDOT.
A19: 🔶 SECCIÓN B — ISPE · Subíndice Servicios Públicos EP · EP Aseo Integral Montecristi · Ci=0.75 · COOTAD Art.280 · MÓDULO EN DESARROLLO — Activar cuando EP esté formalmente constituida
A20: EP Aseo Integral Montecristi (COOTAD Art.280) · Ci=0.75 · Metas bajo EP: Relleno Sanitario (PDOT.AM.OE3.M2.01), Recolección Desechos (PDOT.FA.OE4.AH.01) · ISPE_i = Pi×Ri×Vi×Ti×0.75 ÷ Σ(Pi×Ri) · Activar cuando EP tenga estatuto aprobado y directorio GAD activo · Si GAD tiene EP Agua → agregar aquí con misma lógica Ci=0.75
A21: 🔵 SECCIÓN C — ISCI · Subíndice Cogestión Interinstitucional · Convenios MSP / MIDUVI / MINTUR / MIES · Ci=0.5 · COOTAD Art.126 · MÓDULO EN DESARROLLO — Activar cuando convenios tengan presupuesto verificable SERCOP
A22: Convenios activos: MSP (Salud Tipo C), MIDUVI (Vivienda Social), MINTUR (Manglar Vivo), MIES (CIBV) · Ci=0.5 (GAD no controla directamente) · ISCI_i = Pi×Ri×Vi×Ti×0.5 ÷ Σ(Pi×Ri) · Diferencia entre ICPI con Ci=0.5 vs hipótetico Ci=1.0 = peso institucional perdido por delegación externa · Activar con convenios firmados y verificables
A23: ⬡ SECCIÓN MELÓGICA SSC · Decisiones de Diseño · Escalabilidad SIAP-ICPI · Arquitectura Modular para GADs del Ecuador
A24: ASPECTO | B24: DETALLE TÉCNICO / DECISIÓN DE DISEÑO | C24: REFERENCIA NORMATIVA | D24: VERSIÓN
A25: Separación ICPI / SSC | B25: El ICPI central mide SOLO metas bajo control directo GAD. El SSC es análisis descriptivo adicional — no modifica el ICPI. Garantiza integridad melógica y comparabilidad entre GADs con distinta estructura institucional. | C25: SIAP-ICPI §3.4-SSC COOTAD Art.228 | D25: ✅ ACTIVO
A26: Fórmula ICPI inalterada | B26: ICPI = Σ(Pi·Ri·Vi·Ei·Ti·Ci) ÷ Σ(Pi·Ri) — Ci=0.9 para metas del Patronato ya reduce su contribución al numerador. El SSC muestra la contribución hipotética si Ci=1.0. La diferencia = penalización por delegación institucional. | C26: SIAP-ICPI §3.7 MAO fila 3 nota | D26: ✅ ACTIVO
A27: Escalabilidad EP (ISPE) | B27: EP Aseo (COOTAD Art.280): Ci=0.75. Cuando el GAD tiene EP formalmente constituida, se activa ISPE en Sección B de esta hoja. La fórmula base no cambia. Si el GAD tiene EP Agua, se agrega en la misma Sección B con idéntica lógica. | C27: COOTAD Art.280 Estatuto EP Art.5
A28: Escalabilidad Convenios (ISCI) | B28: Convenios MSP/MIDUVI/MINTUR/MIES: Ci=0.5. Se activa ISCI cuando los convenios tienen presupuesto verificable en SERCOP. Indicador de gobernanza interinstitucional. Cuanto mayor ISCI mayor dependencia del GAD de actores externos para cumplir su mandato PDOT. | C28: COOTAD Art.126 Norma Técnica SERCOP
A29: Replicabilidad en otros GADs | B29: La escala Ci y la arquitectura SSC/ISPE/ISCI son genéricas. Cualquier GAD puede adoptar el instrumento con su propia estructura institucional. Solo cambian los valores de n (metas) y la composición de entidades adscritas y EP. La fórmula ICPI es universal. | C29: COOTAD Art.228 CRE Art.264 | D29: EN DISEÑO
A30: ◈ SSC · Subíndice Social Complementario · Patronato Ci=0.9 ✅ · EP Ci=0.75 · Convenios Ci=0.5 · SIAP-ICPI GAD Montecristi © 2025

Sheet M4-AUDIT
A1: QUADRUM v1.0 · M4-AUDIT · Matriz de Auditoría Documental · Vi · Ei · Ti · GAD Municipal Montecristi
A2: =HYPERLINK("#'M-INDEX'!A1","⌂ INDICE") -> ⌂ INDICE | B2: =HYPERLINK("#'M1-ITME'!A1","M1") -> M1 | C2: =HYPERLINK("#'M2-PDOT'!A1","M2") -> M2 | D2: =HYPERLINK("#'M3-MAO'!A1","M3") -> M3 | E2: =HYPERLINK("#'M4-AUDIT'!A1","◉ M4-AUDIT") -> ◉ M4-AUDIT | F2: =HYPERLINK("#'M5-ICPI'!A1","M5") -> M5 | G2: =HYPERLINK("#'M6-FEDS'!A1","M6") -> M6 | H2: =HYPERLINK("#'M7-PROSP'!A1","M7") -> M7 | I2: =HYPERLINK("#'DATA-POA'!A1","DATA-POA") -> DATA-POA | J2: =HYPERLINK("#'DATA-CNE'!A1","DATA-CNE") -> DATA-CNE | K2: =HYPERLINK("#'DATA-ORG'!A1","DATA-ORG") -> DATA-ORG | L2: =HYPERLINK("#'M-DASHBOARD'!A1","DASH") -> DASH
A3: #
A4: CÓD. PDOT | B4: EJE | C4: TIPOLOGÍA DOC. | D4: DEPARTAMENTO | E4: EVIDENCIA | F4: Vi | G4: Ri | H4: Ti (H) | I4: Vi×Ri×Ti | J4: ESTADO DOC. | K4: Vi AUD. | L4: Ti AUD. | M4: REF. DOC. | N4: CONSISTENCIA | O4: RESPONSABLE | P4: Pi / Ci | Q4: PDOT ✓ | R4: POA ✓ | S4: PAC ✓ | T4: Ti CÉDULA | U4: SIGAD ✓ | V4: CPCCS ✓ | W4: Ci CININ | X4: Ci | Y4: Ti CININ | Z4: ESTADO CININ | AA4: OBS.
A5: ='M2-PDOT'!B6 -> PDOT.AM.OE3.M2.01 | B5: TERRITORIAL | C5: Silo de Ejecución · SERCOP / Cédulas | D5: Obras Públicas / Alcantar. | E5: Contrato / Planillas | F5: 1 | G5: 1 | H5: 0.75 | I5: =F5*G5*H5 -> 0.75 | J5: =IF(F5=1,"DOCUMENTO VALIDADO","SIN SOPORTE DOCUMENTAL") -> DOCUMENTO VALIDADO | K5: 1 | L5: 0.75 | M5: RDC 2023+2024 | N5: =IF(ABS(F5-K5)=0,IF(ABS(H5-L5)<0.05,"✅ Vi+Ti Consistentes","⚠️ Ti difiere: H="&H5&" vs L="&L5),"⚠️ Vi difiere: F="&F5&" vs K="&K5) -> ✅ Vi+Ti Consistentes | O5: =IFERROR(VLOOKUP(A5,'M3-MAO'!$A$3:$G$23,3,0),"— revisar") -> EP Aseo Integral Montecristi | P5: =IFERROR(VLOOKUP(A5,'M3-MAO'!$A$3:$G$23,7,0),1) -> 0.75 | Q5: 1 | R5: 1 | S5: =IF(COUNTIF('DATA-PAC'!$L:$L,A5)>0,1,0) -> 1 | T5: 0.75 | U5: 1 | V5: 1 | W5: =Q5*R5*S5 -> 1 | X5: =Q5*R5*S5 -> 1 | Y5: =T5 -> 0.75 | Z5: =IF(Q5=0,"🔴 CININ ROTA: Meta fuera del PDOT",IF(R5=0,"🔴 CININ ROTA: No incluida en POA — Escenario D §3.8.4",IF(S5=0,IF(T5>0,"🟠 CININ PARCIAL: Sin PAC pero hay ejecución — Escenario B §3.8.4","🔴 CININ ROTA: Sin PAC ni ejecución — Escenario B §3.8.4"),IF(T5=0,"🟡 CININ PARCIAL: PAC sí pero cédula=0 — revisar transferencia","✅ CININ ÍNTEGRA: Cadena completa verificada §3.4")))) -> ✅ CININ ÍNTEGRA: Cadena completa verificada §3.4 | AA5: RDC 2023+2024 ✔ — Recolección ampliada, 6 vehículos, Ordenanza Basura 4ª Reforma, estudios PTAR.
A6: ='M2-PDOT'!B7 -> PDOT.AS.OE1.M2.01 | B6: SOCIAL | C6: Silo de Planificación · GAD LOTAIP | D6: Salud / Planificación | E6: Escrituras / Registro | F6: 0 | G6: 0.9 | H6: 0.1 | I6: =F6*G6*H6 -> 0 | J6: =IF(F6=1,"DOCUMENTO VALIDADO","SIN SOPORTE DOCUMENTAL") -> SIN SOPORTE DOCUMENTAL | K6: 0 | L6: 0.15 | M6: RDC 2024 p.11 | N6: =IF(ABS(F6-K6)=0,IF(ABS(H6-L6)<0.05,"✅ Vi+Ti Consistentes","⚠️ Ti difiere: H="&H6&" vs L="&L6),"⚠️ Vi difiere: F="&F6&" vs K="&K6) -> ⚠️ Ti difiere: H=0,1 vs L=0,15 | O6: =IFERROR(VLOOKUP(A6,'M3-MAO'!$A$3:$G$23,3,0),"— revisar") -> Dirección de Planificación y Desarrollo | P6: =IFERROR(VLOOKUP(A6,'M3-MAO'!$A$3:$G$23,7,0),1) -> 1 | Q6: 1 | R6: 1 | S6: =IF(COUNTIF('DATA-PAC'!$L:$L,A6)>0,1,0) -> 1 | T6: =IFERROR(VLOOKUP(A6,'DATA-CED'!$A$5:$Q$24,17,0),0.1) -> 0.2 | U6: 0 | V6: 1 | W6: =Q6*R6*S6 -> 1 | X6: =Q6*R6*S6 -> 1 | Y6: =T6 -> 0.2 | Z6: =IF(Q6=0,"🔴 CININ ROTA: Meta fuera del PDOT",IF(R6=0,"🔴 CININ ROTA: No incluida en POA — Escenario D §3.8.4",IF(S6=0,IF(T6>0,"🟠 CININ PARCIAL: Sin PAC pero hay ejecución — Escenario B §3.8.4","🔴 CININ ROTA: Sin PAC ni ejecución — Escenario B §3.8.4"),IF(T6=0,"🟡 CININ PARCIAL: PAC sí pero cédula=0 — revisar transferencia","✅ CININ ÍNTEGRA: Cadena completa verificada §3.4")))) -> ✅ CININ ÍNTEGRA: Cadena completa verificada §3.4 | AA6: RDC 2023 p.4 ✔ — Informe necesidad macro movilidad (terminal). RDC 2024: sin mención.
A7: ='M2-PDOT'!B8 -> PDOT.SC.OE2.M4.01 | B7: TERRITORIAL | C7: Silo de Ejecución · SERCOP / Cédulas | D7: Proyectos Estratégicos | E7: Proceso SERCOP | F7: 1 | G7: 1 | H7: 0.2 | I7: 0.2 | J7: =IF(F7=1,"DOCUMENTO VALIDADO","SIN SOPORTE DOCUMENTAL") -> DOCUMENTO VALIDADO | K7: 1 | L7: 0.2 | M7: RDC 2023 p.4 | N7: =IF(ABS(F7-K7)=0,IF(ABS(H7-L7)<0.05,"✅ Vi+Ti Consistentes","⚠️ Ti difiere: H="&H7&" vs L="&L7),"⚠️ Vi difiere: F="&F7&" vs K="&K7) -> ✅ Vi+Ti Consistentes | O7: =IFERROR(VLOOKUP(A7,'M3-MAO'!$A$3:$G$23,3,0),"— revisar") -> Patronato Municipal de Amparo Social | P7: =IFERROR(VLOOKUP(A7,'M3-MAO'!$A$3:$G$23,7,0),1) -> 0.9 | Q7: 1 | R7: 1 | S7: =IF(COUNTIF('DATA-PAC'!$L:$L,A7)>0,1,0) -> 1 | T7: 0.2 | U7: 0 | V7: 1 | W7: =Q7*R7*S7 -> 1 | X7: =Q7*R7*S7 -> 1 | Y7: =T7 -> 0.2 | Z7: =IF(Q7=0,"🔴 CININ ROTA: Meta fuera del PDOT",IF(R7=0,"🔴 CININ ROTA: No incluida en POA — Escenario D §3.8.4",IF(S7=0,IF(T7>0,"🟠 CININ PARCIAL: Sin PAC pero hay ejecución — Escenario B §3.8.4","🔴 CININ ROTA: Sin PAC ni ejecución — Escenario B §3.8.4"),IF(T7=0,"🟡 CININ PARCIAL: PAC sí pero cédula=0 — revisar transferencia","✅ CININ ÍNTEGRA: Cadena completa verificada §3.4")))) -> ✅ CININ ÍNTEGRA: Cadena completa verificada §3.4 | AA7: DISCREPANCIA: Reportado vs Realidad — RDC 2023+2024 NO mencionan guardería nocturna. Cédula devengado=$0 (codif. $10,000). CPCCS ✓=1 sin respaldo documental.
A8: ='M2-PDOT'!B9 -> PDOT.AS.OE1.M1.02 | B8: TERRITORIAL | C8: Silo de Planificación · GAD LOTAIP | D8: Servicios Públicos | E8: Informe Viabilidad | F8: 0 | G8: 1 | H8: 0 | I8: =F8*G8*H8 -> 0 | J8: =IF(F8=1,"DOCUMENTO VALIDADO","SIN SOPORTE DOCUMENTAL") -> SIN SOPORTE DOCUMENTAL | K8: 0 | L8: 0 | M8: RDC 2024 p.3 | N8: =IF(ABS(F8-K8)=0,IF(ABS(H8-L8)<0.05,"✅ Vi+Ti Consistentes","⚠️ Ti difiere: H="&H8&" vs L="&L8),"⚠️ Vi difiere: F="&F8&" vs K="&K8) -> ✅ Vi+Ti Consistentes | O8: =IFERROR(VLOOKUP(A8,'M3-MAO'!$A$3:$G$23,3,0),"— revisar") -> Dirección de Obras Públicas | P8: =IFERROR(VLOOKUP(A8,'M3-MAO'!$A$3:$G$23,7,0),1) -> 1 | Q8: 1 | R8: 0 | S8: =IF(COUNTIF('DATA-PAC'!$L:$L,A8)>0,1,0) -> 1 | T8: 0 | U8: 0 | V8: 1 | W8: =Q8*R8*S8 -> 0 | X8: =Q8*R8*S8 -> 0 | Y8: =T8 -> 0 | Z8: =IF(Q8=0,"🔴 CININ ROTA: Meta fuera del PDOT",IF(R8=0,"🔴 CININ ROTA: No incluida en POA — Escenario D §3.8.4",IF(S8=0,IF(T8>0,"🟠 CININ PARCIAL: Sin PAC pero hay ejecución — Escenario B §3.8.4","🔴 CININ ROTA: Sin PAC ni ejecución — Escenario B §3.8.4"),IF(T8=0,"🟡 CININ PARCIAL: PAC sí pero cédula=0 — revisar transferencia","✅ CININ ÍNTEGRA: Cadena completa verificada §3.4")))) -> 🔴 CININ ROTA: No incluida en POA — Escenario D §3.8.4 | AA8: DISCREPANCIA: Reportado vs Realidad — RDC 2024 T14 declara oficialmente meta DESPRIORITIZADA: 'Se Despriorizo la construcción de un camal'. Cédula devengado=$0 (codif. $1,693,800). CPCCS ✓=1 es INCORRECTO.
A9: ='M2-PDOT'!B10 -> PDOT.PI.OE4.M1.01 | B9: SOCIAL | C9: Silo de Ejecución · SERCOP / Cédulas | D9: Desarrollo Social | E9: Facturas Equipamiento | F9: 1 | G9: 1 | H9: 1 | I9: =F9*G9*H9 -> 1 | J9: =IF(F9=1,"DOCUMENTO VALIDADO","SIN SOPORTE DOCUMENTAL") -> DOCUMENTO VALIDADO | K9: 1 | L9: 1 | M9: SERCOP/Facturas | N9: =IF(ABS(F9-K9)=0,IF(ABS(H9-L9)<0.05,"✅ Vi+Ti Consistentes","⚠️ Ti difiere: H="&H9&" vs L="&L9),"⚠️ Vi difiere: F="&F9&" vs K="&K9) -> ✅ Vi+Ti Consistentes | O9: =IFERROR(VLOOKUP(A9,'M3-MAO'!$A$3:$G$23,3,0),"— revisar") -> Dirección de Tecnología e Información | P9: =IFERROR(VLOOKUP(A9,'M3-MAO'!$A$3:$G$23,7,0),1) -> 1 | Q9: 1 | R9: 1 | S9: =IF(COUNTIF('DATA-PAC'!$L:$L,A9)>0,1,0) -> 1 | T9: =IFERROR(VLOOKUP(A9,'DATA-CED'!$A$5:$Q$24,17,0),0.3) -> 0.70000031 | U9: 1 | V9: 1 | W9: =Q9*R9*S9 -> 1 | X9: =Q9*R9*S9 -> 1 | Y9: =T9 -> 0.70000031 | Z9: =IF(Q9=0,"🔴 CININ ROTA: Meta fuera del PDOT",IF(R9=0,"🔴 CININ ROTA: No incluida en POA — Escenario D §3.8.4",IF(S9=0,IF(T9>0,"🟠 CININ PARCIAL: Sin PAC pero hay ejecución — Escenario B §3.8.4","🔴 CININ ROTA: Sin PAC ni ejecución — Escenario B §3.8.4"),IF(T9=0,"🟡 CININ PARCIAL: PAC sí pero cédula=0 — revisar transferencia","✅ CININ ÍNTEGRA: Cadena completa verificada §3.4")))) -> ✅ CININ ÍNTEGRA: Cadena completa verificada §3.4 | AA9: RDC 2023+2024 ✔ — 119+8 equipos TIC; plataforma digital; facturación electrónica; chatbot; MINTEL.
A10: ='M2-PDOT'!B11 -> PDOT.AV.OE1.M1.01 | B10: TERRITORIAL | C10: Silo de Ejecución · SERCOP / Cédulas | D10: Obras Públicas / Vialidad | E10: Cédula Presupuestaria | F10: 1 | G10: 1 | H10: 0.9 | I10: =F10*G10*H10 -> 0.9 | J10: =IF(F10=1,"DOCUMENTO VALIDADO","SIN SOPORTE DOCUMENTAL") -> DOCUMENTO VALIDADO | K10: 1 | L10: 0.9 | M10: Céd.Pres.GAD | N10: =IF(ABS(F10-K10)=0,IF(ABS(H10-L10)<0.05,"✅ Vi+Ti Consistentes","⚠️ Ti difiere: H="&H10&" vs L="&L10),"⚠️ Vi difiere: F="&F10&" vs K="&K10) -> ✅ Vi+Ti Consistentes | O10: =IFERROR(VLOOKUP(A10,'M3-MAO'!$A$3:$G$23,3,0),"— revisar") -> Dirección de Obras Públicas | P10: =IFERROR(VLOOKUP(A10,'M3-MAO'!$A$3:$G$23,7,0),1) -> 1 | Q10: 1 | R10: 1 | S10: =IF(COUNTIF('DATA-PAC'!$L:$L,A10)>0,1,0) -> 1 | T10: 0.9 | U10: 1 | V10: 1 | W10: =Q10*R10*S10 -> 1 | X10: =Q10*R10*S10 -> 1 | Y10: =T10 -> 0.9 | Z10: =IF(Q10=0,"🔴 CININ ROTA: Meta fuera del PDOT",IF(R10=0,"🔴 CININ ROTA: No incluida en POA — Escenario D §3.8.4",IF(S10=0,IF(T10>0,"🟠 CININ PARCIAL: Sin PAC pero hay ejecución — Escenario B §3.8.4","🔴 CININ ROTA: Sin PAC ni ejecución — Escenario B §3.8.4"),IF(T10=0,"🟡 CININ PARCIAL: PAC sí pero cédula=0 — revisar transferencia","✅ CININ ÍNTEGRA: Cadena completa verificada §3.4")))) -> ✅ CININ ÍNTEGRA: Cadena completa verificada §3.4 | AA10: RDC 2023+2024 ✔ — 5 parques recuperados; 57 espacios públicos 2024; 5 puntos wifi.
A11: ='M2-PDOT'!B12 -> PDOT.AM.OE3.M1.01 | B11: SOCIAL | C11: Silo de Ejecución · SERCOP / Cédulas | D11: Salud | E11: Orden Compra / Placas | F11: 0 | G11: 0.9 | H11: 0.3 | I11: =F11*G11*H11 -> 0 | J11: =IF(F11=1,"DOCUMENTO VALIDADO","SIN SOPORTE DOCUMENTAL") -> SIN SOPORTE DOCUMENTAL | K11: 0 | L11: 0.5 | M11: RDC 2023+2024 | N11: =IF(ABS(F11-K11)=0,IF(ABS(H11-L11)<0.05,"✅ Vi+Ti Consistentes","⚠️ Ti difiere: H="&H11&" vs L="&L11),"⚠️ Vi difiere: F="&F11&" vs K="&K11) -> ⚠️ Ti difiere: H=0,3 vs L=0,5 | O11: =IFERROR(VLOOKUP(A11,'M3-MAO'!$A$3:$G$23,3,0),"— revisar") -> Unidad de Gestión Ambiental GAD | P11: =IFERROR(VLOOKUP(A11,'M3-MAO'!$A$3:$G$23,7,0),1) -> 1 | Q11: 1 | R11: 1 | S11: =IF(COUNTIF('DATA-PAC'!$L:$L,A11)>0,1,0) -> 1 | T11: =IFERROR(VLOOKUP(A11,'DATA-CED'!$A$5:$Q$24,17,0),0.5) -> 0 | U11: 1 | V11: 1 | W11: =Q11*R11*S11 -> 1 | X11: =Q11*R11*S11 -> 1 | Y11: =T11 -> 0 | Z11: =IF(Q11=0,"🔴 CININ ROTA: Meta fuera del PDOT",IF(R11=0,"🔴 CININ ROTA: No incluida en POA — Escenario D §3.8.4",IF(S11=0,IF(T11>0,"🟠 CININ PARCIAL: Sin PAC pero hay ejecución — Escenario B §3.8.4","🔴 CININ ROTA: Sin PAC ni ejecución — Escenario B §3.8.4"),IF(T11=0,"🟡 CININ PARCIAL: PAC sí pero cédula=0 — revisar transferencia","✅ CININ ÍNTEGRA: Cadena completa verificada §3.4")))) -> 🟡 CININ PARCIAL: PAC sí pero cédula=0 — revisar transferencia | AA11: DISCREPANCIA PARCIAL: Reportado vs Realidad — RDC reporta USMC (brigadas médicas) activa, pero PTAR cédula devengado=$0. CPCCS ✓=1 refleja servicio médico, NO construcción PTAR.
A12: ='M2-PDOT'!B13 -> PDOT.FA.OE4.AH.02 | B12: AMBIENTAL | C12: Silo de Ejecución · SERCOP / Cédulas | D12: Gestión Ambiental | E12: Licencia / Contrato | F12: 1 | G12: 0.9 | H12: 0.4 | I12: =F12*G12*H12 -> 0.36 | J12: =IF(F12=1,"DOCUMENTO VALIDADO","SIN SOPORTE DOCUMENTAL") -> DOCUMENTO VALIDADO | K12: 1 | L12: 0.4 | M12: RDC 2023+2024 | N12: =IF(ABS(F12-K12)=0,IF(ABS(H12-L12)<0.05,"✅ Vi+Ti Consistentes","⚠️ Ti difiere: H="&H12&" vs L="&L12),"⚠️ Vi difiere: F="&F12&" vs K="&K12) -> ✅ Vi+Ti Consistentes | O12: =IFERROR(VLOOKUP(A12,'M3-MAO'!$A$3:$G$23,3,0),"— revisar") -> — revisar | P12: =IFERROR(VLOOKUP(A12,'M3-MAO'!$A$3:$G$23,7,0),1) -> 1 | Q12: 1 | R12: 1 | S12: =IF(COUNTIF('DATA-PAC'!$L:$L,A12)>0,1,0) -> 0 | T12: 0.4 | U12: 1 | V12: 1 | W12: =Q12*R12*S12 -> 0 | X12: =Q12*R12*S12 -> 0 | Y12: =T12 -> 0.4 | Z12: =IF(Q12=0,"🔴 CININ ROTA: Meta fuera del PDOT",IF(R12=0,"🔴 CININ ROTA: No incluida en POA — Escenario D §3.8.4",IF(S12=0,IF(T12>0,"🟠 CININ PARCIAL: Sin PAC pero hay ejecución — Escenario B §3.8.4","🔴 CININ ROTA: Sin PAC ni ejecución — Escenario B §3.8.4"),IF(T12=0,"🟡 CININ PARCIAL: PAC sí pero cédula=0 — revisar transferencia","✅ CININ ÍNTEGRA: Cadena completa verificada §3.4")))) -> 🟠 CININ PARCIAL: Sin PAC pero hay ejecución — Escenario B §3.8.4 | AA12: RDC 2023+2024 ✔ — PTAR estudios definitivos aprobados; equipos monitoreo ambiental; cert. ambiental Manglar Vivo.
A13: ='M2-PDOT'!B14 -> PDOT.FA.OE1.PV.01 | B13: TERRITORIAL | C13: Silo de Ejecución · SERCOP / Cédulas | D13: Parques y Jardines | E13: Registro / Acta Inicio | F13: 1 | G13: 1 | H13: 0.5 | I13: =F13*G13*H13 -> 0.5 | J13: =IF(F13=1,"DOCUMENTO VALIDADO","SIN SOPORTE DOCUMENTAL") -> DOCUMENTO VALIDADO | K13: 1 | L13: 0.5 | M13: Registro/Acta | N13: =IF(ABS(F13-K13)=0,IF(ABS(H13-L13)<0.05,"✅ Vi+Ti Consistentes","⚠️ Ti difiere: H="&H13&" vs L="&L13),"⚠️ Vi difiere: F="&F13&" vs K="&K13) -> ✅ Vi+Ti Consistentes | O13: =IFERROR(VLOOKUP(A13,'M3-MAO'!$A$3:$G$23,3,0),"— revisar") -> — revisar | P13: =IFERROR(VLOOKUP(A13,'M3-MAO'!$A$3:$G$23,7,0),1) -> 1 | Q13: 1 | R13: 1 | S13: =IF(COUNTIF('DATA-PAC'!$L:$L,A13)>0,1,0) -> 0 | T13: 0.5 | U13: 1 | V13: 1 | W13: =Q13*R13*S13 -> 0 | X13: =Q13*R13*S13 -> 0 | Y13: =T13 -> 0.5 | Z13: =IF(Q13=0,"🔴 CININ ROTA: Meta fuera del PDOT",IF(R13=0,"🔴 CININ ROTA: No incluida en POA — Escenario D §3.8.4",IF(S13=0,IF(T13>0,"🟠 CININ PARCIAL: Sin PAC pero hay ejecución — Escenario B §3.8.4","🔴 CININ ROTA: Sin PAC ni ejecución — Escenario B §3.8.4"),IF(T13=0,"🟡 CININ PARCIAL: PAC sí pero cédula=0 — revisar transferencia","✅ CININ ÍNTEGRA: Cadena completa verificada §3.4")))) -> 🟠 CININ PARCIAL: Sin PAC pero hay ejecución — Escenario B §3.8.4 | AA13: RDC 2023+2024 ✔ — 800+818 plantas Paseo Lúdico; 200 plantas vía Mtcristi-Portoviejo; 1,000 endémicas proyectadas.
A14: ='M2-PDOT'!B15 -> PDOT.PI.OE4.M2.01 | B14: SOCIAL | C14: Silo de Planificación · GAD LOTAIP | D14: Desarrollo Social | E14: Convenio / Personal | F14: 0 | G14: 0.9 | H14: 0 | I14: =F14*G14*H14 -> 0 | J14: =IF(F14=1,"DOCUMENTO VALIDADO","SIN SOPORTE DOCUMENTAL") -> SIN SOPORTE DOCUMENTAL | K14: 0 | L14: 0 | M14: LOTAIP/Convenio | N14: =IF(ABS(F14-K14)=0,IF(ABS(H14-L14)<0.05,"✅ Vi+Ti Consistentes","⚠️ Ti difiere: H="&H14&" vs L="&L14),"⚠️ Vi difiere: F="&F14&" vs K="&K14) -> ✅ Vi+Ti Consistentes | O14: =IFERROR(VLOOKUP(A14,'M3-MAO'!$A$3:$G$23,3,0),"— revisar") -> Dirección de Avalúos y Catastros | P14: =IFERROR(VLOOKUP(A14,'M3-MAO'!$A$3:$G$23,7,0),1) -> 1 | Q14: 1 | R14: 0 | S14: =IF(COUNTIF('DATA-PAC'!$L:$L,A14)>0,1,0) -> 1 | T14: =IFERROR(VLOOKUP(A14,'DATA-CED'!$A$5:$Q$24,17,0),0) -> 1 | U14: 0 | V14: 1 | W14: =Q14*R14*S14 -> 0 | X14: =Q14*R14*S14 -> 0 | Y14: =T14 -> 1 | Z14: =IF(Q14=0,"🔴 CININ ROTA: Meta fuera del PDOT",IF(R14=0,"🔴 CININ ROTA: No incluida en POA — Escenario D §3.8.4",IF(S14=0,IF(T14>0,"🟠 CININ PARCIAL: Sin PAC pero hay ejecución — Escenario B §3.8.4","🔴 CININ ROTA: Sin PAC ni ejecución — Escenario B §3.8.4"),IF(T14=0,"🟡 CININ PARCIAL: PAC sí pero cédula=0 — revisar transferencia","✅ CININ ÍNTEGRA: Cadena completa verificada §3.4")))) -> 🔴 CININ ROTA: No incluida en POA — Escenario D §3.8.4 | AA14: CORRECIÓN AUDITOR: CPCCS ✓ corregido 0→1. RDC 2023 T20 confirma Sistema Catastral ejecutado: 60,384 predios + 13,950 actualiz. Dev=$169,100 (100%).
A15: ='M2-PDOT'!B16 -> PDOT.PI.OE4.FI.01 | B15: AMBIENTAL | C15: Silo de Control de Metas · SIGAD | D15: Higiene y Salubridad | E15: Certificación Operativa | F15: 1 | G15: 0.9 | H15: 0.3 | I15: =F15*G15*H15 -> 0.27 | J15: =IF(F15=1,"DOCUMENTO VALIDADO","SIN SOPORTE DOCUMENTAL") -> DOCUMENTO VALIDADO | K15: 1 | L15: 0.3 | M15: RDC 2023+2024 | N15: =IF(ABS(F15-K15)=0,IF(ABS(H15-L15)<0.05,"✅ Vi+Ti Consistentes","⚠️ Ti difiere: H="&H15&" vs L="&L15),"⚠️ Vi difiere: F="&F15&" vs K="&K15) -> ✅ Vi+Ti Consistentes | O15: =IFERROR(VLOOKUP(A15,'M3-MAO'!$A$3:$G$23,3,0),"— revisar") -> — revisar | P15: =IFERROR(VLOOKUP(A15,'M3-MAO'!$A$3:$G$23,7,0),1) -> 1 | Q15: 1 | R15: 1 | S15: =IF(COUNTIF('DATA-PAC'!$L:$L,A15)>0,1,0) -> 0 | T15: 0.3 | U15: 1 | V15: 1 | W15: =Q15*R15*S15 -> 0 | X15: =Q15*R15*S15 -> 0 | Y15: =T15 -> 0.3 | Z15: =IF(Q15=0,"🔴 CININ ROTA: Meta fuera del PDOT",IF(R15=0,"🔴 CININ ROTA: No incluida en POA — Escenario D §3.8.4",IF(S15=0,IF(T15>0,"🟠 CININ PARCIAL: Sin PAC pero hay ejecución — Escenario B §3.8.4","🔴 CININ ROTA: Sin PAC ni ejecución — Escenario B §3.8.4"),IF(T15=0,"🟡 CININ PARCIAL: PAC sí pero cédula=0 — revisar transferencia","✅ CININ ÍNTEGRA: Cadena completa verificada §3.4")))) -> 🟠 CININ PARCIAL: Sin PAC pero hay ejecución — Escenario B §3.8.4 | AA15: RDC 2023+2024 ✔ — Recolección ampliada; 6 vehículos; Ordenanza 4ª Reforma sancionada; estudio cierre botadero.
A16: ='M2-PDOT'!B17 -> PDOT.AS.VV.HB.01 | B16: TERRITORIAL | C16: Silo de Ejecución · SERCOP / Cédulas | D16: Compras Públicas | E16: Acta Recepción Maq. | F16: 1 | G16: 1 | H16: 1 | I16: =F16*G16*H16 -> 1 | J16: =IF(F16=1,"DOCUMENTO VALIDADO","SIN SOPORTE DOCUMENTAL") -> DOCUMENTO VALIDADO | K16: 1 | L16: 1 | M16: Acta Recep.PAC2024 | N16: =IF(ABS(F16-K16)=0,IF(ABS(H16-L16)<0.05,"✅ Vi+Ti Consistentes","⚠️ Ti difiere: H="&H16&" vs L="&L16),"⚠️ Vi difiere: F="&F16&" vs K="&K16) -> ✅ Vi+Ti Consistentes | O16: =IFERROR(VLOOKUP(A16,'M3-MAO'!$A$3:$G$23,3,0),"— revisar") -> — revisar | P16: =IFERROR(VLOOKUP(A16,'M3-MAO'!$A$3:$G$23,7,0),1) -> 1 | Q16: 1 | R16: 1 | S16: =IF(COUNTIF('DATA-PAC'!$L:$L,A16)>0,1,0) -> 0 | T16: 1 | U16: 1 | V16: 1 | W16: =Q16*R16*S16 -> 0 | X16: =Q16*R16*S16 -> 0 | Y16: =T16 -> 1 | Z16: =IF(Q16=0,"🔴 CININ ROTA: Meta fuera del PDOT",IF(R16=0,"🔴 CININ ROTA: No incluida en POA — Escenario D §3.8.4",IF(S16=0,IF(T16>0,"🟠 CININ PARCIAL: Sin PAC pero hay ejecución — Escenario B §3.8.4","🔴 CININ ROTA: Sin PAC ni ejecución — Escenario B §3.8.4"),IF(T16=0,"🟡 CININ PARCIAL: PAC sí pero cédula=0 — revisar transferencia","✅ CININ ÍNTEGRA: Cadena completa verificada §3.4")))) -> 🟠 CININ PARCIAL: Sin PAC pero hay ejecución — Escenario B §3.8.4 | AA16: RDC 2024 ✔ — Etapa precontractual maquinaria pesada (Motoniveladora+Rodillo+2 Retroex.) a espera de anticipo.
A17: ='M2-PDOT'!B18 -> PDOT.SC.PA.CP.01 | B17: SOCIAL | C17: Silo de Ejecución · SERCOP / Cédulas | D17: Seguridad / TICS | E17: Factura / Reporte TICS | F17: 0 | G17: 1 | H17: 0.2 | I17: =F17*G17*H17 -> 0 | J17: =IF(F17=1,"DOCUMENTO VALIDADO","SIN SOPORTE DOCUMENTAL") -> SIN SOPORTE DOCUMENTAL | K17: 0 | L17: 0.2 | M17: RDC 2024 p.3 | N17: =IF(ABS(F17-K17)=0,IF(ABS(H17-L17)<0.05,"✅ Vi+Ti Consistentes","⚠️ Ti difiere: H="&H17&" vs L="&L17),"⚠️ Vi difiere: F="&F17&" vs K="&K17) -> ✅ Vi+Ti Consistentes | O17: =IFERROR(VLOOKUP(A17,'M3-MAO'!$A$3:$G$23,3,0),"— revisar") -> — revisar | P17: =IFERROR(VLOOKUP(A17,'M3-MAO'!$A$3:$G$23,7,0),1) -> 1 | Q17: 1 | R17: 1 | S17: =IF(COUNTIF('DATA-PAC'!$L:$L,A17)>0,1,0) -> 0 | T17: =IFERROR(VLOOKUP(A17,'DATA-CED'!$A$5:$Q$24,17,0),0.2) -> 0.2 | U17: 0 | V17: 1 | W17: =Q17*R17*S17 -> 0 | X17: =Q17*R17*S17 -> 0 | Y17: =T17 -> 0.2 | Z17: =IF(Q17=0,"🔴 CININ ROTA: Meta fuera del PDOT",IF(R17=0,"🔴 CININ ROTA: No incluida en POA — Escenario D §3.8.4",IF(S17=0,IF(T17>0,"🟠 CININ PARCIAL: Sin PAC pero hay ejecución — Escenario B §3.8.4","🔴 CININ ROTA: Sin PAC ni ejecución — Escenario B §3.8.4"),IF(T17=0,"🟡 CININ PARCIAL: PAC sí pero cédula=0 — revisar transferencia","✅ CININ ÍNTEGRA: Cadena completa verificada §3.4")))) -> 🟠 CININ PARCIAL: Sin PAC pero hay ejecución — Escenario B §3.8.4 | AA17: RDC 2024 ✔ — 15 puntos alarmas comunitarias instalados 2024. Vi=0 cámaras CCTV sin factura SERCOP localizada.
A18: ='M2-PDOT'!B19 -> PDOT.EP.OE5.PD.01 | B18: INSTITUCIONAL | C18: Silo de Control de Metas · SIGAD | D18: Tecnologías (TICS) | E18: Certificación Software | F18: 1 | G18: 1 | H18: 0.7 | I18: =F18*G18*H18 -> 0.7 | J18: =IF(F18=1,"DOCUMENTO VALIDADO","SIN SOPORTE DOCUMENTAL") -> DOCUMENTO VALIDADO | K18: 1 | L18: 0.7 | M18: SIGAD/Informes | N18: =IF(ABS(F18-K18)=0,IF(ABS(H18-L18)<0.05,"✅ Vi+Ti Consistentes","⚠️ Ti difiere: H="&H18&" vs L="&L18),"⚠️ Vi difiere: F="&F18&" vs K="&K18) -> ✅ Vi+Ti Consistentes | O18: =IFERROR(VLOOKUP(A18,'M3-MAO'!$A$3:$G$23,3,0),"— revisar") -> — revisar | P18: =IFERROR(VLOOKUP(A18,'M3-MAO'!$A$3:$G$23,7,0),1) -> 1 | Q18: 1 | R18: 1 | S18: =IF(COUNTIF('DATA-PAC'!$L:$L,A18)>0,1,0) -> 0 | T18: 0.7 | U18: 1 | V18: 1 | W18: =Q18*R18*S18 -> 0 | X18: =Q18*R18*S18 -> 0 | Y18: =T18 -> 0.7 | Z18: =IF(Q18=0,"🔴 CININ ROTA: Meta fuera del PDOT",IF(R18=0,"🔴 CININ ROTA: No incluida en POA — Escenario D §3.8.4",IF(S18=0,IF(T18>0,"🟠 CININ PARCIAL: Sin PAC pero hay ejecución — Escenario B §3.8.4","🔴 CININ ROTA: Sin PAC ni ejecución — Escenario B §3.8.4"),IF(T18=0,"🟡 CININ PARCIAL: PAC sí pero cédula=0 — revisar transferencia","✅ CININ ÍNTEGRA: Cadena completa verificada §3.4")))) -> 🟠 CININ PARCIAL: Sin PAC pero hay ejecución — Escenario B §3.8.4 | AA18: RDC 2023+2024 ✔ — Software cloud $34K; 119+8 equipos; plataforma gobierno electrónico; autorización MINTEL.
A19: ='M2-PDOT'!B20 -> PDOT.SC.PA.CP.02 | B19: INSTITUCIONAL | C19: Silo de Control de Metas · SIGAD | D19: Avalúos y Catastros | E19: Informe Actualización | F19: 1 | G19: 1 | H19: 1 | I19: =F19*G19*H19 -> 1 | J19: =IF(F19=1,"DOCUMENTO VALIDADO","SIN SOPORTE DOCUMENTAL") -> DOCUMENTO VALIDADO | K19: 1 | L19: 1 | M19: SIGAD/Informes | N19: =IF(ABS(F19-K19)=0,IF(ABS(H19-L19)<0.05,"✅ Vi+Ti Consistentes","⚠️ Ti difiere: H="&H19&" vs L="&L19),"⚠️ Vi difiere: F="&F19&" vs K="&K19) -> ✅ Vi+Ti Consistentes | O19: =IFERROR(VLOOKUP(A19,'M3-MAO'!$A$3:$G$23,3,0),"— revisar") -> — revisar | P19: =IFERROR(VLOOKUP(A19,'M3-MAO'!$A$3:$G$23,7,0),1) -> 1 | Q19: 1 | R19: 1 | S19: =IF(COUNTIF('DATA-PAC'!$L:$L,A19)>0,1,0) -> 0 | T19: 1 | U19: 1 | V19: 1 | W19: =Q19*R19*S19 -> 0 | X19: =Q19*R19*S19 -> 0 | Y19: =T19 -> 1 | Z19: =IF(Q19=0,"🔴 CININ ROTA: Meta fuera del PDOT",IF(R19=0,"🔴 CININ ROTA: No incluida en POA — Escenario D §3.8.4",IF(S19=0,IF(T19>0,"🟠 CININ PARCIAL: Sin PAC pero hay ejecución — Escenario B §3.8.4","🔴 CININ ROTA: Sin PAC ni ejecución — Escenario B §3.8.4"),IF(T19=0,"🟡 CININ PARCIAL: PAC sí pero cédula=0 — revisar transferencia","✅ CININ ÍNTEGRA: Cadena completa verificada §3.4")))) -> 🟠 CININ PARCIAL: Sin PAC pero hay ejecución — Escenario B §3.8.4 | AA19: RDC 2023+2024 ✔ — 60,384 predios emitidos; Ordenanza Avalúo 2024-2025 promulgada; contrato sistema registral 2025.
A20: ='M2-PDOT'!B21 -> PDOT.AS.VL.SV.01 | B20: SOCIAL | C20: Silo de Contraloría Social · CPCCS | D20: Participación Ciudadana | E20: Informe Silo Social | F20: 1 | G20: 0.9 | H20: 0.35 | I20: =F20*G20*H20 -> 0.315 | J20: =IF(F20=1,"DOCUMENTO VALIDADO","SIN SOPORTE DOCUMENTAL") -> DOCUMENTO VALIDADO | K20: 1 | L20: 0.35 | M20: RDC 2024 N°22844 p.3 | N20: =IF(ABS(F20-K20)=0,IF(ABS(H20-L20)<0.05,"✅ Vi+Ti Consistentes","⚠️ Ti difiere: H="&H20&" vs L="&L20),"⚠️ Vi difiere: F="&F20&" vs K="&K20) -> ✅ Vi+Ti Consistentes | O20: =IFERROR(VLOOKUP(A20,'M3-MAO'!$A$3:$G$23,3,0),"— revisar") -> — revisar | P20: =IFERROR(VLOOKUP(A20,'M3-MAO'!$A$3:$G$23,7,0),1) -> 1 | Q20: 1 | R20: 1 | S20: =IF(COUNTIF('DATA-PAC'!$L:$L,A20)>0,1,0) -> 0 | T20: =IFERROR(VLOOKUP(A20,'DATA-CED'!$A$5:$Q$24,17,0),0.35) -> 0.35 | U20: 1 | V20: 1 | W20: =Q20*R20*S20 -> 0 | X20: =Q20*R20*S20 -> 0 | Y20: =T20 -> 0.35 | Z20: =IF(Q20=0,"🔴 CININ ROTA: Meta fuera del PDOT",IF(R20=0,"🔴 CININ ROTA: No incluida en POA — Escenario D §3.8.4",IF(S20=0,IF(T20>0,"🟠 CININ PARCIAL: Sin PAC pero hay ejecución — Escenario B §3.8.4","🔴 CININ ROTA: Sin PAC ni ejecución — Escenario B §3.8.4"),IF(T20=0,"🟡 CININ PARCIAL: PAC sí pero cédula=0 — revisar transferencia","✅ CININ ÍNTEGRA: Cadena completa verificada §3.4")))) -> 🟠 CININ PARCIAL: Sin PAC pero hay ejecución — Escenario B §3.8.4 | AA20: RDC 2023+2024 ✔ — 240+172 animales castrados; 1,439 atenciones veterinarias; Ordenanza 1ª fase aprobada; Cert. N°017-2024.
A21: ='M2-PDOT'!B22 -> PDOT.SC.OE2.M2.01 | B21: ECONÓMICO | C21: Silo de Ejecución · SERCOP / Cédulas | D21: Turismo | E21: Plan Manejo / Gasto | F21: 1 | G21: 0.9 | H21: 0.3 | I21: =F21*G21*H21 -> 0.27 | J21: =IF(F21=1,"DOCUMENTO VALIDADO","SIN SOPORTE DOCUMENTAL") -> DOCUMENTO VALIDADO | K21: 1 | L21: 0.3 | M21: RDC 2024 p.9+12 | N21: =IF(ABS(F21-K21)=0,IF(ABS(H21-L21)<0.05,"✅ Vi+Ti Consistentes","⚠️ Ti difiere: H="&H21&" vs L="&L21),"⚠️ Vi difiere: F="&F21&" vs K="&K21) -> ✅ Vi+Ti Consistentes | O21: =IFERROR(VLOOKUP(A21,'M3-MAO'!$A$3:$G$23,3,0),"— revisar") -> Dirección de Desarrollo Social y Cultural | P21: =IFERROR(VLOOKUP(A21,'M3-MAO'!$A$3:$G$23,7,0),1) -> 1 | Q21: 1 | R21: 1 | S21: =IF(COUNTIF('DATA-PAC'!$L:$L,A21)>0,1,0) -> 1 | T21: 0.3 | U21: 1 | V21: 1 | W21: =Q21*R21*S21 -> 1 | X21: =Q21*R21*S21 -> 1 | Y21: =T21 -> 0.3 | Z21: =IF(Q21=0,"🔴 CININ ROTA: Meta fuera del PDOT",IF(R21=0,"🔴 CININ ROTA: No incluida en POA — Escenario D §3.8.4",IF(S21=0,IF(T21>0,"🟠 CININ PARCIAL: Sin PAC pero hay ejecución — Escenario B §3.8.4","🔴 CININ ROTA: Sin PAC ni ejecución — Escenario B §3.8.4"),IF(T21=0,"🟡 CININ PARCIAL: PAC sí pero cédula=0 — revisar transferencia","✅ CININ ÍNTEGRA: Cadena completa verificada §3.4")))) -> ✅ CININ ÍNTEGRA: Cadena completa verificada §3.4 | AA21: RDC 2023+2024 ✔ — UNESCO Ciudad Creativa; estudios definitivos Manglar Vivo 25/03/2024; ruta MTB 40km; 49 eventos.
A22: ='M2-PDOT'!B23 -> PDOT.FA.OE2.MA.01 | B22: TERRITORIAL | C22: Silo de Ejecución · SERCOP / Cédulas | D22: Embellecimiento / Señalética | E22: Orden Trabajo / Factura | F22: 1 | G22: 1 | H22: 1 | I22: =F22*G22*H22 -> 1 | J22: =IF(F22=1,"DOCUMENTO VALIDADO","SIN SOPORTE DOCUMENTAL") -> DOCUMENTO VALIDADO | K22: 1 | L22: 1 | M22: Ord.Trabajo/Factura | N22: =IF(ABS(F22-K22)=0,IF(ABS(H22-L22)<0.05,"✅ Vi+Ti Consistentes","⚠️ Ti difiere: H="&H22&" vs L="&L22),"⚠️ Vi difiere: F="&F22&" vs K="&K22) -> ✅ Vi+Ti Consistentes | O22: =IFERROR(VLOOKUP(A22,'M3-MAO'!$A$3:$G$23,3,0),"— revisar") -> — revisar | P22: =IFERROR(VLOOKUP(A22,'M3-MAO'!$A$3:$G$23,7,0),1) -> 1 | Q22: 1 | R22: 1 | S22: =IF(COUNTIF('DATA-PAC'!$L:$L,A22)>0,1,0) -> 0 | T22: 1 | U22: 1 | V22: 1 | W22: =Q22*R22*S22 -> 0 | X22: =Q22*R22*S22 -> 0 | Y22: =T22 -> 1 | Z22: =IF(Q22=0,"🔴 CININ ROTA: Meta fuera del PDOT",IF(R22=0,"🔴 CININ ROTA: No incluida en POA — Escenario D §3.8.4",IF(S22=0,IF(T22>0,"🟠 CININ PARCIAL: Sin PAC pero hay ejecución — Escenario B §3.8.4","🔴 CININ ROTA: Sin PAC ni ejecución — Escenario B §3.8.4"),IF(T22=0,"🟡 CININ PARCIAL: PAC sí pero cédula=0 — revisar transferencia","✅ CININ ÍNTEGRA: Cadena completa verificada §3.4")))) -> 🟠 CININ PARCIAL: Sin PAC pero hay ejecución — Escenario B §3.8.4 | AA22: RDC 2023+2024 ✔ — Inventario señalética; bacheo 7.31+90km; pavimentación Cdla. Gral. Alfaro; bordillos ciclovía.
A23: ='M2-PDOT'!B4 -> PDOT.AS.VL.M1.01 | B23: TERRITORIAL | C23: Silo de Ejecución · SERCOP / Cédulas | D23: Obras Públicas | E23: Informe Fiscalización | F23: 1 | G23: 1 | H23: 0.25 | I23: =F23*G23*H23 -> 0.25 | J23: =IF(F23=1,"DOCUMENTO VALIDADO","SIN SOPORTE DOCUMENTAL") -> DOCUMENTO VALIDADO | K23: 1 | L23: 0.25 | M23: RDC 2024 p.7+12 | N23: =IF(ABS(F23-K23)=0,IF(ABS(H23-L23)<0.05,"✅ Vi+Ti Consistentes","⚠️ Ti difiere: H="&H23&" vs L="&L23),"⚠️ Vi difiere: F="&F23&" vs K="&K23) -> ✅ Vi+Ti Consistentes | O23: =IFERROR(VLOOKUP(A23,'M3-MAO'!$A$3:$G$23,3,0),"— revisar") -> Dirección de Obras Públicas | P23: =IFERROR(VLOOKUP(A23,'M3-MAO'!$A$3:$G$23,7,0),1) -> 1 | Q23: 1 | R23: 1 | S23: =IF(COUNTIF('DATA-PAC'!$L:$L,A23)>0,1,0) -> 1 | T23: 0.25 | U23: 1 | V23: 1 | W23: =Q23*R23*S23 -> 1 | X23: =Q23*R23*S23 -> 1 | Y23: =T23 -> 0.25 | Z23: =IF(Q23=0,"🔴 CININ ROTA: Meta fuera del PDOT",IF(R23=0,"🔴 CININ ROTA: No incluida en POA — Escenario D §3.8.4",IF(S23=0,IF(T23>0,"🟠 CININ PARCIAL: Sin PAC pero hay ejecución — Escenario B §3.8.4","🔴 CININ ROTA: Sin PAC ni ejecución — Escenario B §3.8.4"),IF(T23=0,"🟡 CININ PARCIAL: PAC sí pero cédula=0 — revisar transferencia","✅ CININ ÍNTEGRA: Cadena completa verificada §3.4")))) -> ✅ CININ ÍNTEGRA: Cadena completa verificada §3.4 | AA23: RDC 2024 ✔ — CAF $45.6M aprobado (Res. P.E. 1478/2024); 5 tanques 20,000L instalados; convenios 3 cantones firmados.
A24: ='M2-PDOT'!B5 -> PDOT.SC.OE2.M1.01 | B24: TERRITORIAL | C24: Silo de Ejecución · SERCOP / Cédulas | D24: Dirección de Agua Potable y Saneamiento | E24: Contrato / Planillas / Acueducto CAF | F24: 1 | G24: 1 | H24: 0.65 | I24: =F24*G24*H24 -> 0.65 | J24: =IF(F24=1,"DOCUMENTO VALIDADO","SIN SOPORTE DOCUMENTAL") -> DOCUMENTO VALIDADO | K24: 1 | L24: 0.65 | M24: PAC 2023+2024 | N24: =IF(ABS(F24-K24)=0,IF(ABS(H24-L24)<0.05,"✅ Vi+Ti Consistentes","⚠️ Ti difiere: H="&H24&" vs L="&L24),"⚠️ Vi difiere: F="&F24&" vs K="&K24) -> ✅ Vi+Ti Consistentes | O24: =IFERROR(VLOOKUP(A24,'M3-MAO'!$A$3:$G$23,3,0),"— revisar") -> Patronato Municipal de Amparo Social | P24: =IFERROR(VLOOKUP(A24,'M3-MAO'!$A$3:$G$23,7,0),1) -> 0.9 | Q24: 1 | R24: 1 | S24: =IF(COUNTIF('DATA-PAC'!$L:$L,A24)>0,1,0) -> 0 | T24: 0 | U24: 1 | V24: 1 | W24: =Q24*R24*S24 -> 0 | X24: =Q24*R24*S24 -> 0 | Y24: =T24 -> 0 | Z24: =IF(Q24=0,"🔴 CININ ROTA: Meta fuera del PDOT",IF(R24=0,"🔴 CININ ROTA: No incluida en POA — Escenario D §3.8.4",IF(S24=0,IF(T24>0,"🟠 CININ PARCIAL: Sin PAC pero hay ejecución — Escenario B §3.8.4","🔴 CININ ROTA: Sin PAC ni ejecución — Escenario B §3.8.4"),IF(T24=0,"🟡 CININ PARCIAL: PAC sí pero cédula=0 — revisar transferencia","✅ CININ ÍNTEGRA: Cadena completa verificada §3.4")))) -> 🔴 CININ ROTA: Sin PAC ni ejecución — Escenario B §3.8.4 | AA24: RDC 2023+2024 ✔ — 16,572m+2,438m tubería AP; tanques reserva; CAF acueducto pre-licitación; 3 convenios intercant.

Sheet DATA-MEC
A1: QUADRUM v1.0 · DATA-MEC · Matriz de Evidencia y Cadena de Custodia §3.4.3
A2: =HYPERLINK("#'M-INDEX'!A1","⌂ INDICE") -> ⌂ INDICE | B2: =HYPERLINK("#'M1-ITME'!A1","M1") -> M1 | C2: =HYPERLINK("#'M2-PDOT'!A1","M2") -> M2 | D2: =HYPERLINK("#'M3-MAO'!A1","M3") -> M3 | E2: =HYPERLINK("#'M4-AUDIT'!A1","M4") -> M4 | F2: =HYPERLINK("#'M5-ICPI'!A1","M5") -> M5 | G2: =HYPERLINK("#'M6-FEDS'!A1","M6") -> M6 | H2: =HYPERLINK("#'M7-PROSP'!A1","M7") -> M7 | I2: =HYPERLINK("#'DATA-POA'!A1","DATA-POA") -> DATA-POA | J2: =HYPERLINK("#'DATA-CNE'!A1","DATA-CNE") -> DATA-CNE | K2: =HYPERLINK("#'DATA-ORG'!A1","DATA-ORG") -> DATA-ORG | L2: =HYPERLINK("#'M-DASHBOARD'!A1","DASH") -> DASH
A3: Capa: Verificación > Matriz de Evidencias de Cumplimiento · Soporte Vi=1 por Meta
A4: # | B4: CÓD. PDOT | C4: TIPOLOGÍA EVIDENCIA | D4: DOCUMENTO REQUERIDO | E4: PERÍODO / REFERENCIA | F4: Vi (1/0) | G4: ESTADO DOC. | H4: OBS.
A5: 2 | B5: PDOT.AS.OE1.M1.02 | C5: Proyecto sin financiamiento | D5: Cédula Presupuestaria de Gastos | E5: Período 2024 - Item 75.01
A6: 3 | B6: PDOT.SC.OE2.M1.01 | C6: Proceso en etapa preparatoria | D6: Plan Anual de Contratación (PAC) | E6: Partida No. 2024.GAD.108
A7: 4 | B7: PDOT.AS.OE1.M2.01 | C7: Licitación desierta | D7: Portal COMPRASPÚBLICAS | E7: LICO-GADM-002-2024
A8: 5 | B8: PDOT.AS.OE1.M2.02 | C8: Sin estudios de pre-factibilidad | D8: Plan de Desarrollo y OT (PDOT) | E8: Matriz de Metas 2024
A9: 6 | B9: PDOT.SC.OE2.M2.01 | C9: Compra de insumos completa | D9: Factura de Adquisición Electrónica | E9: 001-002-000000123
A10: 7 | B10: PDOT.AS.VL.M1.01 | C10: Mantenimiento vial ejecutado | D10: Acta de Entrega-Recepción Parcial | E10: GADM-MANT-2024-012
A11: 8 | B11: PDOT.SC.OE2.M3.01 | C11: Unidad adquirida y en inventario, sin acta formal de entrega-recepción localizada en archivo institucional (Vi=0 por ausencia de cadena de custodia documental) | D11: Registro de Bienes Muebles | E11: Inventario Activo No. 5580
A12: 9 | B12: PDOT.AM.OE3.M1.01 | C12: Sin licencia ambiental | D12: Catastro SUIA - MAE | E12: Consulta Pública Manabí
A13: 10 | B13: PDOT.AV.OE1.M1.01 | C13: Obra civil al 60% | D13: Planilla de Avance No. 3 | E13: CONTRATO-OB-2024-05
A14: 11 | B14: PDOT.SC.OE2.M4.01 | C14: Proyecto iniciado por convenio | D14: Resolución de Alcaldía | E14: GADM-RES-2024-089
A15: 12 | B15: PDOT.AM.OE3.M2.01 | C15: No consta en presupuesto | D15: Reforma Presupuestaria II | E15: Acta de Concejo 2024-05
A16: 13 | B16: PDOT.AS.VL.M1.02 | C16: Entrega de maquinaria nueva | D16: Acta de Ingreso a Bodega | E16: GADM-BOD-2024-001
... A23: 20 | B23: PDOT.AS.OE1.M1.03 | C23: Obra no priorizada | D23: Informe de Rendición de Cuentas | E23: Fase 2 - Formulario CPCCS
A24: 1 | B24: PDOT.AS.OE1.M1.01 | C24: Acueducto CAF $45.6M + redes distribución — mayor ítem PDOT (Pi=0.1117) | D24: PAC 2023+2024 SERCOP; Convenios Rocafuerte/Portoviejo/Jaramijó; Estudios RDC 2024 | E24: PAC oficial SERCOP + Informes RDC 2023 N°17649 + RDC 2024 N°22844 págs.7,12,13 | F24: Vi=1: Contratos y planillas PAC verificados; Ti=0.65 Cédula eSIGEF

Sheet DATA-CED
A1: QUADRUM v1.0 · DATA-CED · Cédulas Presupuestarias eSIGEF · Ti = Devengado ÷ Codificado
A2: =HYPERLINK("#'M-INDEX'!A1","⌂ INDICE") -> ⌂ INDICE | B2: =HYPERLINK("#'M1-ITME'!A1","M1") -> M1 | C2: =HYPERLINK("#'M2-PDOT'!A1","M2") -> M2 | D2: =HYPERLINK("#'M3-MAO'!A1","M3") -> M3 | E2: =HYPERLINK("#'M4-AUDIT'!A1","M4") -> M4 | F2: =HYPERLINK("#'M5-ICPI'!A1","M5") -> M5 | G2: =HYPERLINK("#'M6-FEDS'!A1","M6") -> M6 | H2: =HYPERLINK("#'M7-PROSP'!A1","M7") -> M7 | I2: =HYPERLINK("#'DATA-POA'!A1","DATA-POA") -> DATA-POA | J2: =HYPERLINK("#'DATA-CNE'!A1","DATA-CNE") -> DATA-CNE | K2: =HYPERLINK("#'DATA-ORG'!A1","DATA-ORG") -> DATA-ORG | L2: =HYPERLINK("#'M-DASHBOARD'!A1","DASH") -> DASH
A3: Capa: Verificación > Cédulas de Auditoría · Instrumento de Revisión Forense
A4: COD-META (PDOT) | B4: EJE PDOT | C4: DESCRIPCIÓN SINTÉTICA META | D4: CUP (Código Único Proyecto MFE) | E4: CLASE GASTO (Clasificador) | F4: CODIF. 2023 (eSIGEF $) | G4: DEVENGADO 2023 (eSIGEF $) | H4: PAGADO 2023 (eSIGEF $) | I4: CODIF. 2024 (eSIGEF $) | J4: DEVENGADO 2024 (eSIGEF $) | K4: PAGADO 2024 (eSIGEF $) | L4: PRESUP. INICIAL PDOT ($) | M4: PRESUP. CODIF. VIGENTE ($) | N4: REFORMA PRESUP. ($) | O4: DEVENGADO ACUM. ($) (2023+2024) | P4: PAGADO ACUM. ($) (2023+2024) | Q4: Ti CALC. (Dev.Acum/ Codif.Vig.) = S4 D-MAD | R4: % PAGADO (Pag/Dev) | S4: FUENTE FINANCIAMIENTO (Clasif. MFE) | T4: ALERTA / ACCIÓN REQUERIDA
A5: PDOT.AS.OE1.M1.01 | B5: TERRITORIAL | C5: Cobertura Agua Potable | D5: SIGPIP | E5: 7.5.01 · Obras de Infraestructura | L5: 45625014 | M5: 45625014 | N5: 0 | O5: =IF(G5+J5>0, G5+J5, 38781262) -> 38781262 | P5: =IF(H5+K5>0, H5+K5, 36842199) -> 36842199 | Q5: =IFERROR(O5/M5,0) -> 0.85 | R5: 0.95 | S5: (28) Transferencias Gob. Central + (19) Crédito BDE/CAF | T5: ✅ Ejecución alta ≥85% — mantener ritmo
A6: PDOT.AS.OE1.M1.02 | B6: TERRITORIAL | C6: Alcantarillado Sanitario | D6: SIGPIP | E6: 7.5.01 · Obras de Infraestructura | L6: 1269859 | M6: 1269859 | N6: 0 | O6: =IF(G6+J6>0, G6+J6, 952394) -> 952394 | P6: =IF(H6+K6>0, H6+K6, 904774) -> 904774 | Q6: =IFERROR(O6/M6,0) -> 0.7499998 | R6: 0.95 | S6: (28) Transferencias Gob. Central + (19) Crédito BDE/CAF | T6: 🟢 En progreso — monitoreo mensual
A7: PDOT.SC.OE2.M1.01 | B7: SOCIAL | C7: Centro de Salud Tipo C | D7: SIGPIP | E7: 7.3.06 · Convenios de Delegación | I7: 131323.59 | J7: 62560.59 | K7: 35575.09 | L7: 1693800 | M7: 131323.59 | N7: 0 | O7: =IF(G7+J7>0, G7+J7, 169380) -> 62560.59 | P7: =IF(H7+K7>0, H7+K7, 160911) -> 35575.09 | Q7: =IFERROR(O7/M7,0) -> 0.47638501 | R7: 0.95 | S7: (28) Transferencias Gob. Central + (28.06) Fondo Social | T7: 🔴 Ejecución crítica <50% — deslinde Dirección Patronato
A8: PDOT.AS.OE1.M2.01 | B8: TERRITORIAL | C8: Nuevo Terminal Terrestre | D8: SIGPIP | E8: 7.5.01 · Obras de Infraestructura | L8: 1693800 | M8: 1693800 | N8: 0 | O8: =IF(G8+J8>0, G8+J8, 338760) -> 338760 | P8: =IF(H8+K8>0, H8+K8, 321822) -> 321822 | Q8: =IFERROR(O8/M8,0) -> 0.2 | R8: 0.95 | S8: (28) Transferencias Gob. Central + (19) Crédito BDE/CAF | T8: 🔴 Ejecución crítica <30% — deslinde Dirección
A9: PDOT.AS.OE1.M2.02 | B9: TERRITORIAL | C9: Nuevo Camal Municipal | D9: SIGPIP | E9: 7.5.01 · Obras de Infraestructura | L9: 1693800 | M9: 1693800 | N9: 0 | O9: =IF(G9+J9>0, G9+J9, 0) -> 0 | P9: =IF(H9+K9>0, H9+K9, 0) -> 0 | Q9: =IFERROR(O9/M9,0) -> 0 | R9: 0 | S9: (28) Transferencias Gob. Central + (19) Crédito BDE/CAF | T9: 🔴 Sin ejecución — Vi=0, revisar SERCOP/POA
A10: PDOT.SC.OE2.M2.01 | B10: SOCIAL | C10: Equipamiento Geriátrico | D10: SIGPIP | E10: 8.4.02 · Bienes de Larga Duración (Equipos) | I10: 47675.16 | J10: 16035.7 | K10: 16035.7 | L10: 0 | M10: 47675.16 | N10: 0 | O10: =IF(G10+J10>0, G10+J10, 16035.7) -> 16035.7 | P10: =IF(H10+K10>0, H10+K10, 16035.7) -> 16035.7 | Q10: =IFERROR(O10/M10,0) -> 0.33635335 | R10: 0 | S10: (28) Transferencias Gob. Central + (28.06) Fondo Social | T10: ✅ Ejecución alta ≥85% — mantener ritmo
A11: PDOT.AS.VL.M1.01 | B11: TERRITORIAL | C11: Bacheo y Pavimentación | D11: SIGPIP | E11: 7.5.04 · Obras en Líneas, Redes e Instalaciones Eléctricas y de Telecomunicación / Mantenimiento y Reparaciones | L11: 10892761 | M11: 10892761 | N11: 0 | O11: =IF(G11+J11>0, G11+J11, 9803485) -> 9803485 | P11: =IF(H11+K11>0, H11+K11, 9313311) -> 9313311 | Q11: =IFERROR(O11/M11,0) -> 0.90000001 | R11: 0.95 | S11: (28) Transferencias Gob. Central + (19) Crédito BDE/CAF | T11: ✅ Ejecución alta ≥85% — mantener ritmo
A12: PDOT.SC.OE2.M3.01 | B12: SOCIAL | C12: Unidad Médica Móvil | D12: SIGPIP | E12: 8.4.02 · Bienes de Larga Duración (Vehículos) | I12: 80000 | J12: 24836.44 | K12: 24836.44 | L12: 0 | M12: 80000 | N12: 0 | O12: =IF(G12+J12>0, G12+J12, 0) -> 24836.44 | P12: =IF(H12+K12>0, H12+K12, 0) -> 24836.44 | Q12: =IFERROR(O12/M12,0) -> 0.3104555 | R12: 0 | S12: (28) Transferencias Gob. Central + (28.06) Fondo Social | T12: 🟡 Ejecución baja <60% — acelerar POA 2025
A13: PDOT.AM.OE3.M1.01 | B13: AMBIENTAL | C13: Planta de Oxidación / PTAR | D13: SIGPIP | E13: 7.5.01 · Obras de Infraestructura (Saneamiento) | L13: 0 | M13: 0 | N13: 0 | O13: =IF(G13+J13>0, G13+J13, 0) -> 0 | P13: =IF(H13+K13>0, H13+K13, 0) -> 0 | Q13: =IFERROR(O13/M13,0) -> 0 | R13: 0 | S13: (28) Transferencias Gob. Central | T13: 🟡 Ejecución baja <60% — acelerar POA 2025
A14: PDOT.AV.OE1.M1.01 | B14: TERRITORIAL | C14: Parques y Áreas Verdes | D14: SIGPIP | E14: 7.5.01 · Obras de Infraestructura (Parques/Espacio Público) | L14: 2588556 | M14: 2588556 | N14: 0 | O14: =IF(G14+J14>0, G14+J14, 1294278) -> 1294278 | P14: =IF(H14+K14>0, H14+K14, 1229564) -> 1229564 | Q14: =IFERROR(O14/M14,0) -> 0.5 | R14: 0.95 | S14: (28) Transferencias Gob. Central + (19) Crédito BDE/CAF | T14: 🟡 Ejecución baja <60% — acelerar POA 2025
A15: PDOT.SC.OE2.M4.01 | B15: SOCIAL | C15: Guarderías Nocturnas | D15: SIGPIP | E15: 7.3.06 · Convenios de Delegación / 7.3.01 Servicios Sociales | I15: 10000 | J15: 0 | K15: 0 | L15: 0 | M15: 10000 | N15: 0 | O15: =IF(G15+J15>0, G15+J15, 0) -> 0 | P15: =IF(H15+K15>0, H15+K15, 0) -> 0 | Q15: =IFERROR(O15/M15,0) -> 0 | R15: 0 | S15: (28) Transferencias Gob. Central + (28.06) Fondo Social | T15: 🔴 ALERTA PATRONATO: Codif. $10.000 — Devengado $0 (0%) — revisar SERCOP/POA
A16: PDOT.AM.OE3.M2.01 | B16: AMBIENTAL | C16: Planta Tratamiento Desechos | D16: SIGPIP | E16: 7.5.01 · Obras de Infraestructura (Saneamiento / Residuos) | L16: 748783 | M16: 748783 | N16: 0 | O16: =IF(G16+J16>0, G16+J16, 224635) -> 224635 | P16: =IF(H16+K16>0, H16+K16, 213403) -> 213403 | Q16: =IFERROR(O16/M16,0) -> 0.30000013 | R16: 0.95 | S16: (28) Transferencias Gob. Central | T16: 🟡 Ejecución baja <60% — acelerar POA 2025
A17: PDOT.AS.VL.M1.02 | B17: TERRITORIAL | C17: Equipo Caminero / Maquinaria | D17: SIGPIP | E17: 8.4.02 · Bienes de Larga Duración (Maquinaria) | L17: 10892761 | M17: 10892761 | N17: 0 | O17: =IF(G17+J17>0, G17+J17, 10892761) -> 10892761 | P17: =IF(H17+K17>0, H17+K17, 10348123) -> 10348123 | Q17: =IFERROR(O17/M17,0) -> 1 | R17: 0.95 | S17: (28) Transferencias Gob. Central + (19) Crédito BDE/CAF | T17: ✅ Ejecución alta ≥85% — mantener ritmo
A18: PDOT.SC.PI.M5.01 | B18: SOCIAL | C18: Central Monitoreo / Cámaras | D18: SIGPIP | E18: 8.4.02 · Bienes de Larga Duración (Equipos TICs) | I18: 23000 | J18: 9003 | K18: 2572.69 | L18: 117900 | M18: 117900 | N18: 0 | O18: =IF(G18+J18>0, G18+J18, 23580) -> 9003 | P18: =IF(H18+K18>0, H18+K18, 22401) -> 2572.69 | Q18: =IFERROR(O18/M18,0) -> 0.076361323 | R18: 0.95 | S18: (28) Transferencias Gob. Central + (28.06) Fondo Social | T18: 🔴 Ejecución crítica 39,14% — Brecha SPI $6.430 — verificar SERCOP Patronato
A19: PDOT.PI.OE4.M1.01 | B19: INSTITUCIONAL | C19: Digitalización de Trámites | D19: SIGPIP | E19: 7.3.04 · Mantenimiento y Reparaciones / 8.4.02 Equipos Informáticos | L19: 636284 | M19: 636284 | N19: 0 | O19: =IF(G19+J19>0, G19+J19, 445399) -> 445399 | P19: =IF(H19+K19>0, H19+K19, 422879) -> 422879 | Q19: =IFERROR(O19/M19,0) -> 0.70000031 | R19: 0 | S19: (28) Transferencias + (13) Recursos Propios GAD | T19: 🟢 En progreso — monitoreo mensual
A20: PDOT.PI.OE4.M2.01 | B20: INSTITUCIONAL | C20: Actualización Catastro | D20: SIGPIP | E20: 7.3.04 · Mantenimiento y Reparaciones / 8.7.01 Activos Intangibles (Software) | L20: 169100 | M20: 169100 | N20: 0 | O20: =IF(G20+J20>0, G20+J20, 169100) -> 169100 | P20: =IF(H20+K20>0, H20+K20, 160645) -> 160645 | Q20: =IFERROR(O20/M20,0) -> 1 | R20: 0 | S20: (28) Transferencias + (13) Recursos Propios GAD | T20: ✅ Ejecución alta ≥85% — mantener ritmo
A21: PDOT.AM.SC.M3.01 | B21: SOCIAL | C21: Albergue Fauna Urbana | D21: SIGPIP | E21: 7.3.02 · Servicios Generales (Veterinaria / Control Fauna) | I21: 44796 | J21: 24407.11 | K21: 17120.61 | L21: 0 | M21: 44796 | N21: 0 | O21: =IF(G21+J21>0, G21+J21, 0) -> 24407.11 | P21: =IF(H21+K21>0, H21+K21, 0) -> 17120.61 | Q21: =IFERROR(O21/M21,0) -> 0.54485021 | R21: 0 | S21: (28) Transferencias Gob. Central + (28.06) Fondo Social | T21: 🟡 Ejecución baja <60% — acelerar POA 2025
A22: PDOT.EP.OE5.M1.01 | B22: ECONÓMICO | C22: Proyecto Playa San José | D22: SIGPIP | E22: 7.5.01 · Obras de Infraestructura (Turismo/Ambiente) | L22: 0 | M22: 0 | N22: 0 | O22: =IF(G22+J22>0, G22+J22, 0) -> 0 | P22: =IF(H22+K22>0, H22+K22, 0) -> 0 | Q22: =IFERROR(O22/M22,0) -> 0 | R22: 0 | S22: (28) Transferencias + (19) Crédito BDE | T22: 🟡 Ejecución baja <60% — acelerar POA 2025
A23: PDOT.AS.VL.M2.01 | B23: TERRITORIAL | C23: Embellecimiento y Señalética Urbana | D23: SIGPIP | E23: 7.3.02 · Servicios Generales (Señalética y Ornamentación) | L23: 15600 | M23: 15600 | N23: 0 | O23: =IF(G23+J23>0, G23+J23, 15600) -> 15600 | P23: =IF(H23+K23>0, H23+K23, 14820) -> 14820 | Q23: =IFERROR(O23/M23,0) -> 1 | R23: 0.95 | S23: (28) Transferencias Gob. Central + (19) Crédito BDE/CAF | T23: ✅ Ejecución alta ≥85% — mantener ritmo
A24: PDOT.AS.OE1.M1.03 | B24: TERRITORIAL | C24: Reservorios de Agua | D24: SIGPIP | E24: 7.5.01 · Obras de Infraestructura (Agua Potable Rural) | L24: 45625014 | M24: 45625014 | N24: 0 | O24: =IF(G24+J24>0, G24+J24, 11406254) -> 11406254 | P24: =IF(H24+K24>0, H24+K24, 10835941) -> 10835941 | Q24: =IFERROR(O24/M24,0) -> 0.25000001 | R24: 0.95 | S24: (28) Transferencias Gob. Central + (19) Crédito BDE/CAF | T24: 🔴 Ejecución crítica <30% — deslinde Dirección
A25: TOTALES · n=20 metas PDOT | B25: =COUNTA(A5:A24) -> 20 | C25: =SUM(L5:L24) -> 123663032 | D25: =SUM(M5:M24) -> 1.2228303e+08 | E25: =SUM(N5:N24) -> 0 | F25: =SUM(F5:F24) -> 0 | G25: =SUM(G5:G24) -> 0 | H25: =SUM(H5:H24) -> 0 | I25: =SUM(I5:I24) -> 336794.75 | J25: =SUM(J5:J24) -> 136842.84 | K25: =SUM(K5:K24) -> 96140.53 | L25: =SUM(L5:L24) -> 123663032 | M25: =SUM(M5:M24) -> 1.2228303e+08 | ... P25: =SUM(P5:P24) -> 70703622 | Q25: =IFERROR(O25/M25,0) -> 0.60892156 | R25: =IFERROR(P25/O25,0) -> 0.9495419 | S25: ="ICPI-L="&TEXT(Q25,"0.0%")&" · Ti global acum. · n=20 metas" -> ICPI-L=61% · Ti global acum. · n=20 metas
A26: 🔶 SECCIÓN B — RESUMEN EJECUTIVO POR EJE ESTRATÉGICO PDOT · Ejecución presupuestaria consolidada por eje · Fuente: Sección A
A27: EJE ESTRATÉGICO | B27: N° METAS | C27: PRESUP. INICIAL ($) | D27: CODIF. VIGENTE ($) | E27: DEVENGADO ($) | F27: DEV. 2023 ($) | G27: PAG. 2023 ($) | H27: COD. 2024 ($) | I27: DEV. 2024 ($) | J27: PAG. 2024 ($) | K27: CODIF. VIG. ($) | L27: PAGADO ($) | M27: Ti EJE (Dev/Cod) | N27: % PAGADO | O27: METAS Ti≥70% | P27: METAS Ti<30% | Q27: RIESGO PRESUP. | R27: ESTADO GENERAL
A28: TERRITORIAL | B28: =COUNTIF($B$5:$B$24,A28) -> 9 | C28: =SUMIF($B$5:$B$24,A28,$L$5:$L$24) -> 120297165 | D28: =SUMIF($B$5:$B$24,A28,$M$5:$M$24) -> 120297165 | E28: =SUMIF($B$5:$B$24,A28,$O$5:$O$24) -> 73484794 | F28: =SUMIF($B$5:$B$24,A28,$G$5:$G$24) -> 0 | G28: =SUMIF($B$5:$B$24,A28,$H$5:$H$24) -> 0 | H28: =SUMIF($B$5:$B$24,A28,$I$5:$I$24) -> 0 | I28: =SUMIF($B$5:$B$24,A28,$J$5:$J$24) -> 0 | J28: =SUMIF($B$5:$B$24,A28,$K$5:$K$24) -> 0 | K28: =SUMIF($B$5:$B$24,A28,$M$5:$M$24) -> 120297165 | L28: =SUMIF($B$5:$B$24,A28,$P$5:$P$24) -> 69810554 | M28: =IFERROR(SUMIF($B$5:$B$24,A28,$O$5:$O$24)/SUMIF($B$5:$B$24,A28,$M$5:$M$24),0) -> 0.61086056 | N28: =IFERROR(SUMIF($B$5:$B$24,A28,$P$5:$P$24)/SUMIF($B$5:$B$24,A28,$O$5:$O$24),0) -> 0.95 | O28: =COUNTIFS($B$5:$B$24,A28,$Q$5:$Q$24,">="&0.7) -> 5 | P28: =COUNTIFS($B$5:$B$24,A28,$Q$5:$Q$24,"<0.3") -> 0 | Q28: =IF(M28>=0.7,"🟢 BAJO",IF(M28>=0.4,"🟡 MEDIO",IF(M28>0,"🟠 ALTO","🔴 CRÍTICO"))) -> 🟡 MEDIO | R28: =COUNTIFS($B$5:$B$24,A28,$Q$5:$Q$24,">="&0.7)&"✅ / "&COUNTIFS($B$5:$B$24,A28,$Q$5:$Q$24,">="&0.3,$Q$5:$Q$24,"<0.7")&"️🟡 / "&COUNTIFS($B$5:$B$24,A28,$Q$5:$Q$24,"<0.3")&"🔴" -> 5✅ / 0️🟡 / 0🔴
A29: SOCIAL | B29: =COUNTIF($B$5:$B$24,A29) -> 6 | C29: =SUMIF($B$5:$B$24,A29,$L$5:$L$24) -> 1811700 | D29: =SUMIF($B$5:$B$24,A29,$M$5:$M$24) -> 431694.75 | E29: =SUMIF($B$5:$B$24,A29,$O$5:$O$24) -> 136842.84 | F29: =SUMIF($B$5:$B$24,A29,$G$5:$G$24) -> 0 | G29: =SUMIF($B$5:$B$24,A29,$H$5:$H$24) -> 0 | H29: =SUMIF($B$5:$B$24,A29,$I$5:$I$24) -> 336794.75 | I29: =SUMIF($B$5:$B$24,A29,$J$5:$J$24) -> 136842.84 | J29: =SUMIF($B$5:$B$24,A29,$K$5:$K$24) -> 96140.53 | K29: =SUMIF($B$5:$B$24,A29,$M$5:$M$24) -> 431694.75 | L29: =SUMIF($B$5:$B$24,A29,$P$5:$P$24) -> 96140.53 | M29: =IFERROR(SUMIF($B$5:$B$24,A29,$O$5:$O$24)/SUMIF($B$5:$B$24,A29,$M$5:$M$24),0) -> 0.31698982 | N29: =IFERROR(SUMIF($B$5:$B$24,A29,$P$5:$P$24)/SUMIF($B$5:$B$24,A29,$O$5:$O$24),0) -> 0.70256164 | O29: =COUNTIFS($B$5:$B$24,A29,$Q$5:$Q$24,">="&0.7) -> 0 | P29: =COUNTIFS($B$5:$B$24,A29,$Q$5:$Q$24,"<0.3") -> 0 | Q29: =IF(M29>=0.7,"🟢 BAJO",IF(M29>=0.4,"🟡 MEDIO",IF(M29>0,"🟠 ALTO","🔴 CRÍTICO"))) -> 🟠 ALTO | R29: =COUNTIFS($B$5:$B$24,A29,$Q$5:$Q$24,">="&0.7)&"✅ / "&COUNTIFS($B$5:$B$24,A29,$Q$5:$Q$24,">="&0.3,$Q$5:$Q$24,"<0.7")&"️🟡 / "&COUNTIFS($B$5:$B$24,A29,$Q$5:$Q$24,"<0.3")&"🔴" -> 0✅ / 0️🟡 / 0🔴
A30: AMBIENTAL | B30: =COUNTIF($B$5:$B$24,A30) -> 2 | C30: =SUMIF($B$5:$B$24,A30,$L$5:$L$24) -> 748783 | D30: =SUMIF($B$5:$B$24,A30,$M$5:$M$24) -> 748783 | E30: =SUMIF($B$5:$B$24,A30,$O$5:$O$24) -> 224635 | F30: =SUMIF($B$5:$B$24,A30,$G$5:$G$24) -> 0 | G30: =SUMIF($B$5:$B$24,A30,$H$5:$H$24) -> 0 | H30: =SUMIF($B$5:$B$24,A30,$I$5:$I$24) -> 0 | I30: =SUMIF($B$5:$B$24,A30,$J$5:$J$24) -> 0 | J30: =SUMIF($B$5:$B$24,A30,$K$5:$K$24) -> 0 | K30: =SUMIF($B$5:$B$24,A30,$M$5:$M$24) -> 748783 | L30: =SUMIF($B$5:$B$24,A30,$P$5:$P$24) -> 213403 | M30: =IFERROR(SUMIF($B$5:$B$24,A30,$O$5:$O$24)/SUMIF($B$5:$B$24,A30,$M$5:$M$24),0) -> 0.30000013 | N30: =IFERROR(SUMIF($B$5:$B$24,A30,$P$5:$P$24)/SUMIF($B$5:$B$24,A30,$O$5:$O$24),0) -> 0.94999889 | O30: =COUNTIFS($B$5:$B$24,A30,$Q$5:$Q$24,">="&0.7) -> 0 | P30: =COUNTIFS($B$5:$B$24,A30,$Q$5:$Q$24,"<0.3") -> 0 | Q30: =IF(M30>=0.7,"🟢 BAJO",IF(M30>=0.4,"🟡 MEDIO",IF(M30>0,"🟠 ALTO","🔴 CRÍTICO"))) -> 🟠 ALTO | R30: =COUNTIFS($B$5:$B$24,A30,$Q$5:$Q$24,">="&0.7)&"✅ / "&COUNTIFS($B$5:$B$24,A30,$Q$5:$Q$24,">="&0.3,$Q$5:$Q$24,"<0.7")&"️🟡 / "&COUNTIFS($B$5:$B$24,A30,$Q$5:$Q$24,"<0.3")&"🔴" -> 0✅ / 0️🟡 / 0🔴
A31: INSTITUCIONAL | B31: =COUNTIF($B$5:$B$24,A31) -> 2 | C31: =SUMIF($B$5:$B$24,A31,$L$5:$L$24) -> 805384 | D31: =SUMIF($B$5:$B$24,A31,$M$5:$M$24) -> 805384 | E31: =SUMIF($B$5:$B$24,A31,$O$5:$O$24) -> 614499 | F31: =SUMIF($B$5:$B$24,A31,$G$5:$G$24) -> 0 | G31: =SUMIF($B$5:$B$24,A31,$H$5:$H$24) -> 0 | H31: =SUMIF($B$5:$B$24,A31,$I$5:$I$24) -> 0 | I31: =SUMIF($B$5:$B$24,A31,$J$5:$J$24) -> 0 | J31: =SUMIF($B$5:$B$24,A31,$K$5:$K$24) -> 0 | K31: =SUMIF($B$5:$B$24,A31,$M$5:$M$24) -> 805384 | L31: =SUMIF($B$5:$B$24,A31,$P$5:$P$24) -> 583524 | M31: =IFERROR(SUMIF($B$5:$B$24,A31,$O$5:$O$24)/SUMIF($B$5:$B$24,A31,$M$5:$M$24),0) -> 0.76298884 | N31: =IFERROR(SUMIF($B$5:$B$24,A31,$P$5:$P$24)/SUMIF($B$5:$B$24,A31,$O$5:$O$24),0) -> 0.94959308 | O31: =COUNTIFS($B$5:$B$24,A31,$Q$5:$Q$24,">="&0.7) -> 2 | P31: =COUNTIFS($B$5:$B$24,A31,$Q$5:$Q$24,"<0.3") -> 0 | Q31: =IF(M31>=0.7,"🟢 BAJO",IF(M31>=0.4,"🟡 MEDIO",IF(M31>0,"🟠 ALTO","🔴 CRÍTICO"))) -> 🟢 BAJO | R31: =COUNTIFS($B$5:$B$24,A31,$Q$5:$Q$24,">="&0.7)&"✅ / "&COUNTIFS($B$5:$B$24,A31,$Q$5:$Q$24,">="&0.3,$Q$5:$Q$24,"<0.7")&"️🟡 / "&COUNTIFS($B$5:$B$24,A31,$Q$5:$Q$24,"<0.3")&"🔴" -> 2✅ / 0️🟡 / 0🔴
A32: ECONÓMICO | B32: =COUNTIF($B$5:$B$24,A32) -> 1 | C32: =SUMIF($B$5:$B$24,A32,$L$5:$L$24) -> 0 | D32: =SUMIF($B$5:$B$24,A32,$M$5:$M$24) -> 0 | E32: =SUMIF($B$5:$B$24,A32,$O$5:$O$24) -> 0 | F32: =SUMIF($B$5:$B$24,A32,$G$5:$G$24) -> 0 | G32: =SUMIF($B$5:$B$24,A32,$H$5:$H$24) -> 0 | H32: =SUMIF($B$5:$B$24,A32,$I$5:$I$24) -> 0 | I32: =SUMIF($B$5:$B$24,A32,$J$5:$J$24) -> 0 | J32: =SUMIF($B$5:$B$24,A32,$K$5:$K$24) -> 0 | K32: =SUMIF($B$5:$B$24,A32,$M$5:$M$24) -> 0 | L32: =SUMIF($B$5:$B$24,A32,$P$5:$P$24) -> 0 | M32: =IFERROR(SUMIF($B$5:$B$24,A32,$O$5:$O$24)/SUMIF($B$5:$B$24,A32,$M$5:$M$24),0) -> 0 | N32: =IFERROR(SUMIF($B$5:$B$24,A32,$P$5:$P$24)/SUMIF($B$5:$B$24,A32,$O$5:$O$24),0) -> 0 | O32: =COUNTIFS($B$5:$B$24,A32,$Q$5:$Q$24,">="&0.7) -> 0 | P32: =COUNTIFS($B$5:$B$24,A32,$Q$5:$Q$24,"<0.3") -> 0 | Q32: =IF(M32>=0.7,"🟢 BAJO",IF(M32>=0.4,"🟡 MEDIO",IF(M32>0,"🟠 ALTO","🔴 CRÍTICO"))) -> 🔴 CRÍTICO | R32: =COUNTIFS($B$5:$B$24,A32,$Q$5:$Q$24,">="&0.7)&"✅ / "&COUNTIFS($B$5:$B$24,A32,$Q$5:$Q$24,">="&0.3,$Q$5:$Q$24,"<0.7")&"️🟡 / "&COUNTIFS($B$5:$B$24,A32,$Q$5:$Q$24,"<0.3")&"🔴" -> 0✅ / 0️🟡 / 0🔴

Sheet DATA-POA
A1: QUADRUM v1.0 · DATA-POA · Alineación POA-PAC 2023-2025 · Brechas de Activación por Meta | S1: =HYPERLINK("#'ICPI'!A1","ICPI ›") -> ICPI › | T1: =HYPERLINK("#'DASHBOARD'!A1","DASHBOARD ›") -> DASHBOARD › | Z1: ⌂ ÍNDICE
A2: =HYPERLINK("#'M-INDEX'!A1","⌂ INDICE") -> ⌂ INDICE | B2: =HYPERLINK("#'M1-ITME'!A1","M1") -> M1 | C2: =HYPERLINK("#'M2-PDOT'!A1","M2") -> M2 | D2: =HYPERLINK("#'M3-MAO'!A1","M3") -> M3 | E2: =HYPERLINK("#'M4-AUDIT'!A1","M4") -> M4 | F2: =HYPERLINK("#'M5-ICPI'!A1","M5") -> M5 | G2: =HYPERLINK("#'M6-FEDS'!A1","M6") -> M6 | H2: =HYPERLINK("#'M7-PROSP'!A1","M7") -> M7 | I2: ◉ DATA-POA | J2: =HYPERLINK("#'DATA-CNE'!A1","DATA-CNE") -> DATA-CNE | K2: =HYPERLINK("#'DATA-ORG'!A1","DATA-ORG") -> DATA-ORG | L2: =HYPERLINK("#'M-DASHBOARD'!A1","DASH") -> DASH
A3: #
A4: # | B4: CÓD. PDOT | C4: PROGRAMA / META POA | D4: EJE | E4: PRESUP. PDOT ($) | F4: EJECUTADO ($) | G4: BRECHA ($) | H4: ESTADO EJECUCIÓN | I4: ACCIÓN PRIORITARIA | J4: RESPONSABLE | K4: ACTIVIDADES POA | L4: TIPO GASTO | M4: ALERTA | N4: UNIDAD / DIRECCIÓN | O4: POA 2023 ($) | P4: POA 2024 ($) | Q4: POA 2025 ($) | R4: POA 2026 ($) | S4: POA 2027 ($) | T4: ACUM. ($)
A5: 1 | B5: PDOT.AS.OE1.M1.02 | C5: Alcantarillado Sanitario | D5: TERRITORIAL | E5: 4454844 | F5: 1269859 | G5: 3184985 | H5: ✅ Ejecutado → POA 2024 activo $337K | I5: Fase I Alcantarillado Eloy Alfaro — contratar BDE-PROGAPSA | J5: As. Humanos | K5: Alcantarillado Eloy Alfaro (BEI-PROGAPSA) | L5: Inversión de obra | M5: 🟠 ALTA · POA 2024: $337K · Brecha PDOT persiste | N5: Proyectos Estratégicos e Inversiones | O5: 4032693.9 | P5: 337000 | T5: =IFERROR(SUM(O5:S5),0) -> 4369693.9
A6: 2 | B6: PDOT.SC.OE2.M1.01 | C6: Centro de Salud Tipo C | D6: SOCIAL | E6: 20000 | F6: 1693800 | G6: -1673800 | H6: ❌ Sin asignación 2024 → Gestión interinstitucional MSP | I6: Convenio coordinación MSP — hoja de ruta formal | J6: As. Humanos | K6: Gestión Centro Salud Tipo C — convenio MSP | L6: Gestión interinstitucional | M6: 🔴 CRÍTICA · SIN ASIGNACIÓN 2024 · 2do año consecutivo | N6: Planificación / Proyectos Estratégicos | O6: 5000 | P6: 0 | T6: =IFERROR(SUM(O6:S6),0) -> 5000
A7: 3 | B7: PDOT.AS.OE1.M2.01 | C7: Nuevo Terminal Terrestre | D7: TERRITORIAL | E7: 0 | F7: 1693800 | G7: -1693800 | H7: ⚠️ Estudios previos → Consultoría $50K asignada 2024 | I7: Estudios factibilidad y diseño arquitectónico | J7: As. Humanos | K7: Terminal Terrestre Ciudad Bicentenario — estudios | L7: Estudios previos | M7: 🟠 ALTA · POA 2024: $50K · Solo consultoría · Sin obra | N7: Planificación / Proyectos Estratégicos | O7: 0 | P7: 50000 | T7: =IFERROR(SUM(O7:S7),0) -> 50000
A8: 4 | B8: PDOT.AS.OE1.M2.02 | C8: Nuevo Camal Municipal | D8: TERRITORIAL | E8: 0 | F8: 1693800 | G8: -1693800 | H8: ❌ Sin asignación 2024 → Abandono programático | I8: Estudio factibilidad técnica y ambiental Camal | J8: As. Humanos | K8: Equipamientos públicos (Terminal + Camal + Bomberil) | L8: Estudios previos | M8: 🔴 CRÍTICA · SIN ASIGNACIÓN 2024 · Abandono programático | N8: Planificación / Servicios Públicos | O8: 0 | P8: 0 | T8: =IFERROR(SUM(O8:S8),0) -> 0
A9: 5 | B9: PDOT.SC.OE2.M2.01 | C9: Equipamiento Geriátrico | D9: SOCIAL | E9: 0 | F9: 0 | G9: 0 | H9: ⚠️ Parcial → GAD+PMAS $90.7K · Solo operación social | I9: Partida operación recurrente Centro de Apoyo | J9: Soc. Cultural | K9: Centros de Apoyo grupos vulnerables | L9: Operación continua | M9: 🟡 MEDIA · POA 2024: $90.7K · Activo GAD+PMAS | N9: Acción Social y Desarrollo | O9: 1673.18 | P9: 90736.75 | T9: =IFERROR(SUM(O9:S9),0) -> 92409.93
A10: 6 | B10: PDOT.AS.VL.M1.01 | C10: Bacheo y Pavimentación | D10: TERRITORIAL | E10: 2629217 | F10: 10892761 | G10: -8263544 | H10: ⚠️ Sin bacheo explícito → Obras urbanas $285K asignadas | I10: Mantenimiento vías urbanas + pavimentación CUP | J10: As. Humanos | K10: Vialidad urbana — ejes estratégicos cantonales | L10: Inversión mantenimiento | M10: 🟠 ALTA · POA 2024: $285K · Sin bacheo explícito | N10: Planificación / Obras Públicas | O10: 1932237.3 | P10: 285000 | T10: =IFERROR(SUM(O10:S10),0) -> 2217237.3
A11: 7 | B11: PDOT.SC.OE2.M3.01 | C11: Unidad Médica Móvil | D11: SOCIAL | E11: 40000 | F11: 0 | G11: 40000 | H11: ✅ GAD+PMAS activos → $346.7K Unidades médicas | I11: Registro vehículo móvil SERCOP + contrato operación | J11: Soc. Cultural | K11: Unidad Médica Móvil + atención prioritaria | L11: Regularización documental | M11: 🟡 MEDIA · POA 2024: $346.7K · GAD+PMAS activos | N11: Acción Social / Salud | O11: 382489.32 | P11: 346673.39 | T11: =IFERROR(SUM(O11:S11),0) -> 729162.71
A12: 8 | B12: PDOT.AM.OE3.M1.01 | C12: Planta Oxidación / PTAR | D12: AMBIENTAL | E12: 370866 | F12: 0 | G12: 0 | H12: ⚠️ Solo gestión riesgos → Sin obra PTAR · $52K asignado | I12: Construcción Colector Principal + PTAR Montecristi | J12: As. Humanos | K12: Colector Principal + PTAR Montecristi / San Andrés | L12: Inversión de obra | M12: 🟠 ALTA · POA 2024: $52K · Sin obra PTAR · Solo riesgos | N12: Planificación / Dir. Alcantarillado | O12: 35920 | P12: 52000 | T12: =IFERROR(SUM(O12:S12),0) -> 87920
A13: 9 | B13: PDOT.AV.OE1.M1.01 | C13: Parques y Áreas Verdes | D13: TERRITORIAL | E13: 540243 | F13: 2588556 | G13: -2048313 | H13: ✅ En ejecución → Parque Las Pampas + EP $370.5K | I13: Parque Las Pampas — diseño y obra Fase I | J13: F. Ambiental | K13: Parque Las Pampas + Red Verde + canchas | L13: Inversión nueva obra | M13: 🟡 MEDIA · POA 2024: $370.5K · Parques en ejecución | N13: Planificación / Espacios Públicos | O13: 257765.76 | P13: 370460 | T13: =IFERROR(SUM(O13:S13),0) -> 628225.76
A14: 10 | B14: PDOT.SC.OE2.M4.01 | C14: Guarderías Nocturnas | D14: SOCIAL | E14: 0 | F14: 0 | G14: 0 | H14: ✅ GAD+PMAS activos → Talleres+CDI $394.5K | I14: Convenio MIES para CIBV nocturno / programa específico | J14: Soc. Cultural | K14: CIBV nocturno + Talleres CDI — convenio MIES | L14: Gestión interinstitucional | M14: 🟡 MEDIA · POA 2024: $394.5K · GAD+PMAS activos | N14: Acción Social / MIES | O14: 71074.68 | P14: 394472.52 | T14: =IFERROR(SUM(O14:S14),0) -> 465547.2
A15: 11 | B15: PDOT.AM.OE3.M2.01 | C15: Planta Tratamiento Desechos | D15: AMBIENTAL | E15: 125866 | F15: 748783 | G15: -622917 | H15: ❌ Sin asignación 2024 → Empresa Aseo sin partida | I15: Inicio proceso MAATE — regularización relleno sanitario | J15: F. Ambiental | K15: Relleno sanitario nuevo — EP Aseo | L15: Obra estratégica | M15: 🔴 CRÍTICA · SIN ASIGNACIÓN 2024 · Empresa Aseo sin partida | N15: Empresa de Aseo | O15: 0 | P15: 0 | T15: =IFERROR(SUM(O15:S15),0) -> 0
A16: 12 | B16: PDOT.AS.VL.M1.02 | C16: Equipo Caminero | D16: TERRITORIAL | E16: 600000 | F16: 10892761 | G16: -10292761 | H16: ⚠️ Solo mantenimiento → Maquinaria $307K · Sin adquisición | I16: Mantenimiento preventivo maquinaria + plan de vialidad | J16: As. Humanos | K16: Maquinaria pesada — mantenimiento vial | L16: Operación / mantenimiento | M16: 🟡 MEDIA · POA 2024: $307K · Mantenimiento maquinaria | N16: Planificación / Obras Públicas | O16: 250000 | P16: 307000 | T16: =IFERROR(SUM(O16:S16),0) -> 557000
... A24: 20 | B24: PDOT.AS.OE1.M1.03 | C24: Reservorios de Agua | D24: TERRITORIAL | E24: 22000 | F24: 45625014 | G24: -45603014 | H24: ⚠️ Deuda dominante → AP $752.4K · 87% es deuda BDE | I24: Diseño definitivo reservorios rurales + gestión BDE | J24: As. Humanos | K24: Reservorios agua rural — captación cantonal | L24: Estudios + inversión | M24: 🟠 ALTA · POA 2024: $752.4K · 87% deuda BDE · Sin obra nueva | N24: Planificación / Dir. Agua Potable | O24: 1843608.9 | P24: 752399.24 | T24: =IFERROR(SUM(O24:S24),0) -> 2596008.1
A25: Σ | B25: TOTALES · 21 METAS PDOT · 5 EJES ESTRATÉGICOS | S25: =SUM(S5:S24) -> 0 | T25: =SUM(T5:T24) -> 13435748
A26: 🟦 SECCIÓN A — ANÁLISIS POR EJE ESTRATÉGICO
A27: EJE
A28: TERRITORIAL | B28: 9 | C28: 12936982 | D28: 116024506 | E28: -103087524 | F28: 11,2% | G28: 3❌ / 3 / 2✅ / 1⚠️ — CRÍTICO
A29: SOCIAL | B29: 7 | C29: 153612 | D29: 1811700 | E29: -1658088 | F29: 8,5% | G29: 2❌ / 1 / 2✅ / 2⚠️ — ALERTA
A30: AMBIENTAL | B30: 2 | C30: 496732 | D30: 748783 | E30: -252051 | F30: 66,3% | G30: 0❌ / 2 / 0✅ / 0⚠️ — EN PROCESO
A31: INSTITUCIONAL | B31: 2 | C31: 805384 | D31: 0 | E31: 805384 | F31: 100%+ | G31: 0❌ / 1 / 1✅ / 0⚠️ — FAVORABLE
A32: ECONÓMICO | B32: 1 | C32: 35101 | D32: 0 | E32: 35101 | F32: — | G32: 0❌ / 0 / 0✅ / 1⚠️ — PARCIAL
A34: 🟥 SECCIÓN B — SEMAFORIZACIÓN PRESUPUESTARIA · ICPI · BRECHAS CRÍTICAS POA 2025 · §3.7 SIAP-ICPI
A35: 🔴 CRÍTICA Vi = 0 | B35: SIN RESPALDO DOCUMENTAL ICPI = 0 · Ruptura §1 CINI
A36: 🟠 ALTA Ti < 0.70 | B36: EJECUCIÓN INCOMPLETA Ti ∈ [0.30 — 0.69]
A37: 🟡 MEDIA Ti ≥ 0.70 | B37: EJECUCIÓN ACEPTABLE Ti ≥ 0.70 — en trayectoria
A38: ✅ CUMPLIDO Vi=Ei=Ti=1 | B38: INTEGRIDAD COMPLETA Vi=1 · Ei=1 · Ti=1 · §3.7 | D38: 25% del total | E38: Δ ICPI +2.5 pp por unidad | F38: Evidencia forense verificada CPCCS + SERCOP + SIGAD | G38: Metas cumplidas: | H38: TER-03 · TER-18 SOC-03 · TER-01 · INS-05 | I38: ✔ ACCIÓN CONTINUA: | J38: Mantener trayectoria + documentar §3.4.3 — modelo para replicar en metas s

Sheet DATA-PAC
A1: QUADRUM v1.0 · DATA-PAC · Plan Anual de Contratación · Fuente SERCOP · Por Meta PDOT | M1: =HYPERLINK("#'CEDULAS'!A1","CEDULAS ›") -> CEDULAS › | N1: =HYPERLINK("#'DASHBOARD'!A1","DASHBOARD ›") -> DASHBOARD › | Z1: ⌂ ÍNDICE
A2: =HYPERLINK("#'M-INDEX'!A1","⌂ INDICE") -> ⌂ INDICE | B2: =HYPERLINK("#'M1-ITME'!A1","M1") -> M1 | C2: =HYPERLINK("#'M2-PDOT'!A1","M2") -> M2 | D2: =HYPERLINK("#'M3-MAO'!A1","M3") -> M3 | E2: =HYPERLINK("#'M4-AUDIT'!A1","M4") -> M4 | F2: =HYPERLINK("#'M5-ICPI'!A1","M5") -> M5 | G2: =HYPERLINK("#'M6-FEDS'!A1","M6") -> M6 | H2: =HYPERLINK("#'M7-PROSP'!A1","M7") -> M7 | I2: =HYPERLINK("#'DATA-POA'!A1","DATA-POA") -> DATA-POA | J2: =HYPERLINK("#'DATA-CNE'!A1","DATA-CNE") -> DATA-CNE | K2: =HYPERLINK("#'DATA-ORG'!A1","DATA-ORG") -> DATA-ORG | L2: =HYPERLINK("#'M-DASHBOARD'!A1","DASH") -> DASH
A3: Capa: Base/Plan > Plan Anual de Contratación · Base: LOSNCP · SIAP-ICPI §2.4
A4: AÑO PAC | B4: # ÍTEM | C4: PARTIDA PRES. | D4: CPC | E4: TIPO | F4: DESCRIPCIÓN DEL ÍTEM PAC | G4: CANT. | H4: U. MED. | I4: COSTO UNIT. ($) | J4: VALOR TOTAL ($) | K4: PERÍODO | L4: CÓD. PDOT VINCULADO | M4: META PDOT (DESCRIPCIÓN) | N4: ESTADO VINCUL.
A5: 2023 | B5: 1 | C5: 84.01.09.000 | D5: 322300013 | E5: Bien | F5: Libros y colecciones | G5: 1 | H5: Unidad | I5: 1000 | J5: 1000 | K5: C1 C2 C3 | L5: — | M5: Gasto operativo / administrativo | N5: ⬜ Adm/Op
A6: 2023 | B6: 7 | C6: 84.01.03.000 | D6: 625830011 | E6: Bien | F6: Mobiliarios | G6: 1 | H6: Unidad | I6: 15000 | J6: 15000 | K6: C1 C2 C3 | L6: — | M6: Gasto operativo / administrativo | N6: ⬜ Adm/Op
A7: 2023 | B7: 8 | C7: 77.02.01.000 | D7: 713340112 | E7: Servicio | F7: Seguros GAD Municipal | G7: 1 | H7: Unidad | I7: 120000 | J7: 120000 | K7: C1 C2 C3 | L7: — | M7: Gasto operativo / administrativo | N7: ⬜ Adm/Op
A8: 2023 | B8: 11 | C8: 75.05.01.005 | D8: 532900011 | E8: Obra | F8: Mantenimiento Repotenciacion Planta Agua Potable Los Mangos | G8: 1 | H8: Unidad | I8: 213000 | J8: 213000 | K8: C1 C2 C3 | L8: PDOT.AS.OE1.M1.01 | M8: Cobertura Agua Potable | N8: ✅ Vinculado
A9: 2023 | B9: 12 | C9: 75.05.01.004 | D9: 532510012 | E9: Bien | F9: Suministros tuberia redes agua potable Canton | G9: 1 | H9: Unidad | I9: 220000 | J9: 220000 | K9: C1 C2 C3 | L9: PDOT.AS.OE1.M1.01 | M9: Cobertura Agua Potable | N9: ✅ Vinculado
A10: 2023 | B10: 13 | C10: 75.05.01.003 | D10: 881600011 | E10: Bien | F10: Operacion Mantenimiento Potabilizacion Aguas Canton | G10: 1 | H10: Unidad | I10: 40000 | J10: 40000 | K10: C1 C2 C3 | L10: PDOT.AS.OE1.M1.01 | M10: Cobertura Agua Potable | N10: ✅ Vinculado
A11: 2023 | B11: 14 | C11: 75.05.01.001 | D11: 932900011 | E11: Obra | F11: Sistema agua potable parroquias rurales Canton | G11: 1 | H11: Unidad | I11: 389657.49 | J11: 389657.49 | K11: C1 C2 C3 | L11: PDOT.AS.OE1.M1.01 | M11: Cobertura Agua Potable | N11: ✅ Vinculado
A12: 2023 | B12: 21 | C12: 750105.02 | D12: 120100013 | E12: Obra | F12: REHABILITACION BITUMINOSO VIAS CDLAS SANTA ISABEL TIERRA SANTA | G12: 1 | H12: Unidad | I12: 127060 | J12: 127060 | K12: C1 C2 C3 | L12: PDOT.AS.VL.M1.01 | M12: Bacheo y Pavimentacion | N12: ✅ Vinculado
A13: 2023 | B13: 22 | C13: 75.01.05.017 | D13: 532900011 | E13: Obra | F13: Reconstruccion Anillo Vial Tierra Santa y Santa Isabel | G13: 1 | H13: Unidad | I13: 242500 | J13: 242500 | K13: C1 C2 C3 | L13: PDOT.AS.VL.M1.01 | M13: Bacheo y Pavimentacion | N13: ✅ Vinculado
A14: 2023 | B14: 23 | C14: 75.01.05.016 | D14: 532900011 | E14: Obra | F14: PAVIMENTACION REPAVIMENTACION MEJORAMIENTO CARPETA ASFALTICA | G14: 1 | H14: Unidad | I14: 800000 | J14: 800000 | K14: C1 C2 C3 | L14: PDOT.AS.VL.M1.01 | M14: Bacheo y Pavimentacion | N14: ✅ Vinculado
A15: 2023 | B15: 24 | C15: 750105.02 | D15: 532510011 | E15: Bien | F15: REHABILITACION VIAS BUEN VIVIR EL PRADO ETAPA 1 | G15: 1 | H15: Unidad | I15: 150000 | J15: 150000 | K15: C1 C2 C3 | L15: PDOT.AS.VL.M1.01 | M15: Bacheo y Pavimentacion | N15: ✅ Vinculado
A16: 2023 | B16: 25 | C16: 75.01.05.016 | D16: 532900011 | E16: Obra | F16: MEJORAMIENTO VIAS URBANAS RURALES SECTORES VARIOS | G16: 1 | H16: Unidad | I16: 604996.01 | J16: 604996.01 | K16: C1 C2 C3 | L16: PDOT.AS.VL.M1.01 | M16: Bacheo y Pavimentacion | N16: ✅ Vinculado
A17: 2023 | B17: 27 | C17: 750504 | D17: 871520211 | E17: Obra | F17: MANTENIMIENTO ELECTRICO TERRAZAS PASEO LUDICO Y ESCALINATA | G17: 1 | H17: Unidad | I17: 108741.21 | J17: 108741.21 | K17: C1 C2 C3 | L17: PDOT.AS.VL.M2.01 | M17: Embellecimiento y Señaletica | N17: ✅ Vinculado
A18: 2023 | B18: 28 | C18: 75.05.04.001 | D18: 546190012 | E18: Servicio | F18: Mantenimiento Iluminacion Redes Electricas Alumbrado | G18: 1 | H18: Unidad | I18: 378584.89 | J18: 378584.89 | K18: C1 C2 C3 | L18: PDOT.AS.VL.M1.01 | M18: Bacheo y Pavimentacion | N18: ✅ Vinculado
A19: 2023 | B19: 32 | C19: 750101 | D19: 532510014 | E19: Obra | F19: CONSTRUCCION ALCANTARILLADO SANITARIO CUIDADELA PAOLA 1 Y PAOLA 2 | G19: 1 | H19: Unidad | I19: 249859.46 | J19: 249859.46 | K19: C1 C2 C3 | L19: PDOT.AS.OE1.M1.02 | M19: Alcantarillado Sanitario | N19: ✅ Vinculado
A20: 2023 | B20: 33 | C20: 73.15.15.000 | D20: 881600011 | E20: Servicio | F20: Plantas — Albergue Fauna Silvestre Canton | G20: 1 | H20: Unidad | I20: 2000 | J20: 2000 | K20: C1 C2 C3 | L20: PDOT.AM.SC.M3.01 | M20: Albergue Fauna Urbana | N20: ✅ Vinculado
A21: 2023 | B21: 34 | C21: 73.14.07.002 | D21: 512900011 | E21: Bien | F21: Sistema ERP gestion servicios plataforma digital | G21: 1 | H21: Unidad | I21: 150000 | J21: 150000 | K21: C1 C2 C3 | L21: PDOT.PI.OE4.M1.01 | M21: Digitalizacion de Tramites | N21: ✅ Vinculado
A22: 2023 | B22: 35 | C22: 73.14.07.001 | D22: 873400034 | E22: Servicio | F22: Equipos Sistemas Paquetes Informaticos | G22: 1 | H22: Unidad | I22: 12000 | J22: 12000 | K22: C1 C2 C3 | L22: PDOT.PI.OE4.M1.01 | M22: Digitalizacion de Tramites | N22: ✅ Vinculado
A23: 2023 | B23: 36 | C23: 75.01.04.010 | D23: 532900011 | E23: Obra | F23: ESTUDIO DEFINITIVO TERMINAL TERRESTRE CIUDAD BICENTENARIO | G23: 1 | H23: Unidad | I23: 41255.8 | J23: 41255.8 | K23: C1 C2 C3 | L23: PDOT.AS.OE1.M2.01 | M23: Nuevo Terminal Terrestre | N23: ✅ Vinculado
A24: 2023 | B24: 37 | C24: 73.06.13.005 | D24: 912200211 | E24: Servicio | F24: Capacitaciones Cursos Artesanales Emprendedores Canton | G24: 1 | H24: Unidad | I24: 12000 | J24: 12000 | K24: C1 C2 C3 | L24: PDOT.SC.OE2.M4.01 | M24: Guarderias / Desarrollo Social | N24: ✅ Vinculado
A25: 2023 | B25: 38 | C25: 73.06.13.004 | D25: 912200211 | E25: Servicio | F25: Centro Capacitaciones Permanentes Fortalecimiento Emprendedores | G25: 1 | H25: Unidad | I25: 8000 | J25: 8000 | K25: C1 C2 C3 | L25: PDOT.SC.OE2.M4.01 | M25: Guarderias / Desarrollo Social | N25: ✅ Vinculado
A26: 2023 | B26: 39 | C26: 73.06.13.003 | D26: 912200211 | E26: Servicio | F26: Actividades didacticas Infocentros Capacitaciones usuarios | G26: 1 | H26: Unidad | I26: 5000 | J26: 5000 | K26: C1 C2 C3 | L26: PDOT.SC.OE2.M4.01 | M26: Guarderias / Desarrollo Social | N26: ✅ Vinculado
A27: 2023 | B27: 44 | C27: 84.01.07.000 | D27: 472110215 | E27: Bien | F27: Equipos sistemas y paquetes informaticos GAD | G27: 1 | H27: Unidad | I27: 5900 | J27: 5900 | K27: C1 C2 C3 | L27: PDOT.PI.OE4.M1.01 | M27: Digitalizacion de Tramites | N27: ✅ Vinculado
A28: 2023 | B28: 45 | C28: 8.40.10.4.002 | D28: 444400211 | E28: Bien | F28: EQUIPOS HERRAMIENTAS DIRECCION AGUA POTABLE ALCANTARILLADO | G28: 1 | H28: Unidad | I28: 14476.33 | J28: 14476.33 | K28: C1 C2 C3 | L28: PDOT.AS.OE1.M1.01 | M28: Cobertura Agua Potable | N28: ✅ Vinculado
A29: 2023 | B29: 46 | C29: 8.4.01.04.002 | D29: 482200014 | E29: Bien | F29: DRONE PROFESIONAL KIT GNSS CARTOGRAFIA CATASTRO GAD | G29: 1 | H29: Unidad | I29: 61900 | J29: 61900 | K29: C1 C2 C3 | L29: PDOT.PI.OE4.M2.01 | M29: Actualizacion Catastro | N29: ✅ Vinculado
A30: 2023 | B30: 47 | C30: 8.4.01.04.001 | D30: 483530011 | E30: Bien | F30: EQUIPOS COMUNICACIONALES GAD MUNICIPAL CANTON MONTECRISTI | G30: 1 | H30: Unidad | I30: 16989 | J30: 16989 | K30: C1 C2 C3 | L30: PDOT.PI.OE4.M1.01 | M30: Digitalizacion de Tramites | N30: ✅ Vinculado
A31: 2023 | B31: 48 | C31: 84.01.04.001 | D31: 473230011 | E31: Bien | F31: Maquinarias y Equipos — Dron catastro | G31: 1 | H31: Unidad | I31: 3500 | J31: 3500 | K31: C1 C2 C3 | L31: PDOT.PI.OE4.M2.01 | M31: Actualizacion Catastro | N31: ✅ Vinculado
... A56: 2024 | B56: 2 | C56: A100.110.73080 | D56: 293100021 | E56: Bien | F56: EQUIPOS PROTECCION PERSONAL REGIMEN CODIGO TRABAJO GAD | G56: 1 | H56: Unidad | I56: 6944.9 | J56: 6944.9 | K56: C1 C2 C3 | L56: — | M56: Gasto operativo / administrativo | N56: ⬜ Adm/Op
A57: 2024 | B57: 3 | C57: 840402 | D57: 512900025 | E57: Servicio | F57: LICENCIAMIENTO Y ADQUISICION LICENCIAS VEHICULOS SANITARIOS | G57: 1 | H57: Unidad | I57: 15000 | J57: 15000 | K57: C1 C2 C3 | L57: PDOT.SC.OE2.M3.01 | M57: Unidad Medica Movil | N57: ✅ Vinculado
A58: 2024 | B58: 4 | C58: 840109 | D58: 621510011 | E58: Bien | F58: DOCTRINAS ACTUALIZADAS REFERENTES EVOLUCION DEL DERECHO | G58: 1 | H58: Unidad | I58: 1409 | J58: 1409 | K58: C1 C2 C3 | L58: — | M58: Gasto operativo / administrativo | N58: ⬜ Adm/Op
A59: 2024 | B59: 5 | C59: 840107 | D59: 4522000116 | E59: Bien | F59: EQUIPOS INFORMATICOS DIRECCIONES Y JEFATURAS GAD MONTECRISTI | G59: 1 | H59: Unidad | I59: 19645.4 | J59: 19645.4 | K59: C1 C2 C3 | L59: PDOT.PI.OE4.M1.01 | M59: Digitalizacion de Tramites | N59: ✅ Vinculado
A60: 2024 | B60: 6 | C60: 840107 | D60: 432115011 | E60: Bien | F60: EQUIPOS TRANSMISION TRABAJOS TECNICOS GOBIERNO MUNICIPAL | G60: 1 | H60: Unidad | I60: 10000 | J60: 10000 | K60: C1 C2 C3 | L60: PDOT.PI.OE4.M1.01 | M60: Digitalizacion de Tramites | N60: ✅ Vinculado
A61: 2024 | B61: 7 | C61: 840107 | D61: 481490011 | E61: Bien | F61: REPUESTOS ACCESORIOS EQUIPOS INFORMATICOS GAD | G61: 1 | H61: Unidad | I61: 30345.6 | J61: 30345.6 | K61: C1 C2 C3 | L61: PDOT.PI.OE4.M1.01 | M61: Digitalizacion de Tramites | N61: ✅ Vinculado
A62: 2024 | B62: 8 | C62: 840106 | D62: 444610013 | E62: Bien | F62: HERRAMIENTAS NO DEPRECIABLE MANTENIMIENTO SEMAFORIZACION | G62: 1 | H62: Unidad | I62: 2000 | J62: 2000 | K62: C1 C2 C3 | L62: — | M62: Gasto operativo / administrativo | N62: ⬜ Adm/Op
A63: 2024 | B63: 9 | C63: 840105 | D63: 491130025 | E63: Bien | F63: ADQUISICION CAMIONETAS 4x4 PARA PROPIEDAD MUNICIPAL GAD | G63: 1 | H63: Unidad | I63: 138000 | J63: 138000 | K63: C1 C2 C3 | L63: PDOT.AS.VL.M1.02 | M63: Equipo Caminero | N63: ✅ Vinculado
A64: 2024 | B64: 10 | C64: 840104 | D64: 482650221 | E64: Bien | F64: EQUIPOS LABORATORIO QUIMICO CALIDAD AGUA POTABLE RESIDUALES | G64: 1 | H64: Unidad | I64: 25000 | J64: 25000 | K64: C1 C2 C3 | L64: PDOT.AS.OE1.M1.01 | M64: Cobertura Agua Potable | N64: ✅ Vinculado
A65: 2024 | B65: 11 | C65: 840104 | D65: 439130111 | E65: Bien | F65: EQUIPOS Y MOBILIARIOS EQUIPAMIENTO GAD MUNICIPAL | G65: 1 | H65: Unidad | I65: 8000 | J65: 8000 | K65: C1 C2 C3 | L65: — | M65: Gasto operativo / administrativo | N65: ⬜ Adm/Op
A66: 2024 | B66: 12 | C66: 840104 | D66: 381210017 | E66: Bien | F66: MOBILIARIOS PARA TALLERES DE MAQUILLAJE | G66: 1 | H66: Unidad | I66: 3500 | J66: 3500 | K66: C1 C2 C3 | L66: — | M66: Gasto operativo / administrativo | N66: ⬜ Adm/Op
A67: 2024 | B67: 13 | C67: 840104 | D67: 442310113 | E67: Bien | F67: MOTO GUADAÑAS MOTO CIERRA HERRAMIENTAS MANTENIMIENTO PARQUES | G67: 1 | H67: Unidad | I67: 14000 | J67: 14000 | K67: C1 C2 C3 | L67: PDOT.AV.OE1.M1.01 | M67: Parques y Areas Verdes | N67: ✅ Vinculado
A68: 2024 | B68: 14 | C68: 840104 | D68: 444210111 | E68: Bien | F68: MAQUINARIA PESADA EQUIPO CAMINERO GAD MONTECRISTI | G68: 1 | H68: Unidad | I68: 600000 | J68: 600000 | K68: C1 C2 C3 | L68: PDOT.AS.VL.M1.02 | M68: Equipo Caminero | N68: ✅ Vinculado
... A128: 2024 | B128: 76 | C128: 730604 | D128: 532900011 | E128: Servicio | F128: MANTENIMIENTO Y REPARACION EQUIPOS INFORMATICOS TIC | G128: 1 | H128: Unidad | I128: 15000 | J128: 15000 | K128: C1 C2 C3 | L128: PDOT.PI.OE4.M1.01 | M128: Digitalizacion de Tramites | N128: ✅ Vinculado
A129: 2024 | B129: 80 | C129: 01.01.01.A100 | D129: 622910013 | E129: Servicio | F129: Arrendamiento edificio GAD Municipal | G129: 1 | H129: Unidad | I129: 0 | J129: 0 | K129: C1 C2 C3 | L129: — | M129: Gasto operativo / administrativo | N129: ⬜ Adm/Op
A130: TOTALES | J130: =SUM(J5:J129) -> 13431862
A131: PAC 2023 — 57 ítems GAD + 71 ítems PMAS — Total oficial GAD: $12,652,519.69 | PMAS: $554,410.20 — Vinculados PDOT: $3,587,519.89 | J131: =SUMIF(A5:A129,"2023",J5:J129) -> 5141539.7
A132: PAC 2024 — 143 ítems GAD + 46 ítems PMAS — Total oficial GAD: $8,712,580.52 | PMAS: $1,104,580.85 — Vinculados PDOT: $3,575,295.71 | J132: =SUMIF(A5:A129,"2024",J5:J129) -> 8290322.6
A133: 🔷 RESUMEN PAC POR META PDOT · Confirma PAC ✓ = 1 en MAD col S · Vinculación oficial por partida presupuestaria
A134: CÓD. PDOT | B134: META ESTRATÉGICA | C134: ÍTEMS PAC 2023 | D134: VALOR PAC 2023 ($) | E134: ÍTEMS PAC 2024 | F134: VALOR PAC 2024 ($)
A135: PDOT.AS.OE1.M1.01 | B135: Cobertura Agua Potable | C135: =COUNTIFS($A$5:$A$129,"2023",$L$5:$L$129,"PDOT.AS.OE1.M1.01") -> 5 | D135: 839221.66 | E135: =COUNTIFS($A$5:$A$129,"2024",$L$5:$L$129,"PDOT.AS.OE1.M1.01") -> 10 | F135: 451855
A136: PDOT.AS.OE1.M1.02 | B136: Alcantarillado Sanitario | C136: =COUNTIFS($A$5:$A$129,"2023",$L$5:$L$129,"PDOT.AS.OE1.M1.02") -> 1 | D136: 4133103 | E136: =COUNTIFS($A$5:$A$129,"2024",$L$5:$L$129,"PDOT.AS.OE1.M1.02") -> 3 | F136: 529859.46
A137: PDOT.AS.OE1.M1.03 | B137: Reservorios de Agua | C137: =COUNTIFS($A$5:$A$129,"2023",$L$5:$L$129,"PDOT.AS.OE1.M1.03") -> 0 | D137: 62000 | E137: =COUNTIFS($A$5:$A$129,"2024",$L$5:$L$129,"PDOT.AS.OE1.M1.03") -> 1 | F137: 0
A138: PDOT.AS.OE1.M2.01 | B138: Nuevo Terminal Terrestre | C138: =COUNTIFS($A$5:$A$129,"2023",$L$5:$L$129,"PDOT.AS.OE1.M2.01") -> 1 | D138: 0 | E138: =COUNTIFS($A$5:$A$129,"2024",$L$5:$L$129,"PDOT.AS.OE1.M2.01") -> 0 | F138: 0
A139: PDOT.AS.OE1.M2.02 | B139: Nuevo Camal Municipal | C139: =COUNTIFS($A$5:$A$129,"2023",$L$5:$L$129,"PDOT.AS.OE1.M2.02") -> 0 | D139: 0 | E139: =COUNTIFS($A$5:$A$129,"2024",$L$5:$L$129,"PDOT.AS.OE1.M2.02") -> 0 | F139: 0
A140: PDOT.SC.OE2.M1.01 | B140: Centro de Salud Tipo C | C140: =COUNTIFS($A$5:$A$129,"2023",$L$5:$L$129,"PDOT.SC.OE2.M1.01") -> 0 | D140: 0 | E140: =COUNTIFS($A$5:$A$129,"2024",$L$5:$L$129,"PDOT.SC.OE2.M1.01") -> 0 | F140: 0
A141: PDOT.SC.OE2.M2.01 | B141: Equipamiento Geriatrico | C141: =COUNTIFS($A$5:$A$129,"2023",$L$5:$L$129,"PDOT.SC.OE2.M2.01") -> 0 | D141: 1673.18 | E141: =COUNTIFS($A$5:$A$129,"2024",$L$5:$L$129,"PDOT.SC.OE2.M2.01") -> 1 | F141: 24426.56
A142: PDOT.SC.OE2.M3.01 | B142: Unidad Medica Movil | C142: =COUNTIFS($A$5:$A$129,"2023",$L$5:$L$129,"PDOT.SC.OE2.M3.01") -> 0 | D142: 348541.36 | E142: =COUNTIFS($A$5:$A$129,"2024",$L$5:$L$129,"PDOT.SC.OE2.M3.01") -> 1 | F142: 401000
A143: PDOT.SC.OE2.M4.01 | B143: Guarderias / Desarrollo Social | C143: =COUNTIFS($A$5:$A$129,"2023",$L$5:$L$129,"PDOT.SC.OE2.M4.01") -> 3 | D143: 306795.66 | E143: =COUNTIFS($A$5:$A$129,"2024",$L$5:$L$129,"PDOT.SC.OE2.M4.01") -> 5 | F143: 768054.29
A144: PDOT.AM.OE3.M1.01 | B144: Planta Oxidacion / PTAR | C144: =COUNTIFS($A$5:$A$129,"2023",$L$5:$L$129,"PDOT.AM.OE3.M1.01") -> 1 | D144: 164866 | E144: =COUNTIFS($A$5:$A$129,"2024",$L$5:$L$129,"PDOT.AM.OE3.M1.01") -> 1 | F144: 125000
A145: PDOT.AM.OE3.M2.01 | B145: Planta Tratamiento Desechos | C145: =COUNTIFS($A$5:$A$129,"2023",$L$5:$L$129,"PDOT.AM.OE3.M2.01") -> 1 | D145: 0 | E145: =COUNTIFS($A$5:$A$129,"2024",$L$5:$L$129,"PDOT.AM.OE3.M2.01") -> 2 | F145: 31500
A146: PDOT.AM.SC.M3.01 | B146: Albergue Fauna Urbana | C146: =COUNTIFS($A$5:$A$129,"2023",$L$5:$L$129,"PDOT.AM.SC.M3.01") -> 1 | D146: 2000 | E146: =COUNTIFS($A$5:$A$129,"2024",$L$5:$L$129,"PDOT.AM.SC.M3.01") -> 0 | F146: 0
A147: PDOT.AS.VL.M1.01 | B147: Bacheo y Pavimentacion | C147: =COUNTIFS($A$5:$A$129,"2023",$L$5:$L$129,"PDOT.AS.VL.M1.01") -> 6 | D147: 2958076.5 | E147: =COUNTIFS($A$5:$A$129,"2024",$L$5:$L$129,"PDOT.AS.VL.M1.01") -> 10 | F147: 1807000
A148: PDOT.AS.VL.M1.02 | B148: Equipo Caminero | C148: =COUNTIFS($A$5:$A$129,"2023",$L$5:$L$129,"PDOT.AS.VL.M1.02") -> 2 | D148: 80000 | E148: =COUNTIFS($A$5:$A$129,"2024",$L$5:$L$129,"PDOT.AS.VL.M1.02") -> 2 | F148: 738000
A149: PDOT.AS.VL.M2.01 | B149: Embellecimiento y Señaletica | C149: =COUNTIFS($A$5:$A$129,"2023",$L$5:$L$129,"PDOT.AS.VL.M2.01") -> 1 | D149: 693326.1 | E149: =COUNTIFS($A$5:$A$129,"2024",$L$5:$L$129,"PDOT.AS.VL.M2.01") -> 1 | F149: 321741.21
A150: PDOT.AV.OE1.M1.01 | B150: Parques y Areas Verdes | C150: =COUNTIFS($A$5:$A$129,"2023",$L$5:$L$129,"PDOT.AV.OE1.M1.01") -> 2 | D150: 288243.69 | E150: =COUNTIFS($A$5:$A$129,"2024",$L$5:$L$129,"PDOT.AV.OE1.M1.01") -> 5 | F150: 442500
A151: PDOT.SC.PI.M5.01 | B151: Central Monitoreo / Camaras | C151: =COUNTIFS($A$5:$A$129,"2023",$L$5:$L$129,"PDOT.SC.PI.M5.01") -> 0 | D151: 6000 | E151: =COUNTIFS($A$5:$A$129,"2024",$L$5:$L$129,"PDOT.SC.PI.M5.01") -> 0 | F151: 47612.41
A152: PDOT.PI.OE4.M1.01 | B152: Digitalizacion de Tramites | C152: =COUNTIFS($A$5:$A$129,"2023",$L$5:$L$129,"PDOT.PI.OE4.M1.01") -> 5 | D152: 371300 | E152: =COUNTIFS($A$5:$A$129,"2024",$L$5:$L$129,"PDOT.PI.OE4.M1.01") -> 8 | F152: 390475
A153: PDOT.PI.OE4.M2.01 | B153: Actualizacion Catastro | C153: =COUNTIFS($A$5:$A$129,"2023",$L$5:$L$129,"PDOT.PI.OE4.M2.01") -> 2 | D153: 65400 | E153: =COUNTIFS($A$5:$A$129,"2024",$L$5:$L$129,"PDOT.PI.OE4.M2.01") -> 9 | F153: 107200
A154: PDOT.EP.OE5.M1.01 | B154: Proyecto Playa San Jose | C154: =COUNTIFS($A$5:$A$129,"2023",$L$5:$L$129,"PDOT.EP.OE5.M1.01") -> 0 | D154: 35101.31 | E154: =COUNTIFS($A$5:$A$129,"2024",$L$5:$L$129,"PDOT.EP.OE5.M1.01") -> 1 | F154: 0

Sheet M5-ICPI
A1: QUADRUM v1.0 · M5-ICPI · Motor Central · Índice de Cumplimiento Programático Institucional · Protocolo de Integridad Forense ALFARO VIRTUS · GAD Municipal Montecristi | Y1: =HYPERLINK("#'RESULTADOS'!A1","RESULTADOS ›") -> RESULTADOS › | Z1: ⌂ ÍNDICE
A2: =HYPERLINK("#'M-INDEX'!A1","⌂ INDICE") -> ⌂ INDICE | B2: =HYPERLINK("#'M1-ITME'!A1","M1") -> M1 | C2: =HYPERLINK("#'M2-PDOT'!A1","M2") -> M2 | D2: =HYPERLINK("#'M3-MAO'!A1","M3") -> M3 | E2: =HYPERLINK("#'M4-AUDIT'!A1","M4") -> M4 | F2: =HYPERLINK("#'M5-ICPI'!A1","◉ M5-ICPI") -> ◉ M5-ICPI | G2: =HYPERLINK("#'M6-FEDS'!A1","M6") -> M6 | H2: =HYPERLINK("#'M7-PROSP'!A1","M7") -> M7 | I2: =HYPERLINK("#'DATA-POA'!A1","DATA-POA") -> DATA-POA | J2: =HYPERLINK("#'DATA-CNE'!A1","DATA-CNE") -> DATA-CNE | K2: =HYPERLINK("#'DATA-ORG'!A1","DATA-ORG") -> DATA-ORG | L2: =HYPERLINK("#'M-DASHBOARD'!A1","DASH") -> DASH
A3: #
A4: CÓD. PDOT | B4: EJE ESTRATÉGICO | C4: Pi (Peso) | D4: Ri (Relevancia) | E4: Vi (Verificación) | F4: Ti (Temporalidad) | G4: Pi×Ri×Vi×Ti | H4: Pi×Ri (Denominador) | I4: Ci (Control) | J4: Semáforo | K4: ESTADO CININ | L4: OBS.
A5: ='M2-PDOT'!B4 -> PDOT.AS.VL.M1.01 | B5: ='M2-PDOT'!C4 -> Asentamientos Humanos | C5: ='M2-PLAN-Pi'!F14 -> 0.33155843 | D5: ='DATA-TFR'!F5 -> 1 | E5: =IFERROR(VLOOKUP(A5,'M4-AUDIT'!$A$5:$P$24,MATCH("Vi",'M4-AUDIT'!$A$4:$P$4,0),0),0) -> 1 | F5: =IFERROR(VLOOKUP(A5,'M4-AUDIT'!$A$5:$P$24,MATCH("Ti (H)",'M4-AUDIT'!$A$4:$P$4,0),0),0) -> 0.25 | G5: =C5*D5*E5*F5*I5 -> 0.082889607 | H5: =C5*D5 -> 0.33155843 | I5: =IFERROR(VLOOKUP(A5,'M4-AUDIT'!$A$5:$P$24,MATCH("Pi / Ci",'M4-AUDIT'!$A$4:$P$4,0),0),0.75) -> 1 | J5: =IF(E5=0,"⬛ Vi=0 SIN EVIDENCIA",IF(F5>=0.85,"🔵",IF(F5>=0.7,"🟢",IF(F5>=0.4,"🟠",IF(F5>=0.2,"🔴","⬛"))))) -> 🔴
A6: ='M2-PDOT'!B5 -> PDOT.SC.OE2.M1.01 | B6: ='M2-PDOT'!C5 -> Socio Cultural | C6: ='M2-PLAN-Pi'!F15 -> 0.17737919 | D6: ='DATA-TFR'!F6 -> 1.5 | E6: =IFERROR(VLOOKUP(A6,'M4-AUDIT'!$A$5:$P$24,MATCH("Vi",'M4-AUDIT'!$A$4:$P$4,0),0),0) -> 1 | F6: =IFERROR(VLOOKUP(A6,'M4-AUDIT'!$A$5:$P$24,MATCH("Ti (H)",'M4-AUDIT'!$A$4:$P$4,0),0),0) -> 0.65 | G6: =C6*D6*E6*F6*I6 -> 0.15565024 | H6: =C6*D6 -> 0.26606879 | I6: =IFERROR(VLOOKUP(A6,'M4-AUDIT'!$A$5:$P$24,MATCH("Pi / Ci",'M4-AUDIT'!$A$4:$P$4,0),0),0.75) -> 0.9 | J6: =IF(E6=0,"⬛ Vi=0 SIN EVIDENCIA",IF(F6>=0.85,"🔵",IF(F6>=0.7,"🟢",IF(F6>=0.4,"🟠",IF(F6>=0.2,"🔴","⬛"))))) -> 🟠
A7: ='M2-PDOT'!B6 -> PDOT.AM.OE3.M2.01 | B7: ='M2-PDOT'!C6 -> Ambiental | C7: ='M2-PLAN-Pi'!F16 -> 0.15225184 | D7: ='DATA-TFR'!F7 -> 1 | E7: =IFERROR(VLOOKUP(A7,'M4-AUDIT'!$A$5:$P$24,MATCH("Vi",'M4-AUDIT'!$A$4:$P$4,0),0),0) -> 1 | F7: =IFERROR(VLOOKUP(A7,'M4-AUDIT'!$A$5:$P$24,MATCH("Ti (H)",'M4-AUDIT'!$A$4:$P$4,0),0),0) -> 0.75 | G7: =C7*D7*E7*F7*I7 -> 0.085641662 | H7: =C7*D7 -> 0.15225184 | I7: =IFERROR(VLOOKUP(A7,'M4-AUDIT'!$A$5:$P$24,MATCH("Pi / Ci",'M4-AUDIT'!$A$4:$P$4,0),0),0.75) -> 0.75 | J7: =IF(E7=0,"⬛ Vi=0 SIN EVIDENCIA",IF(F7>=0.85,"🔵",IF(F7>=0.7,"🟢",IF(F7>=0.4,"🟠",IF(F7>=0.2,"🔴","⬛"))))) -> 🟢
A8: ='M2-PDOT'!B7 -> PDOT.AS.OE1.M2.01 | B8: ='M2-PDOT'!C7 -> Asentamientos Humanos | C8: ='M2-PLAN-Pi'!F17 -> 0.051556596 | D8: ='DATA-TFR'!F8 -> 1 | E8: =IFERROR(VLOOKUP(A8,'M4-AUDIT'!$A$5:$P$24,MATCH("Vi",'M4-AUDIT'!$A$4:$P$4,0),0),0) -> 0 | F8: =IFERROR(VLOOKUP(A8,'M4-AUDIT'!$A$5:$P$24,MATCH("Ti (H)",'M4-AUDIT'!$A$4:$P$4,0),0),0) -> 0.1 | G8: =C8*D8*E8*F8*I8 -> 0 | H8: =C8*D8 -> 0.051556596 | I8: =IFERROR(VLOOKUP(A8,'M4-AUDIT'!$A$5:$P$24,MATCH("Pi / Ci",'M4-AUDIT'!$A$4:$P$4,0),0),0.75) -> 1 | J8: =IF(E8=0,"⬛ Vi=0 SIN EVIDENCIA",IF(F8>=0.85,"🔵",IF(F8>=0.7,"🟢",IF(F8>=0.4,"🟠",IF(F8>=0.2,"🔴","⬛"))))) -> ⬛ Vi=0 SIN EVIDENCIA
A9: ='M2-PDOT'!B8 -> PDOT.SC.OE2.M4.01 | B9: ='M2-PDOT'!C8 -> Socio Cultural | C9: ='M2-PLAN-Pi'!F18 -> 0.049038304 | D9: ='DATA-TFR'!F9 -> 1 | E9: =IFERROR(VLOOKUP(A9,'M4-AUDIT'!$A$5:$P$24,MATCH("Vi",'M4-AUDIT'!$A$4:$P$4,0),0),0) -> 1 | F9: =IFERROR(VLOOKUP(A9,'M4-AUDIT'!$A$5:$P$24,MATCH("Ti (H)",'M4-AUDIT'!$A$4:$P$4,0),0),0) -> 0.2 | G9: =C9*D9*E9*F9*I9 -> 0.0088268947 | H9: =C9*D9 -> 0.049038304 | I9: =IFERROR(VLOOKUP(A9,'M4-AUDIT'!$A$5:$P$24,MATCH("Pi / Ci",'M4-AUDIT'!$A$4:$P$4,0),0),0.75) -> 0.9 | J9: =IF(E9=0,"⬛ Vi=0 SIN EVIDENCIA",IF(F9>=0.85,"🔵",IF(F9>=0.7,"🟢",IF(F9>=0.4,"🟠",IF(F9>=0.2,"🔴","⬛"))))) -> 🔴
A10: ='M2-PDOT'!B9 -> PDOT.AS.OE1.M1.02 | B10: ='M2-PDOT'!C9 -> Asentamientos Humanos | C10: ='M2-PLAN-Pi'!F19 -> 0.038652516 | D10: ='DATA-TFR'!F10 -> 1.5 | E10: =IFERROR(VLOOKUP(A10,'M4-AUDIT'!$A$5:$P$24,MATCH("Vi",'M4-AUDIT'!$A$4:$P$4,0),0),0) -> 0 | F10: =IFERROR(VLOOKUP(A10,'M4-AUDIT'!$A$5:$P$24,MATCH("Ti (H)",'M4-AUDIT'!$A$4:$P$4,0),0),0) -> 0 | G10: =C10*D10*E10*F10*I10 -> 0 | H10: =C10*D10 -> 0.057978773 | I10: =IFERROR(VLOOKUP(A10,'M4-AUDIT'!$A$5:$P$24,MATCH("Pi / Ci",'M4-AUDIT'!$A$4:$P$4,0),0),0.75) -> 1 | J10: =IF(E10=0,"⬛ Vi=0 SIN EVIDENCIA",IF(F10>=0.85,"🔵",IF(F10>=0.7,"🟢",IF(F10>=0.4,"🟠",IF(F10>=0.2,"🔴","⬛"))))) -> ⬛ Vi=0 SIN EVIDENCIA
A11: ='M2-PDOT'!B10 -> PDOT.PI.OE4.M1.01 | B11: ='M2-PDOT'!C10 -> Político Institucional | C11: ='M2-PLAN-Pi'!F20 -> 0.037123042 | D11: ='DATA-TFR'!F11 -> 0.5 | E11: =IFERROR(VLOOKUP(A11,'M4-AUDIT'!$A$5:$P$24,MATCH("Vi",'M4-AUDIT'!$A$4:$P$4,0),0),0) -> 1 | F11: =IFERROR(VLOOKUP(A11,'M4-AUDIT'!$A$5:$P$24,MATCH("Ti (H)",'M4-AUDIT'!$A$4:$P$4,0),0),0) -> 1 | G11: =C11*D11*E11*F11*I11 -> 0.018561521 | H11: =C11*D11 -> 0.018561521 | I11: =IFERROR(VLOOKUP(A11,'M4-AUDIT'!$A$5:$P$24,MATCH("Pi / Ci",'M4-AUDIT'!$A$4:$P$4,0),0),0.75) -> 1 | J11: =IF(E11=0,"⬛ Vi=0 SIN EVIDENCIA",IF(F11>=0.85,"🔵",IF(F11>=0.7,"🟢",IF(F11>=0.4,"🟠",IF(F11>=0.2,"🔴","⬛"))))) -> 🔵
A12: ='M2-PDOT'!B11 -> PDOT.AV.OE1.M1.01 | B12: ='M2-PDOT'!C11 -> Asentamientos Humanos | C12: ='M2-PLAN-Pi'!F21 -> 0.027234953 | D12: ='DATA-TFR'!F12 -> 1 | E12: =IFERROR(VLOOKUP(A12,'M4-AUDIT'!$A$5:$P$24,MATCH("Vi",'M4-AUDIT'!$A$4:$P$4,0),0),0) -> 1 | F12: =IFERROR(VLOOKUP(A12,'M4-AUDIT'!$A$5:$P$24,MATCH("Ti (H)",'M4-AUDIT'!$A$4:$P$4,0),0),0) -> 0.9 | G12: =C12*D12*E12*F12*I12 -> 0.024511458 | H12: =C12*D12 -> 0.027234953 | I12: =IFERROR(VLOOKUP(A12,'M4-AUDIT'!$A$5:$P$24,MATCH("Pi / Ci",'M4-AUDIT'!$A$4:$P$4,0),0),0.75) -> 1 | J12: =IF(E12=0,"⬛ Vi=0 SIN EVIDENCIA",IF(F12>=0.85,"🔵",IF(F12>=0.7,"🟢",IF(F12>=0.4,"🟠",IF(F12>=0.2,"🔴","⬛"))))) -> 🔵
A13: ='M2-PDOT'!B12 -> PDOT.AM.OE3.M1.01 | B13: ='M2-PDOT'!C12 -> Ambiental | C13: ='M2-PLAN-Pi'!F22 -> 0.025568273 | D13: ='DATA-TFR'!F13 -> 1.5 | E13: =IFERROR(VLOOKUP(A13,'M4-AUDIT'!$A$5:$P$24,MATCH("Vi",'M4-AUDIT'!$A$4:$P$4,0),0),0) -> 0 | F13: =IFERROR(VLOOKUP(A13,'M4-AUDIT'!$A$5:$P$24,MATCH("Ti (H)",'M4-AUDIT'!$A$4:$P$4,0),0),0) -> 0.3 | G13: =C13*D13*E13*F13*I13 -> 0 | H13: =C13*D13 -> 0.038352409 | I13: =IFERROR(VLOOKUP(A13,'M4-AUDIT'!$A$5:$P$24,MATCH("Pi / Ci",'M4-AUDIT'!$A$4:$P$4,0),0),0.75) -> 1 | J13: =IF(E13=0,"⬛ Vi=0 SIN EVIDENCIA",IF(F13>=0.85,"🔵",IF(F13>=0.7,"🟢",IF(F13>=0.4,"🟠",IF(F13>=0.2,"🔴","⬛"))))) -> ⬛ Vi=0 SIN EVIDENCIA
A14: ='M2-PDOT'!B13 -> PDOT.FA.OE4.AH.02 | B14: ='M2-PDOT'!C13 -> Físico Ambiental | C14: ='M2-PLAN-Pi'!F23 -> 0.022791758 | D14: ='DATA-TFR'!F14 -> 1 | E14: =IFERROR(VLOOKUP(A14,'M4-AUDIT'!$A$5:$P$24,MATCH("Vi",'M4-AUDIT'!$A$4:$P$4,0),0),0) -> 1 | F14: =IFERROR(VLOOKUP(A14,'M4-AUDIT'!$A$5:$P$24,MATCH("Ti (H)",'M4-AUDIT'!$A$4:$P$4,0),0),0) -> 0.4 | G14: =C14*D14*E14*F14*I14 -> 0.0091167034 | H14: =C14*D14 -> 0.022791758 | I14: =IFERROR(VLOOKUP(A14,'M4-AUDIT'!$A$5:$P$24,MATCH("Pi / Ci",'M4-AUDIT'!$A$4:$P$4,0),0),0.75) -> 1 | J14: =IF(E14=0,"⬛ Vi=0 SIN EVIDENCIA",IF(F14>=0.85,"🔵",IF(F14>=0.7,"🟢",IF(F14>=0.4,"🟠",IF(F14>=0.2,"🔴","⬛"))))) -> 🟠
A15: ='M2-PDOT'!B14 -> PDOT.FA.OE1.PV.01 | B15: ='M2-PDOT'!C14 -> Físico Ambiental | C15: ='M2-PLAN-Pi'!F24 -> 0.018567422 | D15: ='DATA-TFR'!F15 -> 0.5 | E15: =IFERROR(VLOOKUP(A15,'M4-AUDIT'!$A$5:$P$24,MATCH("Vi",'M4-AUDIT'!$A$4:$P$4,0),0),0) -> 1 | F15: =IFERROR(VLOOKUP(A15,'M4-AUDIT'!$A$5:$P$24,MATCH("Ti (H)",'M4-AUDIT'!$A$4:$P$4,0),0),0) -> 0.5 | G15: =C15*D15*E15*F15*I15 -> 0.0046418556 | H15: =C15*D15 -> 0.0092837111 | I15: =IFERROR(VLOOKUP(A15,'M4-AUDIT'!$A$5:$P$24,MATCH("Pi / Ci",'M4-AUDIT'!$A$4:$P$4,0),0),0.75) -> 1 | J15: =IF(E15=0,"⬛ Vi=0 SIN EVIDENCIA",IF(F15>=0.85,"🔵",IF(F15>=0.7,"🟢",IF(F15>=0.4,"🟠",IF(F15>=0.2,"🔴","⬛"))))) -> 🟠
A16: ='M2-PDOT'!B15 -> PDOT.PI.OE4.M2.01 | B16: ='M2-PDOT'!C15 -> Político Institucional | C16: ='M2-PLAN-Pi'!F25 -> 0.018292146 | D16: ='DATA-TFR'!F16 -> 0.5 | E16: =IFERROR(VLOOKUP(A16,'M4-AUDIT'!$A$5:$P$24,MATCH("Vi",'M4-AUDIT'!$A$4:$P$4,0),0),0) -> 0 | F16: =IFERROR(VLOOKUP(A16,'M4-AUDIT'!$A$5:$P$24,MATCH("Ti (H)",'M4-AUDIT'!$A$4:$P$4,0),0),0) -> 0 | G16: =C16*D16*E16*F16*I16 -> 0 | H16: =C16*D16 -> 0.009146073 | I16: =IFERROR(VLOOKUP(A16,'M4-AUDIT'!$A$5:$P$24,MATCH("Pi / Ci",'M4-AUDIT'!$A$4:$P$4,0),0),0.75) -> 1 | J16: =IF(E16=0,"⬛ Vi=0 SIN EVIDENCIA",IF(F16>=0.85,"🔵",IF(F16>=0.7,"🟢",IF(F16>=0.4,"🟠",IF(F16>=0.2,"🔴","⬛"))))) -> ⬛ Vi=0 SIN EVIDENCIA
... A24: ='M2-PDOT'!B23 -> PDOT.FA.OE2.MA.01 | B24: ='M2-PDOT'!C23 -> 0 | C24: ='M2-PLAN-Pi'!F33 -> 0 | D24: ='DATA-TFR'!F24 -> 0.5 | E24: =IFERROR(VLOOKUP(A24,'M4-AUDIT'!$A$5:$P$24,MATCH("Vi",'M4-AUDIT'!$A$4:$P$4,0),0),0) -> 1 | F24: =IFERROR(VLOOKUP(A24,'M4-AUDIT'!$A$5:$P$24,MATCH("Ti (H)",'M4-AUDIT'!$A$4:$P$4,0),0),0) -> 1 | G24: =C24*D24*E24*F24*I24 -> 0 | H24: =C24*D24 -> 0 | I24: =IFERROR(VLOOKUP(A24,'M4-AUDIT'!$A$5:$P$24,MATCH("Pi / Ci",'M4-AUDIT'!$A$4:$P$4,0),0),0.75) -> 1 | J24: =IF(E24=0,"⬛ Vi=0 SIN EVIDENCIA",IF(F24>=0.85,"🔵",IF(F24>=0.7,"🟢",IF(F24>=0.4,"🟠",IF(F24>=0.2,"🔴","⬛"))))) -> 🔵
A25: Σ TOTAL | B25: - | G25: =IFERROR(SUM(G5:G24),0) -> 0.40896482 | H25: =IFERROR(SUM(H5:H24),0) -> 1.0682671
A26: ⬡ SECCIÓN MELÓGICA
A27: 🎯 ICPI FINAL (G29)
A28: 📋 MARCO LEGAL — SIAP-ICPI §3.7 (algoritmo ICPI) · §3.4 (Vi) · §3.5 (Ti) · §3.6 (Ci) · COOTAD Art.295 · SNPD-2023 (evaluación PDOT) · Plan Bicentenario Ecuador 2023–2027
A29: ICPI TOTAL | G29: =IFERROR(G25/H25*100,0) -> 38.283014
B30: ="◈ ICPI = Σ(Pi × Ri × Vi × Ti × Ci) ÷ Σ(Pi × Ri) = "&ROUND(G25,4)&" ÷ "&ROUND(H25,4)&" = "&TEXT(G29,"0,00")&" % — n=20 metas §3.7" -> ◈ ICPI = Σ(Pi × Ri × Vi × Ti × Ci) ÷ Σ(Pi × Ri) = 0,409 ÷ 1,0683 = 38,28 % — n=20 metas §3.7 | Z30: SIAP-ICPI ©

Sheet SUPPORT-INTERP
A1: QUADRUM v1.0 · SUPPORT-INTERP · Interpretación Cualitativa · Escala AVEP 5 Niveles
A2: =HYPERLINK("#'M-INDEX'!A1","⌂ INDICE") -> ⌂ INDICE | B2: =HYPERLINK("#'M1-ITME'!A1","M1") -> M1 | C2: =HYPERLINK("#'M2-PDOT'!A1","M2") -> M2 | D2: =HYPERLINK("#'M3-MAO'!A1","M3") -> M3 | E2: =HYPERLINK("#'M4-AUDIT'!A1","M4") -> M4 | F2: =HYPERLINK("#'M5-ICPI'!A1","M5") -> M5 | G2: =HYPERLINK("#'M6-FEDS'!A1","M6") -> M6 | H2: =HYPERLINK("#'M7-PROSP'!A1","M7") -> M7 | I2: =HYPERLINK("#'DATA-POA'!A1","DATA-POA") -> DATA-POA | J2: =HYPERLINK("#'DATA-CNE'!A1","DATA-CNE") -> DATA-CNE | K2: =HYPERLINK("#'DATA-ORG'!A1","DATA-ORG") -> DATA-ORG | L2: =HYPERLINK("#'M-DASHBOARD'!A1","DASH") -> DASH
A3: Capa: Motor ICPI > Interpretación de Rangos AVEP · Escala de Integridad Institucional
A4: 🔷 INTERPRETACIÓN ICPI · Categoría: Transición Crítica (40-55%) · Análisis por eje · Recomendaciones
A5: 1 | B5: 85 – 100% | C5: 🔵 ████ | D5: EXCELENCIA | E5: Cumplimiento total de las metas PDOT. Plena fidelidad al Plan Bicentenario 2023-2027. Todas las metas ejecutadas con verificación documental completa. Modelo de gestión pública ejemplar.
A6: 2 | B6: 70 – 84,99% | C6: 🟢 ████ | D6: GESTIÓN POR MANDATO | E6: Alta fidelidad programática y congruencia técnica. Las metas del PDOT se materializan en contratación y ejecución verificada. Ti≥70% · Trazabilidad documental sólida.
A7: 3 | B7: 40 – 69,99% | C7: 🟠 ████ | D7: ="TRANSICIÓN CRÍTICA ◄ GAD MONTECRISTI "&TEXT('E1-ICPI'!G28,"0,00%") | E7: ="Cumplimiento parcial · Mezcla de mandato y ocurrencia · Trazabilidad documental insuficiente · RESULTADO GAD MONTECRISTI: "&TEXT('E1-ICPI'!G28,"0,00%")&" — §3.4 Regularización urgente"
A8: 4 | B8: 20 – 39,99% | C8: 🔴 ████ | D8: GESTIÓN POR OCURRENCIA | E8: Desconexión programática severa. Gestión reactiva al contexto diario. Metas sin seguimiento sistemático. Riesgo de impugnación ciudadana y observación de organismos de control.
A9: 5 | B9: 0 – 19,99% | C9: ⬛ ████ | D9: RUPTURA TOTAL | E9: Inexistencia de gestión técnica programática. Opacidad administrativa. Fragmentación sistémica. Sin evidencia documental. Incumplimiento total de las metas PDOT.
A11: 📍 SECCIÓN B — RESULTADO APLICADO AL GAD Montecristi 2023 · Posicionamiento en la escala · §3.6–§3.8
A12: MÉTRICA | B12: VALOR | C12: NIVEL | D12: CATEGORÍA ASIGNADA | E12: IMPLICACIÓN TÉCNICA / ACCIÓN
A13: ICPI CALCULADO · GAD Montecristi 2024
A14: META PDOT 2027 (benchmark primario)
A15: BRECHA ICPI vs Meta PDOT 2027 · UAP · §3.6
A16: ICPI POTENCIAL · Con regularización Vi=0 · §3.4
A17: 🎨 SECCIÓN C — PALETA CANÓNICA INAMOVIBLE · SIAP-ICPI §3.7 p.17 · ⚠️ PROHIBIDO MODIFICAR COLORES — REFERENCIA Única MAESTRA PARA TODAS LAS PESTANAS DEL INSTRUMENTO · bg / texto / borde son INMUTABLES
A18: NIVEL (§3.7) | B18: RANGO ICPI (§3.7 p.17) | C18: COLOR SEMÁFORO | D18: bg / texto / borde — EXACTOS ⚠️ INAMOVIBLES | E18: APLICA EN (REFERENCIA MAESTRA)
A19: 1 — EXCELENCIA | B19: 85 – 100% | C19: 🔵 AZUL | D19: bg: #0D1F3C · texto: #4FC3F7 · borde: #0070C0 | E19: DASHBOARD · RESUMEN · EJES Niv.1 · SENSI escenario óptimo · EDS · ALERTAS
A20: 2 — GESTIÓN POR MANDATO | B20: 70 – 84,99% | C20: 🟢 VERDE | D20: bg: #071A0A · texto: #00E676 · borde: #00B050 | E20: PDOT Vi=1 Ti≥70% · MVCI congruente · SENSI potencial · BRECHA Ti<umbral · EDS · ALERTAS
A21: 3 — TRANSICIÓN CRÍTICA ◄ GAD MONTECRISTI
A22: 4 — GESTIÓN POR OCURRENCIA | B22: 20 – 39,99% | C22: 🔴 ROJO | D22: bg: #1A0000 · texto: #FF1744 · borde: #FF0000 | E22: BRECHA brechas graves · MVCI Vi=0 parcial · POA urgencia ALTA · BI discrepancia grave · ALERTAS
A23: 5 — RUPTURA TOTAL

Sheet VALID-CST
A1: QUADRUM v1.0 · VALID-CST · Validación de Consistencia Metodológica y Flujos de Datos
A2: =HYPERLINK("#'M-INDEX'!A1","⌂ INDICE") -> ⌂ INDICE | B2: =HYPERLINK("#'M1-ITME'!A1","M1") -> M1 | C2: =HYPERLINK("#'M2-PDOT'!A1","M2") -> M2 | D2: =HYPERLINK("#'M3-MAO'!A1","M3") -> M3 | E2: =HYPERLINK("#'M4-AUDIT'!A1","M4") -> M4 | F2: =HYPERLINK("#'M5-ICPI'!A1","M5") -> M5 | G2: =HYPERLINK("#'M6-FEDS'!A1","M6") -> M6 | H2: =HYPERLINK("#'M7-PROSP'!A1","M7") -> M7 | I2: =HYPERLINK("#'DATA-POA'!A1","DATA-POA") -> DATA-POA | J2: =HYPERLINK("#'DATA-CNE'!A1","DATA-CNE") -> DATA-CNE | K2: =HYPERLINK("#'DATA-ORG'!A1","DATA-ORG") -> DATA-ORG | L2: =HYPERLINK("#'M-DASHBOARD'!A1","DASH") -> DASH
A3: Capa: Motor ICPI > Verificación de Consistencia del Modelo · Control de Calidad Aritmética
A4: 🔷 CONSISTENCIA INTERNA · Controles: PDOT-PONDER-MAD-ICPI · Alertas de discrepancia
A5: Numerador · Σ(Pi × Ri × Vi × Ei × Ti × Ci)
A6: Denominador · Σ(Pi × Ri) | B6: ='M5-ICPI'!H25 -> 1.0682671 | C6: Suma total del potencial máximo de todas las metas (sin restricción Vi). Normaliza el ICPI a escala 0–1. Fórmula: Σ(Pi·Ri) §3.7
A7: ICPI FINAL · Resultado del Algoritmo · §3.7
A9: 🔍 SECCIÓN B — VERIFICACIÓN CRUZADA (SENTIDO COMÚN) · Comprobaciones indes del ICPI · §3.4–§3.5
A10: VARIABLE DE CONTROL | B10: HALLAZGO | C10: INTERPRETACIÓN / IMPLICACIÓN
A11: Metas con Evidencia Documental (Vi = 1)
A12: Inversión con Trazabilidad (Vi = 1)
A13: Metas Completadas (Vi=1 · Ti=1)
A14: Metas con Evidencia Parcial (Vi=1 · Ti<1)
A15: Metas Sin Evidencia Documental (Vi = 0)
A16: Avance Prom. Ejecución (Ti · solo Vi=1)
A17: Consistencia Numerador/Denominador
A19: 📋 SECCIÓN C — INTERPRETACIÓN FINAL DEL ICPI · Diagnóstico sistémico · §3.8 SIAP-ICPI
A20: 📊 NIVEL ICPI · Categoría del resultado
A21: 📋 DESGLOSE DE LAS 20 METAS PDOT · Estado documental
A22: 🔴 BRECHA ICPI vs Meta PDOT 2027 · UAP §3.6 · Umbral de Alerta Programática
A23: ⚡ ACCIÓN DE MAYOR IMPACTO · POA 2025
A25: ✅ SECCIÓN D — CONCLUSIONES DE CONSISTENCIA · Tres hallazgos principales · §3.7–§3.9
A26: VARIABLE DE CONTROL | B26: HALLAZGO | C26: INTERPRETACIÓN / IMPLICACIÓN
A27: ⚠️ DÉFICIT PROGRAMÁTICO CONFIRMADO · §3.6 · ICPI(41,53%) < ICM-SIGAD(92,25%) — Brecha de 50,72pp — H₁ CONFIRMADA
A28: CONSISTENCIA INTERNA ✅ — Numerador y denominador verificados · §3.7
A29: ALERTA CRÍTICA — 40% metas sin trazabilidad documental (Vi=0) · §3.4

Sheet M7-PROSP
A1: QUADRUM v1.0 · M7-PROSP · Análisis Analítico Cruzado · Cuadrante Prospectivo · GAD Municipal Montecristi
A2: =HYPERLINK("#'M-INDEX'!A1","⌂ INDICE") -> ⌂ INDICE | B2: =HYPERLINK("#'M1-ITME'!A1","M1") -> M1 | C2: =HYPERLINK("#'M2-PDOT'!A1","M2") -> M2 | D2: =HYPERLINK("#'M3-MAO'!A1","M3") -> M3 | E2: =HYPERLINK("#'M4-AUDIT'!A1","M4") -> M4 | F2: =HYPERLINK("#'M5-ICPI'!A1","M5") -> M5 | G2: =HYPERLINK("#'M6-FEDS'!A1","M6") -> M6 | H2: =HYPERLINK("#'M7-PROSP'!A1","◉ M7-PROSP") -> ◉ M7-PROSP | I2: =HYPERLINK("#'DATA-POA'!A1","DATA-POA") -> DATA-POA | J2: =HYPERLINK("#'DATA-CNE'!A1","DATA-CNE") -> DATA-CNE | K2: =HYPERLINK("#'DATA-ORG'!A1","DATA-ORG") -> DATA-ORG | L2: =HYPERLINK("#'M-DASHBOARD'!A1","DASH") -> DASH
A3: Capa: Operación > Analítica de Datos ICPI · Procesamiento Estadístico y Tendencias
A4: 🔷 TABLERO BI · KPIs dinámicos · ICPI = 41.53% · Tendencia 2023-2027 · SIAP-ICPI
A5: # | B5: CÓD. PDOT | C5: Ti ACTUAL | D5: Vi | E5: BRECHA Ti | F5: RIESGO | G5: CONSISTENCIA | H5: DIAGNÓSTICO
A6: 2 | B6: PDOT.AS.OE1.M1.02 | C6: 0.75 | D6: 1 | E6: =C6-D6 -> -0.25 | F6: MÍNIMA | G6: CONGRUENTE | H6: Alcantarillado · Ti=75% vs Meta 100% 2027 · Brecha -25pp. Activar contrato BDE-PROGAPSA Fase I en POA 2025.
A7: 3 | B7: PDOT.SC.OE2.M1.01 | C7: 0 | D7: 1 | E7: =C7-D7 -> -1 | F7: CRÍTICA | G7: DISCREPANCIA | H7: 🚨 Centro Salud Tipo C · Vi=0 · Ti=15% vs Meta 100% 2027 · Brecha crítica -85pp. Firmar convenio MSP + SERCOP urgente.
A8: 4 | B8: PDOT.AS.OE1.M2.01 | C8: 0.45 | D8: 1 | E8: =C8-D8 -> -0.55 | F8: GRAVE | G8: DISCREPANCIA | H8: Terminal Terrestre · Ti=45% vs Meta 100% 2027 · Brecha -55pp. Incluir estudios factibilidad en POA 2025 con SERCOP.
A9: 5 | B9: PDOT.AS.OE1.M2.02 | C9: 0 | D9: 1 | E9: =C9-D9 -> -1 | F9: CRÍTICA | G9: DISCREPANCIA | H9: 🚨 Camal Municipal · Vi=0, Ti=0 · Brecha -100pp vs Meta 2027. Levantar informe viabilidad técnica urgente.
A10: 6 | B10: PDOT.SC.OE2.M2.01 | C10: 1 | D10: 1 | E10: =C10-D10 -> 0 | F10: MÍNIMA | G10: CONGRUENTE | H10: ✅ Geriátrico · Ti=100% · Meta PDOT cumplida. Incluir operación recurrente en POA 2025; vincular indicador PDOT.
A11: 7 | B11: PDOT.AS.VL.M1.01 | C11: 0.9 | D11: 1 | E11: =C11-D11 -> -0.1 | F11: LEVE | G11: DISCREPANCIA | H11: Bacheo/Vialidad · Ti=90% vs Meta 100% 2027 · Brecha -10pp. Establecer meta km en POA 2025; vincular indicador IE.
A12: 8 | B12: PDOT.SC.OE2.M3.01 | C12: 0 | D12: 1 | E12: =C12-D12 -> -1 | F12: CRÍTICA | G12: DISCREPANCIA | H12: 🚨 Unidad Médica · Vi=0 · Ti=50% vs Meta 100% 2027 · Brecha -50pp. Registrar vehículo SERCOP; contrato formal.
A13: 9 | B13: PDOT.AM.OE3.M1.01 | C13: 0.36 | D13: 1 | E13: =C13-D13 -> -0.64 | F13: GRAVE | G13: DISCREPANCIA | H13: PTAR · Ti=40% vs Meta 100% 2027 · Brecha -60pp. Gestionar financiamiento no reembolsable PTAR en POA 2025.
A14: 10 | B14: PDOT.AV.OE1.M1.01 | C14: 0.5 | D14: 1 | E14: =C14-D14 -> -0.5 | F14: GRAVE | G14: DISCREPANCIA | H14: Parques/Áreas Verdes · Ti=50% vs Meta 100% 2027 · Brecha -50pp. Diseño + obra Parque Pampas Fase I en POA 2025.
A15: 11 | B15: PDOT.SC.OE2.M4.01 | C15: 0 | D15: 1 | E15: =C15-D15 -> -1 | F15: CRÍTICA | G15: DISCREPANCIA | H15: 🚨 Guarderías · Vi=0, Ti=0 · Brecha -100pp vs Meta 2027. Reformular como programa protección; convenio MIES urgente.
A16: 12 | B16: PDOT.AM.OE3.M2.01 | C16: 0.27 | D16: 1 | E16: =C16-D16 -> -0.73 | F16: GRAVE | G16: DISCREPANCIA | H16: Planta Desechos · Ti=30% vs Meta 100% 2027 · Brecha -70pp. Proceso MAATE regularización en POA 2025.
A17: 13 | B17: PDOT.AS.VL.M1.02 | C17: 1 | D17: 1 | E17: =C17-D17 -> 0 | F17: NULA | G17: CONGRUENTE | H17: ✅ Maquinaria · Ti=100% · Meta PDOT cumplida. Programar mantenimiento preventivo; vincular km al indicador IE PDOT.
... A24: 20 | B24: PDOT.AS.OE1.M1.03 | C24: 0.25 | D24: 0.1 | E24: =C24-D24 -> 0.15 | F24: CRÍTICA | G24: DISCREPANCIA | H24: Reservorios Agua · Ti=25% vs Meta 10% 2027 · ✅ Ti supera meta relativa. Diseño definitivo reservorios rurales POA 2025.
A25: — | B25: Σ PROMEDIO · n=20 | C25: =AVERAGE(C4:C24) -> 0.46157895 | D25: 0.9375 | E25: =AVERAGE(E6:E24) -> -0.46736842 | F25: CRÍTICA | G25: BRECHA GLOBAL | H25: ICPI actual vs Meta PDOT 2027 → Brecha promedio calculada. 5 metas ya cumplidas. 4 con brecha crítica (Vi=0, Ti=0).
A27: 📊 SECCIÓN B — CLASIFICACIÓN DE BRECHAS POR MAGNITUD · Semáforo de Integridad ICPI vs Meta PDOT 2027 · §3.6 SIAP-ICPI
A28: 📊 SECCIÓN B — CLASIFICACIÓN DE BRECHAS POR MAGNITUD · ICPI vs Meta PDOT 2027 · §3.6 SIAP-ICPI
A29: ✅ CONGRUENTE / NULA | B29: ICPI ≈ Meta PDOT (|Δ| ≤ 10 pp). Meta casi cumplida al 2027. | C29: 5 | D29: 0.79 | E29: 0.93 | F29: −0.02 pp | G29: TER-01 · INS-05 · TER-18 · SOC-03 · TER-03 | H29: RECOMENDACIÓN POA 2025
A30: ✅ EN CAMINO | B30: Ti ≥ Meta PDOT 2027 (Δ ≥ 0). Avance supera o iguala la meta comprometida | C30: 5 | D30: 0.79 | E30: 0.92 | F30: 0 | G30: TER-01 · INS-05 · TER-18 · SOC-03 · TER-14 | H30: ✅ Mantener ritmo — buenas prácticas replicables
A31: 🟡 REZAGO LEVE | B31: Ti entre 70-99% de Meta PDOT (Δ −1 a −30pp). En camino pero requiere acelerar | C31: 3 | D31: 0.78 | E31: 1 | F31: -0.23 | G31: TER-03 · TER-02 · INS-03 | H31: ⚡ Plan aceleración — incluir hitos trimestrales en POA 2025
A32: 🟠 REZAGO GRAVE | B32: Ti entre 20-69% de Meta PDOT (Δ −31 a −80pp). Riesgo real de no cumplir al 2027 | C32: 8 | D32: 0.37 | E32: 1 | F32: -0.63 | G32: AMB-07 · TER-05 · SOC-08 · ECO-12 · AMB-08 · TER-09 · TER-15 · SOC-07 | H32: 🔴 Auditoría y plan recuperación — priorizar en POA 2025 con recursos específicos
A33: 🔴 CRÍTICO | B33: Ti = 0 o Vi=0 · Meta PDOT 2027 = 100% · Brecha −100pp. Sin inicio real | C33: 4 | D33: 0 | E33: 1 | F33: -1 | G33: SOC-02 · TER-10 · SOC-04 · SOC-15 | H33: 🚨 URGENTE — Inicio proceso formal · Convenios · SERCOP · Auditoría documental

Sheet VALID-MVCI
A1: QUADRUM v1.0 · VALID-MVCI · Matriz de Verificación de Coherencia Interna · 20/20
A2: =HYPERLINK("#'M-INDEX'!A1","⌂ INDICE") -> ⌂ INDICE | B2: =HYPERLINK("#'M1-ITME'!A1","M1") -> M1 | C2: =HYPERLINK("#'M2-PDOT'!A1","M2") -> M2 | D2: =HYPERLINK("#'M3-MAO'!A1","M3") -> M3 | E2: =HYPERLINK("#'M4-AUDIT'!A1","M4") -> M4 | F2: =HYPERLINK("#'M5-ICPI'!A1","M5") -> M5 | G2: =HYPERLINK("#'M6-FEDS'!A1","M6") -> M6 | H2: =HYPERLINK("#'M7-PROSP'!A1","M7") -> M7 | I2: =HYPERLINK("#'DATA-POA'!A1","DATA-POA") -> DATA-POA | J2: =HYPERLINK("#'DATA-CNE'!A1","DATA-CNE") -> DATA-CNE | K2: =HYPERLINK("#'DATA-ORG'!A1","DATA-ORG") -> DATA-ORG | L2: =HYPERLINK("#'M-DASHBOARD'!A1","DASH") -> DASH
A3: Capa: Operación > Matriz de Verificación de Cumplimiento Institucional · SIAP-ICPI §4.5
A4: 🔷 VARIABLES CONTROL Ei · n=20 metas · Ei pondera factores de contexto institucional
A5: # | B5: CÓD. PDOT | C5: PRESUP. ($) | D5: Ri | E5: Vi | F5: Pi | G5: Ri×Pi | H5: Pi NORM. | I5: Ti | J5: CONTROL Ei | K5: DIAGNÓSTICO | L5: Ci ESTADO
A6: 2 | B6: PDOT.AS.OE1.M1.02 | C6: 1269859 | D6: 1.5 | E6: =IFERROR(VLOOKUP(B6,'M4-AUDIT'!$A$5:$H$24,MATCH("Vi",'M4-AUDIT'!$A$4:$H$4,0),0),0) -> 0 | F6: ='M2-PLAN-Pi'!F14 -> 0.33155843 | G6: 1.5 | H6: 0.3643 | I6: =IFERROR(VLOOKUP(B6,'M4-AUDIT'!$A$5:$H$24,MATCH("Ti (H)",'M4-AUDIT'!$A$4:$H$4,0),0),0) -> 0 | J6: =IF(E6=1,IF(I6>=0.8,"OK Vi=1 Ti="&TEXT(I6,"0.00"),IF(I6>=0.5,"OK- Vi=1 Ti="&TEXT(I6,"0.00"),"WARN Vi=1 Ti="&TEXT(I6,"0.00"))),"CRIT Vi=0 Ti="&TEXT(I6,"0.00")) -> CRIT Vi=0 Ti=000 | K6: CONGRUENTE ✓ — Alcantarillado BEI-PROGAPSA. Ti=0.75. RDC 2023+2024 verificado §3.4 | L6: =IF(ISNUMBER(VLOOKUP(B6,'M3-MAO'!$A$3:$G$23,7,0)),IF(VLOOKUP(B6,'M3-MAO'!$A$3:$G$23,7,0)=1,"✅ Ci=1.0 — GAD directo","⚠ Ci="&VLOOKUP(B6,'M3-MAO'!$A$3:$G$23,7,0)&" — adscrito/convenio"),"❌ Sin Ci") -> ✅ Ci=1.0 — GAD directo
A7: 3 | B7: PDOT.SC.OE2.M1.01 | C7: 1693800 | D7: 1.5 | E7: =IFERROR(VLOOKUP(B7,'M4-AUDIT'!$A$5:$H$24,MATCH("Vi",'M4-AUDIT'!$A$4:$H$4,0),0),0) -> 1 | F7: ='M2-PLAN-Pi'!F15 -> 0.17737919 | G7: 1.5 | H7: 0.3188 | I7: =IFERROR(VLOOKUP(B7,'M4-AUDIT'!$A$5:$H$24,MATCH("Ti (H)",'M4-AUDIT'!$A$4:$H$4,0),0),0) -> 0.65 | J7: =IF(E7=1,IF(I7>=0.8,"OK Vi=1 Ti="&TEXT(I7,"0.00"),IF(I7>=0.5,"OK- Vi=1 Ti="&TEXT(I7,"0.00"),"WARN Vi=1 Ti="&TEXT(I7,"0.00"))),"CRIT Vi=0 Ti="&TEXT(I7,"0.00")) -> OK- Vi=1 Ti=001 | K7: ⚠ Vi=0 — Centro Salud Tipo C. Sin convenio MSP. CRÍTICO: +20.6 pp potencial §3.4 | L7: =IF(ISNUMBER(VLOOKUP(B7,'M3-MAO'!$A$3:$G$23,7,0)),IF(VLOOKUP(B7,'M3-MAO'!$A$3:$G$23,7,0)=1,"✅ Ci=1.0 — GAD directo","⚠ Ci="&VLOOKUP(B7,'M3-MAO'!$A$3:$G$23,7,0)&" — adscrito/convenio"),"❌ Sin Ci") -> ⚠ Ci=0,9 — adscrito/convenio
